Workbook

Sheet INPUTS
A1: GASQ MOBILE PATROL HIT SERVICE CALCULATOR
A2: Buyer / Site Inputs
A3: Site Name | B3: Demo Property
A4: Service Type | B4: Park & Walk Thru Check | C4: Dropdown: Drive By Check, Park & Walk Thru Check, Park & Make Contact Check
A5: Weekly Checks | B5: 84 | C5: Dropdown: 21, 28, 42, 56, 84
A6: Weeks Per Year | B6: 52 | C6: Dropdown: 1–52 weeks
A7: Checks Per Day | B7: =B5/7 -> 12 | C7: Auto from Weekly Checks
A8: Average Minutes On Site Per Check | B8: 15
A9: Average Travel / Dispatch Minutes Per Check | B9: 10
A10: Total Billable Minutes Per Check | B10: =B8+B9 -> 25 | C10: Auto
A11: Labor & Operating Cost Inputs
A12: Officer Pay Rate Per Hour | B12: 25
A13: Payroll Burden % | B13: 0.3
A14: Fully Burdened Labor Rate | B14: =B12*(1+B13) -> 32.5 | C14: Auto
A15: Vehicle Cost Per Hour | B15: 6.5
A16: Fuel Cost Per Hour | B16: 2.25
A17: Equipment / Technology Cost Per Hour | B17: 1.75
A18: Supervision / Admin Cost Per Hour | B18: 4
A19: Total Operating Cost Per Hour | B19: =SUM(B14:B18) -> 47 | C19: Auto
A20: Pricing Inputs
A21: Overhead % | B21: 0.1
A22: G&A % | B22: 0.1
A23: Profit / Markup % | B23: 0.1
A24: Minimum Charge Per Check | B24: 23
A25: Add-On Cost Per Check | B25: 0 | C25: Optional fixed add-on cost per patrol check
A26: Output Totals
A27: Total Weekly Checks | B27: =B5 -> 84 | C27: Auto
A28: Total Monthly Checks | B28: =B27*B6/12 -> 364 | C28: Auto based on weeks per year
A29: Total Annual Checks | B29: =B27*B6 -> 4368 | C29: Auto based on weeks per year
A30: Total Weekly Cost | B30: =CALCULATIONS!B15 -> 2171.4 | C30: Auto
A31: Total Monthly Cost | B31: =CALCULATIONS!B16 -> 9409.4 | C31: Auto based on weeks per year
A32: Total Annual Cost | B32: =CALCULATIONS!B17 -> 112912.8 | C32: Auto based on weeks per year

Sheet CALCULATIONS
A1: CALCULATION ENGINE
A2: Hours Per Check | B2: =INPUTS!B10/60 -> 0.41666667
A3: Base Cost Per Check | B3: =B2*INPUTS!B19 -> 19.583333
A4: Overhead Amount Per Check | B4: =B3*INPUTS!B21 -> 1.9583333
A5: G&A Amount Per Check | B5: =B3*INPUTS!B22 -> 1.9583333
A6: Subtotal Cost Per Check | B6: =B3+B4+B5 -> 23.5
A7: Add-On Cost Per Check | B7: =INPUTS!B25 -> 0
A8: Pre-Markup Cost Per Check | B8: =B6+B7 -> 23.5
A9: Profit Amount Per Check | B9: =B8*INPUTS!B23 -> 2.35
A10: Calculated Sell Price Per Check | B10: =B8+B9 -> 25.85
A11: Final Sell Price Per Check | B11: =MAX(B10,INPUTS!B24) -> 25.85
A12: Total Weekly Checks | B12: =INPUTS!B27 -> 84
A13: Total Monthly Checks | B13: =INPUTS!B28 -> 364
A14: Total Annual Checks | B14: =INPUTS!B29 -> 4368
A15: Total Weekly Cost | B15: =B11*B12 -> 2171.4
A16: Total Monthly Cost | B16: =B15*INPUTS!B6/12 -> 9409.4
A17: Total Annual Cost | B17: =B15*INPUTS!B6 -> 112912.8
A18: Gross Profit Per Check | B18: =B11-B8 -> 2.35
A19: Profit Margin % | B19: =IFERROR(B18/B11,0) -> 0.090909091

Sheet RESULTS DASHBOARD
A1: GASQ MOBILE PATROL PRICING DASHBOARD
A3: Service Type | B3: =INPUTS!B4 -> Park & Walk Thru Check | D3: Total Weekly Cost | E3: Total Monthly Cost | F3: Total Annual Cost
A4: Weekly Checks | B4: =CALCULATIONS!B12 -> 84 | D4: =CALCULATIONS!B15 -> 2171.4 | E4: =CALCULATIONS!B16 -> 9409.4 | F4: =CALCULATIONS!B17 -> 112912.8
A5: Weeks Per Year | B5: =INPUTS!B6 -> 52 | D5: Total Weekly Checks | E5: Total Monthly Checks | F5: Total Annual Checks
A6: Checks Per Day | B6: =INPUTS!B7 -> 12 | D6: =CALCULATIONS!B12 -> 84 | E6: =CALCULATIONS!B13 -> 364 | F6: =CALCULATIONS!B14 -> 4368
A7: Total Monthly Checks | B7: =CALCULATIONS!B13 -> 364
A8: Total Annual Checks | B8: =CALCULATIONS!B14 -> 4368
A9: Final Price Per Check | B9: =CALCULATIONS!B11 -> 25.85
A10: Profit Margin | B10: =CALCULATIONS!B19 -> 0.090909091
A12: Cost Category | B12: Per Check | C12: Weekly | D12: Monthly | E12: Annual | F12: Notes
A13: Pre-Markup Cost | B13: =CALCULATIONS!B8 -> 23.5 | C13: =B13*CALCULATIONS!B12 -> 1974 | D13: =C13*INPUTS!B6/12 -> 8554 | E13: =C13*INPUTS!B6 -> 102648 | F13: Cost before profit
A14: Profit Amount | B14: =CALCULATIONS!B9 -> 2.35 | C14: =B14*CALCULATIONS!B12 -> 197.4 | D14: =C14*INPUTS!B6/12 -> 855.4 | E14: =C14*INPUTS!B6 -> 10264.8 | F14: Target profit
A15: Final Sell Price | B15: =CALCULATIONS!B11 -> 25.85 | C15: =B15*CALCULATIONS!B12 -> 2171.4 | D15: =C15*INPUTS!B6/12 -> 9409.4 | E15: =C15*INPUTS!B6 -> 112912.8 | F15: Client-facing price
A16: Base Cost | B16: =CALCULATIONS!B3 -> 19.583333 | C16: =B16*CALCULATIONS!B12 -> 1645 | D16: =C16*INPUTS!B6/12 -> 7128.3333 | E16: =C16*INPUTS!B6 -> 85540 | F16: Labor + operating cost
A17: Overhead | B17: =CALCULATIONS!B4 -> 1.9583333 | C17: =B17*CALCULATIONS!B12 -> 164.5 | D17: =C17*INPUTS!B6/12 -> 712.83333 | E17: =C17*INPUTS!B6 -> 8554 | F17: Overhead allocation
A18: G&A | B18: =CALCULATIONS!B5 -> 1.9583333 | C18: =B18*CALCULATIONS!B12 -> 164.5 | D18: =C18*INPUTS!B6/12 -> 712.83333 | E18: =C18*INPUTS!B6 -> 8554 | F18: G&A allocation
A19: Add-Ons | B19: =CALCULATIONS!B7 -> 0 | C19: =B19*CALCULATIONS!B12 -> 0 | D19: =C19*INPUTS!B6/12 -> 0 | E19: =C19*INPUTS!B6 -> 0 | F19: Optional services

Sheet PDF REPORT
A1: GASQ MOBILE PATROL HIT SERVICE PDF REPORT
A3: Client / Site | B3: Service Type | C3: Weekly Checks | D3: Weeks Per Year | E3: Price Per Check | F3: Annual Cost
A4: =INPUTS!B3 -> Demo Property | B4: =INPUTS!B4 -> Park & Walk Thru Check | C4: =INPUTS!B27 -> 84 | D4: =INPUTS!B6 -> 52 | E4: =CALCULATIONS!B11 -> 25.85 | F4: =CALCULATIONS!B17 -> 112912.8
B5: =INPUTS!B4 -> Park & Walk Thru Check
A6: Pricing Summary
A8: Total Weekly Checks | B8: =INPUTS!B27 -> 84
A9: Total Monthly Checks | B9: =INPUTS!B28 -> 364
A10: Total Annual Checks | B10: =INPUTS!B29 -> 4368
A11: Total Weekly Cost | B11: =INPUTS!B30 -> 2171.4
A12: Total Monthly Cost | B12: =INPUTS!B31 -> 9409.4
A13: Total Annual Cost | B13: =INPUTS!B32 -> 112912.8
A14: Profit Margin | B14: =CALCULATIONS!B19 -> 0.090909091
A16: Executive Narrative
A17: =CONCATENATE("This mobile patrol estimate is based on ",INPUTS!B27," weekly checks over ",INPUTS!B6," weeks per year. The selected service type is ",INPUTS!B4,". Total costs adjust automatically when weeks per year changes from 1 to 52.") -> This mobile patrol estimate is based on 84 weekly checks over 52 weeks per year. The selected service type is Park & Walk Thru Check. Total costs adjust automatically when weeks per year changes from 1 to 52.
A18: Created in collaboration with the GASQ AI Team

Sheet WEEKLY CHECKS GUIDE
A1: WEEKLY CHECK DEFINITIONS
A3: Weekly Checks | B3: Frequency | C3: Plain-English Definition
A4: 21 | B4: Every 8 hours | C4: 3 checks per day or 1 check per 8-hour shift; 7 days per week
A5: 28 | B5: Every 6 hours | C5: 4 checks per day; 7 days per week
A6: 42 | B6: Every 4 hours | C6: 6 checks per day or 2 checks per 8-hour shift; 7 days per week
A7: 56 | B7: Every 3 hours | C7: 8 checks per day; 7 days per week
A8: 84 | B8: Every 2 hours | C8: 12 checks per day or 4 checks per 8-hour shift; 7 days per week

Sheet SETTINGS
A1: GASQ MOBILE PATROL SETTINGS
C2: Weekly Checks | D2: Checks Per Day
A3: Drive By Check | C3: 21 | D3: 3
A4: Park & Walk Thru Check | C4: 28 | D4: 4
A5: Park & Make Contact Check | C5: 42 | D5: 6
C6: 56 | D6: 8
C7: 84 | D7: 12
