Workbook

Sheet Start_Here
A1: GASQ Workforce-to-Post™ Model
A2: Enter data only in highlighted cells. All formulas, dashboards, and client-facing reports are protected.
A4: Recommended workflow | D4: Editing rules | G4: Live model KPIs
A5: 1. Inputs | B5: Open Inputs | D5: Editable input cells | E5: Type only in highlighted cells | G5: Annual Coverage Hours | H5: =Appraisal_Full_Scope_Report!F15 -> 17472
A6: 2. Post roster | B6: Open Post_Positions | D6: Locked formula/report cells | E6: Protected | G6: Service Requster TCO / Hr | H6: =Appraisal_Full_Scope_Report!F8 -> 129.97639
A7: 3. Vendor pricing | B7: Open Vendor_Pricing | D7: Protection password | E7: GASQ | G7: Vendor TCO / Hr | H7: =Appraisal_Full_Scope_Report!H8 -> 90.983473
A8: 4. CLIN pricing | B8: Open CLIN Pricing | G8: Annual Capital Recovery | H8: =Appraisal_Full_Scope_Report!H20 -> 681284.25
A9: 5. Contract summary | B9: Open Contract_Summary
A10: 6. Dashboards | B10: Open GASQ_Dashboard | G10: Visible user tabs
A11: 7. Reports | B11: Open Appraisal Report | G11: • Inputs
A12: 8. Buyer report | B12: Open Buyer_Executive_Report | G12: • Post_Positions
A13: 9. Automation guide | B13: Open Automation_Guide | G13: • Vehicle
G14: • Uniform_Equipment
A15: Buyer PDF shortcut | G15: • Training_Module
A16: OPEN BUYER REPORT TAB (click here) | E16: OPEN AUTOMATION GUIDE (click here)
A19: PDF export reminder | G19: • Vendor_Pricing
A20: The buyer PDF is exported from the Buyer_Executive_Report tab. In Excel: File → Export / Save As → PDF. For a Windows one-click exporter, use the included Export_Buyer_Report.vbs script in the same folder as this workbook.
G23: • Capital_Recovery_Receipt
G24: • Vendor_Price_Evaluation
G25: • Government_IGCE_Comparison
G26: • Capital_Recovery_Dashboard
G27: • GASQ_Dashboard
G28: • Direct_Labor
G29: • Fringe_Costs

Sheet Buyer_Executive_Report
A1: GASQ Buyer Executive Report
A2: Automated buyer-facing summary linked live to Direct_Labor, Summary, Appraisal_Full_Scope_Report, and Vendor_Pricing. Update inputs, recalculate, and export this sheet to PDF.
F3: Setup one-click export
A4: Executive KPIs
A5: Annual Coverage Hours | B5: =Summary!$B$4 -> 17472 | C5: FTEs Required | D5: =Summary!$B$5 -> 12 | E5: Service Requester TCO / Hr | F5: =Summary!$B$6 -> 129.97639 | G5: Annual Service Requester TCO | H5: =Summary!$B$7 -> 2270947.5
A7: Vendor TCO / Hr | B7: =Summary!$B$9 -> 90.983473 | C7: Vendor BAFO / Hr | D7: =Summary!$B$11 -> 77.335952 | E7: Capital Recovery Opportunity ($/Hr) | F7: =Summary!$B$13 -> 38.992917 | G7: Annual Service Requester Savings ($/Year) | H7: =Summary!$B$16 -> 681284.25
A8: Payback Period (Months) | B8: =Appraisal_Full_Scope_Report!$H$22 -> 8.4
A10: Direct Labor Cost Stack
A11: Component | B11: Annual Cost | C11: % of Vendor Stack | D11: Notes
A12: Direct Labor | B12: =Direct_Labor!$D$11 -> 732597.47 | C12: =IFERROR(B12/$B$16,0) -> 0.48242356 | D12: Core productive labor
A13: Fringe & Burden | B13: =Direct_Labor!$D$25 -> 150548.78 | C13: =IFERROR(B13/$B$16,0) -> 0.099138042 | D13: Payroll taxes and paid time off
A14: Operations & Support | B14: =Direct_Labor!$D$40 -> 169734.22 | C14: =IFERROR(B14/$B$16,0) -> 0.11177186 | D14: Training, equipment, vehicles, and insurance
A15: Overhead / G&A / Profit | B15: =Direct_Labor!$D$50 -> 465696.82 | C15: =IFERROR(B15/$B$16,0) -> 0.30666653 | D15: Corporate overhead, G&A, and profit
A16: Total Vendor Labor Stack | B16: =Direct_Labor!$D$52 -> 1518577.3 | C16: =IFERROR(B16/$B$16,0) -> 1 | D16: Vendor fully burdened labor cost stack
A19: Buyer vs Vendor Scenario Comparison
A20: Metric | B20: Buyer / Gov | C20: Vendor TCO | D20: Vendor BAFO/LPTA Target | E20: Vendor LPTA
A21: Annual Coverage Hours | B21: =Summary!$B$4 -> 17472 | C21: =Summary!$B$4 -> 17472 | D21: =Summary!$B$4 -> 17472 | E21: =Summary!$B$4 -> 17472
A22: Rate / Productive Hour | B22: =Summary!$B$6 -> 129.97639 | C22: =Summary!$B$9 -> 90.983473 | D22: =Summary!$B$11 -> 77.335952 | E22: =Summary!$B$10 -> 63.688431
A23: Annual Total Cost | B23: =Summary!$B$7 -> 2270947.5 | C23: =Appraisal_Full_Scope_Report!$H$19 -> 1589663.2 | D23: =D21*D22 -> 1351213.8 | E23: =E21*E22 -> 1112764.3
A24: Hourly Savings vs Buyer | B24: =0 -> 0 | C24: =B22-C22 -> 38.992917 | D24: =B22-D22 -> 52.640438 | E24: =B22-E22 -> 66.287959
A25: Annual Savings / Capital Recovery | B25: =0 -> 0 | C25: =B23-C23 -> 681284.25 | D25: =B23-D23 -> 919733.73 | E25: =B23-E23 -> 1158183.2
A26: Savings % vs Buyer | B26: =0 -> 0 | C26: =IFERROR(C25/B23,0) -> 0.3 | D26: =IFERROR(D25/B23,0) -> 0.405 | E26: =IFERROR(E25/B23,0) -> 0.51
A28: Auto-Generated Buyer Takeaways
A29: ="Direct labor represents "&IFERROR(TEXT(C12,"0.0%"),"-")&" of the vendor fully burdened labor stack." -> Direct labor represents 48.2% of the vendor fully burdened labor stack.
A30: ="Vendor TCO pricing lowers annual buyer spend by "&IFERROR(TEXT(H7,"$#,##0"),"-")&" per year compared with the buyer should-cost benchmark." -> Vendor TCO pricing lowers annual buyer spend by $681,284 per year compared with the buyer should-cost benchmark.
A31: ="Capital recovery opportunity equals "&IFERROR(TEXT(F7,"$0.00"),"-")&" per hour and "&IFERROR(TEXT(H7,"$#,##0"),"-")&" per year." -> Capital recovery opportunity equals $38.99 per hour and $681,284 per year.
A32: ="The buyer should-cost benchmark is "&IFERROR(TEXT(F5,"$0.00"),"-")&" per productive hour versus vendor TCO of "&IFERROR(TEXT(B7,"$0.00"),"-")&"." -> The buyer should-cost benchmark is $129.98 per productive hour versus vendor TCO of $90.98.
A34: This report updates automatically from the linked model tabs. Recalculate in Excel before exporting if you change inputs.

Sheet Automation_Guide
A1: Automation Guide
A2: This workbook includes a buyer report tab plus ready-to-use export scripts. Use the workbook on desktop Excel for best results.
A4: Step | B4: Action | C4: Details
A5: 1 | B5: Open the workbook | C5: Use desktop Excel. The Buyer_Executive_Report tab is moved near the front and colored burgundy.
A6: 2 | B6: Update inputs | C6: Edit the blue / designated input cells on Inputs, Post_Positions, Vendor_Pricing, and related modules.
A7: 3 | B7: Review the report | C7: Open Buyer_Executive_Report and confirm KPIs, cost stack, and comparison values.
A8: 4 | B8: Manual PDF export | C8: In Excel: File → Export / Save As → PDF. Export only Buyer_Executive_Report.
A9: 5 | B9: Windows one-click export | C9: Put Export_Buyer_Report.vbs in the same folder as this workbook, then double-click the script. It recalculates and exports the PDF automatically.
A10: 6 | B10: Optional in-workbook macro button | C10: Import Export_Buyer_Report.bas into VBA, insert a shape/button, and assign macro ExportBuyerReport.
A12: VBA macro (copy/import the included .bas file)
A13: Sub ExportBuyerReport() | C13: Application.CalculateFull
A14: Dim ws As Worksheet, pdfPath As String, folderPath As String | C14: ws.ExportAsFixedFormat Type:=xlTypePDF, Filename:=pdfPath, Quality:=xlQualityStandard, IncludeDocProperties:=True, IgnorePrintAreas:=False, OpenAfterPublish:=True
A15: Set ws = ThisWorkbook.Worksheets("Buyer_Executive_Report") | C15: End Sub
A16: folderPath = ThisWorkbook.Path
A17: If Len(folderPath) = 0 Then folderPath = Application.DefaultFilePath
A18: pdfPath = folderPath & Application.PathSeparator & "GASQ_Buyer_Executive_Report_" & Format(Now, "yyyymmdd_hhmm") & ".pdf"
A19: Export assignment steps
A20: 1 | B20: Open VBA editor | C20: Press Alt+F11 in Excel.
A21: 2 | B21: Import module | C21: File → Import File… → select Export_Buyer_Report.bas.
A22: 3 | B22: Add button/shape | C22: On Buyer_Executive_Report insert a shape and label it Generate Buyer PDF.
A23: 4 | B23: Assign macro | C23: Right-click shape → Assign Macro… → ExportBuyerReport.
A24: 5 | B24: Use it | C24: Click the shape to export the current buyer report to PDF in the workbook folder.

Sheet Inputs
A1: GASQ Assumptions & Controls
A2: GASQ-branded operating model worksheet
A3: Core Controls
A4: Direct Labor Wage ($/paid hour) | B4: 27.48 | C4: =Direct_Labor!C4 -> 33.74 | E4: Edit highlighted assumptions only
A5: Annual Paid Hours per FTE | B5: 1456
A6: Annual Productive Coverage Hours per FTE | B6: 1456
A7: Locality Pay % | B7: 0 | C7: =Direct_Labor!C5 -> 0
A8: Shift Differential % | B8: 0 | C8: =Direct_Labor!C8 -> 0
A9: OT/Holiday Premium % | B9: 0.08 | C9: =Direct_Labor!C9 -> 2.6992
A10: Labor Market Adjustment % | B10: 0 | C10: =Direct_Labor!C6 -> 0
A11: H&W Cash ($/paid hour) | B11: 4.22 | C11: =Direct_Labor!C7 -> 4.22
A12: Fringe / Employer Burden
A13: FICA / Medicare % | B13: 0.0765 | C13: =Direct_Labor!C17 -> 3.2076297
A14: FUTA % | B14: 0.006 | C14: =Direct_Labor!C18 -> 0.2515788
A15: SUTA % | B15: 0.02 | C15: =Direct_Labor!C19 -> 0.838596
A16: Workers Compensation % | B16: 0.016 | C16: =Direct_Labor!C20 -> 0.6708768
A17: Health & Welfare ($/paid hour) | B17: 0 | C17: =Direct_Labor!C21 -> 0
A18: Vacation % | B18: 0.02 | C18: =Direct_Labor!C22 -> 0.838596
A19: Paid Holidays % | B19: 0.04 | C19: =Direct_Labor!C23 -> 1.677192
A20: Sick Leave % | B20: 0.027 | C20: =Direct_Labor!C24 -> 1.1321046
A21: DON/DOFF Minutes per 8-Hour Shift | B21: 15 | C21: =Direct_Labor!C10 -> 1.2706 | E21: Enter minutes per shift (e.g., 15); model converts minutes ÷ 480 into an hourly premium.
A22: Operations / Support
A23: Recruiting / Hiring % | B23: 0 | C23: =Direct_Labor!$C$30 -> 0
A24: Training / Certification % | B24: 0.015 | C24: =Direct_Labor!$C$31 -> 0.628947
A25: Uniforms / Equipment % | B25: 0.001 | C25: =Direct_Labor!$C$32 -> 1.1071394
A26: Field Supervision % | B26: 0 | C26: =Direct_Labor!$C$33 -> 0
A27: Contract Management % | B27: 0 | C27: =Direct_Labor!$C$34 -> 0
A28: Quality Assurance % | B28: 0 | C28: =Direct_Labor!$C$35 -> 0
A29: Vehicles / Patrol % | B29: 0.02 | C29: =Direct_Labor!$C$36 -> 3.5046454
A30: Technology / Systems % | B30: 0.01 | C30: =Direct_Labor!$C$37 -> 0.419298
A31: General Liability Insurance % | B31: 0.0892 | C31: =Direct_Labor!$C$38 -> 3.7401382
A32: Umbrella / Other Insurance % | B32: 0.0075 | C32: =Direct_Labor!$C$39 -> 0.3144735
A34: Corporate & Pricing Controls
A35: Administrative / HR / Payroll % | B35: 0 | C35: =Direct_Labor!$C$45 -> 0
A36: Accounting / Legal % | B36: 0 | C36: =Direct_Labor!$C$46 -> 0
A37: Corporate Overhead (10%) | B37: 0.1 | C37: =Direct_Labor!$C$47 -> 4.19298
A38: G&A (8%) | B38: 0.08 | C38: =Direct_Labor!$C$48 -> 3.354384
A39: Profit / Fee % (5% - 8%) | B39: 0.21 | C39: =Direct_Labor!$C$49 -> 19.106529
A40: Vendor TCO Factor vs Government TCO | B40: 0.7 | C40: =Vendor_Pricing!B5 -> 90.983473
A41: Vendor Floor Factor vs Vendor TCO | B41: 0.7 | C41: =Vendor_Pricing!B6 -> 63.688431
A42: Minimum Weekly Hours for Floor Eligibility | B42: 1500
A43: Government Full Burden Labor Share | B43: 0.7 | C43: =Government_TCO!B5 -> 48.2
A44: Government Workforce Hours Basis | B44: 3744
A45: Locality Pay % | B45: =B7 -> 0 | C45: =Direct_Labor!C5 -> 0
A46: Labor Market Adjustment % | B46: =B10 -> 0 | C46: =Direct_Labor!C6 -> 0
A47: Government TCO Multiplier vs Direct Labor | B47: =IFERROR(Government_TCO!B8/Direct_Labor!C11,0) -> 3.0998571 | C47: =Government_TCO!B16 -> 3.8522937
A48: Model Note
A49: Vehicle Tab Drivers
A50: Vehicle tab linked into Operations / Vehicles line item
A51: Vehicles Required | B51: =Vehicle!B5 -> 1
A52: Avg Miles per Vehicle per Day | B52: =Vehicle!B6 -> 365
A53: Fuel Cost per Gallon | B53: =Vehicle!B10 -> 4 | C53: =Vehicle!B10 -> 4
A54: Total Annual Vehicle Cost | B54: =Vehicle!C29 -> 61233.164 | C54: =Vehicle!C29 -> 61233.164
A55: Vehicle Cost per Labor Hour | B55: =Vehicle!C30 -> 3.5046454 | C55: =Vehicle!C30 -> 3.5046454
A56: Custom Annual Escalation % | B56: 0.03 | C56: =B56 -> 0.03
A57: Used when Option Year scenario = Custom.
A58: Low Escalation % | B58: 0.02
A59: Medium Escalation % | B59: 0.03
A60: High Escalation % | B60: 0.05
A62: Option Year Override Menu
B63: Base | C63: Option Yr 1 | D63: Option Yr 2 | E63: Option Yr 3 | F63: Option Yr 4 | G63: Option Yr 5
A64: Override Mode | B64: Auto | C64: Auto | D64: Auto | E64: Auto | F64: Auto | G64: Auto
A65: Effective Wage ($/Hr) | B65: =IFERROR($B$4,0) -> 27.48 | C65: =IF(C64="Manual",IF(C66<>"",C66,$B$65*(1+'Option Year'!$B$4)^1),$B$65*(1+'Option Year'!$B$4)^1) -> 28.3044 | D65: =IF(D64="Manual",IF(D66<>"",D66,$B$65*(1+'Option Year'!$B$4)^2),$B$65*(1+'Option Year'!$B$4)^2) -> 29.153532 | E65: =IF(E64="Manual",IF(E66<>"",E66,$B$65*(1+'Option Year'!$B$4)^3),$B$65*(1+'Option Year'!$B$4)^3) -> 30.028138 | F65: =IF(F64="Manual",IF(F66<>"",F66,$B$65*(1+'Option Year'!$B$4)^4),$B$65*(1+'Option Year'!$B$4)^4) -> 30.928982 | G65: =IF(G64="Manual",IF(G66<>"",G66,$B$65*(1+'Option Year'!$B$4)^5),$B$65*(1+'Option Year'!$B$4)^5) -> 31.856852
A66: Manual Wage Override ($/Hr)
A67: Effective Weekly Hours | B67: =IFERROR(Appraisal_Full_Scope_Report!$F$11,0) -> 336 | C67: =IF(C64="Manual",IF(C68<>"",C68,$B$67),$B$67) -> 336 | D67: =IF(D64="Manual",IF(D68<>"",D68,$B$67),$B$67) -> 336 | E67: =IF(E64="Manual",IF(E68<>"",E68,$B$67),$B$67) -> 336 | F67: =IF(F64="Manual",IF(F68<>"",F68,$B$67),$B$67) -> 336 | G67: =IF(G64="Manual",IF(G68<>"",G68,$B$67),$B$67) -> 336
A68: Manual Weekly Hours
A69: Effective Number of Weeks | B69: =IFERROR(Appraisal_Full_Scope_Report!$F$14,0) -> 336 | C69: =IF(C64="Manual",IF(C70<>"",C70,$B$69),$B$69) -> 336 | D69: =IF(D64="Manual",IF(D70<>"",D70,$B$69),$B$69) -> 336 | E69: =IF(E64="Manual",IF(E70<>"",E70,$B$69),$B$69) -> 336 | F69: =IF(F64="Manual",IF(F70<>"",F70,$B$69),$B$69) -> 336 | G69: =IF(G64="Manual",IF(G70<>"",G70,$B$69),$B$69) -> 336
A70: Manual Number of Weeks
A71: Effective Annual Hours | B71: =IFERROR(Appraisal_Full_Scope_Report!$F$15,0) -> 17472 | C71: =IF(C64="Manual",IF(C72<>"",C72,IF(AND(C68<>"",C70<>""),C68*C70,IF(C68<>"",C68*$B$69,IF(C70<>"",$B$67*C70,$B$71)))),$B$71) -> 17472 | D71: =IF(D64="Manual",IF(D72<>"",D72,IF(AND(D68<>"",D70<>""),D68*D70,IF(D68<>"",D68*$B$69,IF(D70<>"",$B$67*D70,$B$71)))),$B$71) -> 17472 | E71: =IF(E64="Manual",IF(E72<>"",E72,IF(AND(E68<>"",E70<>""),E68*E70,IF(E68<>"",E68*$B$69,IF(E70<>"",$B$67*E70,$B$71)))),$B$71) -> 17472 | F71: =IF(F64="Manual",IF(F72<>"",F72,IF(AND(F68<>"",F70<>""),F68*F70,IF(F68<>"",F68*$B$69,IF(F70<>"",$B$67*F70,$B$71)))),$B$71) -> 17472 | G71: =IF(G64="Manual",IF(G72<>"",G72,IF(AND(G68<>"",G70<>""),G68*G70,IF(G68<>"",G68*$B$69,IF(G70<>"",$B$67*G70,$B$71)))),$B$71) -> 17472
A72: Manual Annual Hours
A73: Effective Staff Required | B73: =IFERROR(Appraisal_Full_Scope_Report!$F$16,0) -> 12 | C73: =IF(C64="Manual",IF(C74<>"",C74,IFERROR(C71/$B$5,0)),$B$73) -> 12 | D73: =IF(D64="Manual",IF(D74<>"",D74,IFERROR(D71/$B$5,0)),$B$73) -> 12 | E73: =IF(E64="Manual",IF(E74<>"",E74,IFERROR(E71/$B$5,0)),$B$73) -> 12 | F73: =IF(F64="Manual",IF(F74<>"",F74,IFERROR(F71/$B$5,0)),$B$73) -> 12 | G73: =IF(G64="Manual",IF(G74<>"",G74,IFERROR(G71/$B$5,0)),$B$73) -> 12
A74: Manual Staff Required
A75: Instructions | B75: Set any year to Manual to override wage, weekly hours, weeks, annual hours, or staff. If Manual Annual Hours is blank, the model uses Weekly Hours × Number of Weeks when provided.

Sheet CFO_Bill_Rate_Breakdown
A1: CFO Bill Rate Breakdown
A2: Consolidated line-by-line build of the GASQ should-cost model with hourly and annual amounts.
A3: Description | B3: Hourly Amount | C3: Annual Amount
A4: Direct Labor
A5: =Direct_Labor!A4 -> Base Consolidated Blended Direct Labor Wage | B5: =Direct_Labor!C4 -> 33.74 | C5: =Direct_Labor!D4 -> 589505.28
A6: =Direct_Labor!A5 -> Locality Pay | B6: =Direct_Labor!C5 -> 0 | C6: =Direct_Labor!D5 -> 0
A7: =Direct_Labor!A6 -> Labor Market Adjustment | B7: =Direct_Labor!C6 -> 0 | C7: =Direct_Labor!D6 -> 0
A8: =Direct_Labor!A7 -> H&W (Cash) | B8: =Direct_Labor!C7 -> 4.22 | C8: =Direct_Labor!D7 -> 73731.84
A9: =Direct_Labor!A8 -> Shift Differential | B9: =Direct_Labor!C8 -> 0 | C9: =Direct_Labor!D8 -> 0
A10: =Direct_Labor!A9 -> OT/Holiday Premium | B10: =Direct_Labor!C9 -> 2.6992 | C10: =Direct_Labor!D9 -> 47160.422
A11: =Direct_Labor!A10 -> DON/DOFF | B11: =Direct_Labor!C10 -> 1.2706 | C11: =Direct_Labor!D10 -> 22199.923
A12: =Direct_Labor!A11 -> Total Direct Labor | B12: =Direct_Labor!C11 -> 41.9298 | C12: =Direct_Labor!D11 -> 732597.47
A14: Fringe / Employer Burden
A15: =Direct_Labor!A17 -> FICA / Medicare | B15: =Direct_Labor!C17 -> 3.2076297 | C15: =Direct_Labor!D17 -> 56043.706
A16: =Direct_Labor!A18 -> FUTA | B16: =Direct_Labor!C18 -> 0.2515788 | C16: =Direct_Labor!D18 -> 4395.5848
A17: =Direct_Labor!A19 -> SUTA | B17: =Direct_Labor!C19 -> 0.838596 | C17: =Direct_Labor!D19 -> 14651.949
A18: =Direct_Labor!A20 -> Workers Compensation | B18: =Direct_Labor!C20 -> 0.6708768 | C18: =Direct_Labor!D20 -> 11721.559
A19: =Direct_Labor!A21 -> Health & Welfare | B19: =Direct_Labor!C21 -> 0 | C19: =Direct_Labor!D21 -> 0
A20: =Direct_Labor!A22 -> Vacation | B20: =Direct_Labor!C22 -> 0.838596 | C20: =Direct_Labor!D22 -> 14651.949
A21: =Direct_Labor!A23 -> Paid Holidays | B21: =Direct_Labor!C23 -> 1.677192 | C21: =Direct_Labor!D23 -> 29303.899
A22: =Direct_Labor!A24 -> Sick Leave | B22: =Direct_Labor!C24 -> 1.1321046 | C22: =Direct_Labor!D24 -> 19780.132
A23: =Direct_Labor!A25 -> Total Fringe / Burden | B23: =Direct_Labor!C25 -> 8.6165739 | C23: =Direct_Labor!D25 -> 150548.78
A24: =Direct_Labor!A26 -> Total Direct Labor + Fringe | B24: =Direct_Labor!C26 -> 50.546374 | C24: =Direct_Labor!D26 -> 883146.24
A26: Operations / Support
A27: =Direct_Labor!$A$30 -> Recruiting / Hiring | B27: =Direct_Labor!$C$30 -> 0 | C27: =Direct_Labor!$D$30 -> 0
A28: =Direct_Labor!$A$31 -> Training / Certification | B28: =Direct_Labor!$C$31 -> 0.628947 | C28: =Direct_Labor!$D$31 -> 10988.962
A29: =Direct_Labor!$A$32 -> Uniforms / Equipment | B29: =Direct_Labor!$C$32 -> 1.1071394 | C29: =Direct_Labor!$D$32 -> 19343.94
A30: =Direct_Labor!$A$33 -> Field Supervision | B30: =Direct_Labor!$C$33 -> 0 | C30: =Direct_Labor!$D$33 -> 0
A31: =Direct_Labor!$A$34 -> Contract Management | B31: =Direct_Labor!$C$34 -> 0 | C31: =Direct_Labor!$D$34 -> 0
A32: =Direct_Labor!$A$35 -> Quality Assurance | B32: =Direct_Labor!$C$35 -> 0 | C32: =Direct_Labor!$D$35 -> 0
A33: =Direct_Labor!$A$36 -> Vehicles / Patrol | B33: =Direct_Labor!$C$36 -> 3.5046454 | C33: =Direct_Labor!$D$36 -> 61233.164
A34: =Direct_Labor!$A$37 -> Technology / Systems | B34: =Direct_Labor!$C$37 -> 0.419298 | C34: =Direct_Labor!$D$37 -> 7325.9747
A35: =Direct_Labor!$A$38 -> General Liability Insurance | B35: =Direct_Labor!$C$38 -> 3.7401382 | C35: =Direct_Labor!$D$38 -> 65347.694
A36: =Direct_Labor!$A$39 -> Umbrella / Other Insurance | B36: =Direct_Labor!$C$39 -> 0.3144735 | C36: =Direct_Labor!$D$39 -> 5494.481
A37: =Direct_Labor!$A$40 -> Total Operations / Support | B37: =Direct_Labor!$C$40 -> 9.7146414 | C37: =Direct_Labor!$D$40 -> 169734.22
A39: Overhead / G&A / Profit
A40: =Direct_Labor!$A$45 -> Administrative / HR / Payroll | B40: =Direct_Labor!$C$45 -> 0 | C40: =Direct_Labor!$D$45 -> 0
A41: =Direct_Labor!$A$46 -> Accounting / Legal | B41: =Direct_Labor!$C$46 -> 0 | C41: =Direct_Labor!$D$46 -> 0
A42: =Direct_Labor!$A$47 -> Corporate Overhead | B42: =Direct_Labor!$C$47 -> 4.19298 | C42: =Direct_Labor!$D$47 -> 73259.747
A43: =Direct_Labor!$A$48 -> G&A | B43: =Direct_Labor!$C$48 -> 3.354384 | C43: =Direct_Labor!$D$48 -> 58607.797
A44: =Direct_Labor!$A$49 -> Profit / Fee | B44: =Direct_Labor!$C$49 -> 19.106529 | C44: =Direct_Labor!$D$49 -> 333829.28
A45: =Direct_Labor!$A$50 -> Total Overhead / G&A / Profit | B45: =Direct_Labor!$C$50 -> 26.653893 | C45: =Direct_Labor!$D$50 -> 465696.82
A47: Module Feeds (Memo Only - Included Above Where Applicable)
A48: Vehicle Cost per Labor Hour | B48: =Vehicle!$C$30 -> 3.5046454 | C48: =Vehicle!$C$29 -> 61233.164
A49: Uniform & Equipment Cost per Labor Hour | B49: =Uniform_Equipment!$C$36 -> 1.1071394 | C49: =Uniform_Equipment!$C$35 -> 19343.94 | E49: GASQ Price Realism Review
A50: Training Program Cost per Labor Hour | B50: =IFERROR((SUMPRODUCT(Training_Module!$B$2:$B$8,Training_Module!$D$2:$D$8,Training_Module!$E$2:$E$8)+SUM(Training_Module!$F$2:$F$8)+SUM(Training_Module!$G$2:$G$8))/_Calc_Backend!$X$37,0) -> 2.2161172 | C50: =SUMPRODUCT(Training_Module!$B$2:$B$8,Training_Module!$D$2:$D$8,Training_Module!$E$2:$E$8)+SUM(Training_Module!$F$2:$F$8)+SUM(Training_Module!$G$2:$G$8) -> 38720 | E50: GASQ-branded operating model worksheet
E51: Benchmark Rates
A52: Total Bill Rate | B52: =Direct_Labor!$C$52 -> 86.914909 | C52: =Direct_Labor!$D$52 -> 1518577.3 | E52: Government Should-Cost TCO Benchmark | F52: =Government_TCO!B8 -> 129.97639 | G52: =IFERROR(F52*Appraisal_Full_Scope_Report!F15,"") -> 2270947.5
A53: Vendor TCO Benchmark | B53: =Vendor_Pricing!$B$5 -> 90.983473 | C53: =Vendor_Pricing!$B$5*Appraisal_Full_Scope_Report!$F$15 -> 1589663.2 | E53: Reserved Should-Cost Government Rate | F53: =Vendor_Pricing!B6 -> 63.688431 | G53: =IFERROR(F53*Appraisal_Full_Scope_Report!F15,"") -> 1112764.3
A54: Capital Recovery Opportunity | B54: =B52-B53 -> -4.0685643 | C54: =C52-C53 -> -71085.956 | E54: Market Target Rate | F54: =Vendor_Pricing!B7 -> 77.335952 | G54: =IFERROR(F54*Appraisal_Full_Scope_Report!F15,"") -> 1351213.8
A55: Vendor Premium / (Discount) vs GASQ | B55: =B53-B52 -> 4.0685643 | C55: =C53-C52 -> 71085.956 | E55: Vendor Total Cost of Ownership Rate | F55: =Vendor_Pricing!B8 -> 90.983473 | G55: =IFERROR(F55*Appraisal_Full_Scope_Report!F15,"") -> 1589663.2
A56: Reconciliation Check | B56: =IF(ABS(B52-Direct_Labor!$C$52)<0.01,0,1) -> 0 | C56: =IF(ABS(C52-Direct_Labor!$D$52)<1,0,1) -> 0
E57: Evaluation Grid
E58: Vendor | F58: Bid Rate | G58: Annual Amount | H58: Delta vs Gov TCO | I58: Delta % | J58: Benchmark Position | K58: Recommendation
E59: =Vendor_Pricing!A15 -> Vendor 1 | F59: =Vendor_Pricing!B15 -> 35 | G59: =IF(B11="","",B11*Appraisal_Full_Scope_Report!$F$15) -> 22199.923 | H59: =IF(B11="","",B11-$B$4) -> 1.2706 | I59: =IFERROR(D11/$B$4,"") | J59: =Vendor_Pricing!E15 -> Below Floor | K59: =IF(B11="","",IF(B11<$B$5,"Below reserved should-cost floor",IF(B11<=$B$6,"Within target range",IF(B11<=$B$7,"Above target but within TCO ceiling","Above TCO ceiling")))) -> Below reserved should-cost floor
E60: =Vendor_Pricing!A16 -> Vendor 2 | F60: =Vendor_Pricing!B16 -> 37 | G60: =IF(B12="","",B12*Appraisal_Full_Scope_Report!$F$15) -> 732597.47 | H60: =IF(B12="","",B12-$B$4) -> 41.9298 | I60: =IFERROR(D12/$B$4,"") | J60: =Vendor_Pricing!E16 -> Below Floor | K60: =IF(B12="","",IF(B12<$B$5,"Below reserved should-cost floor",IF(B12<=$B$6,"Within target range",IF(B12<=$B$7,"Above target but within TCO ceiling","Above TCO ceiling")))) -> Above TCO ceiling
E61: =Vendor_Pricing!A17 -> Vendor 3 | F61: =Vendor_Pricing!B17 -> 41 | G61: =IF(B13="","",B13*Appraisal_Full_Scope_Report!$F$15) | H61: =IF(B13="","",B13-$B$4) | I61: =IFERROR(D13/$B$4,"") | J61: =Vendor_Pricing!E17 -> Below Floor | K61: =IF(B13="","",IF(B13<$B$5,"Below reserved should-cost floor",IF(B13<=$B$6,"Within target range",IF(B13<=$B$7,"Above target but within TCO ceiling","Above TCO ceiling"))))
E62: =Vendor_Pricing!A18 -> Vendor 4 | F62: =Vendor_Pricing!B18 -> 42 | G62: =IF(B14="","",B14*Appraisal_Full_Scope_Report!$F$15) | H62: =IF(B14="","",B14-$B$4) | I62: =IFERROR(D14/$B$4,"") | J62: =Vendor_Pricing!E18 -> Below Floor | K62: =IF(B14="","",IF(B14<$B$5,"Below reserved should-cost floor",IF(B14<=$B$6,"Within target range",IF(B14<=$B$7,"Above target but within TCO ceiling","Above TCO ceiling"))))
E63: =Vendor_Pricing!A19 -> Vendor 5 | F63: =Vendor_Pricing!B19 -> 50 | G63: =IF(B15="","",B15*Appraisal_Full_Scope_Report!$F$15) -> 56043.706 | H63: =IF(B15="","",B15-$B$4) -> 3.2076297 | I63: =IFERROR(D15/$B$4,"") | J63: =Vendor_Pricing!E19 -> Below Floor | K63: =IF(B15="","",IF(B15<$B$5,"Below reserved should-cost floor",IF(B15<=$B$6,"Within target range",IF(B15<=$B$7,"Above target but within TCO ceiling","Above TCO ceiling")))) -> Below reserved should-cost floor
E66: Typical Federal-Style Logic | F66: Below floor suggests performance risk. Bids within target/ceiling range are generally the most defensible.

Sheet Post_Positions
A1: POST POSITION SUMMARY | B1: Qty Required | C1: Blended Pay Rate | D1: Weekly Hours/Hits | E1: Weekly Cost | F1: Monthly Hours | G1: Monthly Cost | H1: Annual Hours/Hits | I1: Annual Direct Labor Cost | K1: INPUT / CONTROL PANEL | L1: User Pay Rate | M1: Weekly Cost | N1: Monthly Cost | O1: Annual Cost | P1: Staff Count | Q1: Weekly Hours | R1: Monthly Hours | S1: Annual Hours
A2: Unarmed S/O | B2: =+P2 -> 6 | C2: =+L2 -> 27.48 | D2: =+Q2 -> 168 | E2: =+M2 -> 4616.64 | F2: =+R2 -> 728 | G2: =+N2 -> 20005.44 | H2: =+S2 -> 8736 | I2: =+O2 -> 240065.28 | K2: Post / Labor Category | L2: 27.48 | M2: =+$L2*$Q2 -> 4616.64 | N2: =+$L2*$R2 -> 20005.44 | O2: =+$L2*$S2 -> 240065.28 | P2: =+Q2/28 -> 6 | Q2: =+S2/52 -> 168 | R2: =+S2/12 -> 728 | S2: 8736
A3: Supervisor | B3: =+P3 -> 6.2686567 | C3: =+L3 -> 40 | D3: =+Q3 -> 168 | E3: =+M3 -> 6720 | F3: =+R3 -> 728 | G3: =+N3 -> 29120 | H3: =+S3 -> 8736 | I3: =+O3 -> 349440 | K3: Set pay rate | L3: 40 | M3: =+$L3*$Q3 -> 6720 | N3: =+$L3*$R3 -> 29120 | O3: =+$L3*$S3 -> 349440 | P3: =+Q3/26.8 -> 6.2686567 | Q3: =+S3/52 -> 168 | R3: =+S3/12 -> 728 | S3: 8736
A4: Unarmed S/O | B4: =+P4 -> 0 | C4: =+L4 -> 0 | D4: =+Q4 -> 0 | E4: =+M4 -> 0 | F4: =+R4 -> 0 | G4: =+N4 -> 0 | H4: =+S4 -> 0 | I4: =+O4 -> 0 | K4: Auto weekly cost | L4: 0 | M4: =+$L4*$Q4 -> 0 | N4: =+$L4*$R4 -> 0 | O4: =+$L4*$S4 -> 0 | P4: =+Q4/26.8 -> 0 | Q4: =+S4/52 -> 0 | R4: =+S4/12 -> 0 | S4: 0
A5: Unarmed S/O | B5: =+P5 -> 0 | C5: =+L5 -> 0 | D5: =+Q5 -> 0 | E5: =+M5 -> 0 | F5: =+R5 -> 0 | G5: =+N5 -> 0 | H5: =+S5 -> 0 | I5: =+O5 -> 0 | K5: Auto monthly cost | L5: 0 | M5: =+$L5*$Q5 -> 0 | N5: =+$L5*$R5 -> 0 | O5: =+$L5*$S5 -> 0 | P5: =+Q5/26.8 -> 0 | Q5: =+S5/52 -> 0 | R5: =+S5/12 -> 0 | S5: 0
A6: Rovering Patrol Officer | B6: =+P6 -> 0 | C6: =+L6 -> 0 | D6: =+Q6 -> 0 | E6: =+M6 -> 0 | F6: =+R6 -> 0 | G6: =+N6 -> 0 | H6: =+S6 -> 0 | I6: =+O6 -> 0 | K6: Auto annual cost | L6: 0 | M6: =+$L6*$Q6 -> 0 | N6: =+$L6*$R6 -> 0 | O6: =+$L6*$S6 -> 0 | P6: =+Q6/26.8 -> 0 | Q6: =+S6/52 -> 0 | R6: =+S6/12 -> 0 | S6: 0
A7: Unarmed S/O | B7: =+P7 -> 0 | C7: =+L7 -> 0 | D7: =+Q7 -> 0 | E7: =+M7 -> 0 | F7: =+R7 -> 0 | G7: =+N7 -> 0 | H7: =+S7 -> 0 | I7: =+O7 -> 0 | K7: Auto staff count | L7: 0 | M7: =+$L7*$Q7 -> 0 | N7: =+$L7*$R7 -> 0 | O7: =+$L7*$S7 -> 0 | P7: =+Q7/26.8 -> 0 | Q7: =+S7/52 -> 0 | R7: =+S7/12 -> 0 | S7: 0
A8: Unarmed S/O | B8: =+P8 -> 0 | C8: =+L8 -> 0 | D8: =+Q8 -> 0 | E8: =+M8 -> 0 | F8: =+R8 -> 0 | G8: =+N8 -> 0 | H8: =+S8 -> 0 | I8: =+O8 -> 0 | K8: Input weekly hours | L8: 0 | M8: =+$L8*$Q8 -> 0 | N8: =+$L8*$R8 -> 0 | O8: =+$L8*$S8 -> 0 | P8: =+Q8/26.8 -> 0 | Q8: =+S8/52 -> 0 | R8: =+S8/12 -> 0 | S8: 0
A9: Unarmed S/O | B9: =+P9 -> 0 | C9: =+L9 -> 0 | D9: =+Q9 -> 0 | E9: =+M9 -> 0 | F9: =+R9 -> 0 | G9: =+N9 -> 0 | H9: =+S9 -> 0 | I9: =+O9 -> 0 | K9: Auto monthly hours | L9: 0 | M9: =+$L9*$Q9 -> 0 | N9: =+$L9*$R9 -> 0 | O9: =+$L9*$S9 -> 0 | P9: =+Q9/26.8 -> 0 | Q9: =+S9/52 -> 0 | R9: =+S9/12 -> 0 | S9: 0
A10: Unarmed S/O | B10: =+P10 -> 0 | C10: =+L10 -> 0 | D10: =+Q10 -> 0 | E10: =+M10 -> 0 | F10: =+R10 -> 0 | G10: =+N10 -> 0 | H10: =+S10 -> 0 | I10: =+O10 -> 0 | K10: Input annual hours | L10: 0 | M10: =+$L10*$Q10 -> 0 | N10: =+$L10*$R10 -> 0 | O10: =+$L10*$S10 -> 0 | P10: =+Q10/26.8 -> 0 | Q10: =+S10/52 -> 0 | R10: =+S10/12 -> 0 | S10: 0
A11: Unarmed S/O | B11: =+P11 -> 0 | C11: =+L11 -> 0 | D11: =+Q11 -> 0 | E11: =+M11 -> 0 | F11: =+R11 -> 0 | G11: =+N11 -> 0 | H11: =+S11 -> 0 | I11: =+O11 -> 0 | L11: 0 | M11: =+$L11*$Q11 -> 0 | N11: =+$L11*$R11 -> 0 | O11: =+$L11*$S11 -> 0 | P11: =+Q11/26.8 -> 0 | Q11: =+S11/52 -> 0 | R11: =+S11/12 -> 0 | S11: 0
A12: ESTIMATED TOTAL | B12: =SUM(B2:B11) -> 12.268657 | C12: =AVERAGEIF(C2:C11,">0") -> 33.74 | D12: =SUM(D2:D11) -> 336 | E12: =SUM(E2:E11) -> 11336.64 | F12: =SUM(F2:F11) -> 1456 | G12: =SUM(G2:G11) -> 49125.44 | H12: =SUM(H2:H11) -> 17472 | I12: =SUM(I2:I11) -> 589505.28 | K12: Control Totals | M12: =SUM(M2:M11) -> 11336.64 | N12: =SUM(N2:N11) -> 49125.44 | O12: =SUM(O2:O11) -> 589505.28 | P12: =+Q12/26.8 -> 12.537313 | Q12: =+S12/52 -> 336 | R12: =SUM(R2:R11) -> 1456 | S12: =SUM(S2:S11) -> 17472

Sheet Uniform_Equipment
A1: GASQ Uniform & Equipment Module
A2: GASQ-branded operating model worksheet
A3: Program Inputs
A4: Input / Line Item | B4: Value | C4: Units | D4: Calc / Annualized | E4: Notes
A5: FTEs Required | B5: =ROUNDUP(_Calc_Backend!$X$38,0) -> 12 | C5: FTEs | E5: Linked from Scope_of_Work
A6: Annual Labor Hours | B6: =_Calc_Backend!$X$37 -> 17472 | C6: hours | E6: Linked from Scope_of_Work
A7: Uniform Sets per Employee | B7: 3 | C7: sets/FTE | E7: Hardcoded input
A8: Cost per Uniform Set | B8: 333 | C8: $ / set | E8: Hardcoded input
A9: Uniform Useful Life | B9: 12 | C9: months | E9: Annual issue if 12 months
A10: Duty Gear Kit per Employee | B10: 350 | C10: $ / FTE | E10: Belts, pouches, accessories
A11: Duty Gear Useful Life | B11: 24 | C11: months | E11: Annualized over useful life
A12: Radio / Device per Employee | B12: 275 | C12: $ / FTE | E12: Phones, radios, chargers
A13: Radio / Device Useful Life | B13: 36 | C13: months | E13: Annualized over useful life
A14: Badge / ID / Misc. Issue per Employee | B14: 45 | C14: $ / FTE | E14: Initial issue
A15: Badge / ID Useful Life | B15: 12 | C15: months | E15: Annualized over useful life
A16: Annual Consumables / Small Equipment | B16: 85 | C16: $ / FTE / year | E16: Gloves, batteries, notebooks
A17: Spare / Float Inventory Factor | B17: 0.1 | C17: % | E17: Reserve for extras, turnover
A18: Program Management / Logistics Factor | B18: 0.05 | C18: % | E18: Sizing and replacement admin
A21: Annual Cost Build
A22: Metric | B22: Formula | C22: Result | D22: Units | E22: Comment
A23: Initial Uniform Issue | B23: =B5*B7*B8 -> 11988 | C23: =B23 -> 11988 | D23: $ | E23: FTEs × sets × cost
A24: Annual Uniform Cost | B24: =IFERROR(C23*(12/B9),0) -> 11988 | C24: =B24 -> 11988 | D24: $ / year | E24: Annualized by useful life
A25: Initial Duty Gear Issue | B25: =B5*B10 -> 4200 | C25: =B25 -> 4200 | D25: $ | E25: FTEs × kit cost
A26: Annual Duty Gear Cost | B26: =IFERROR(C25*(12/B11),0) -> 2100 | C26: =B26 -> 2100 | D26: $ / year | E26: Annualized by useful life
A27: Initial Radio / Device Issue | B27: =B5*B12 -> 3300 | C27: =B27 -> 3300 | D27: $ | E27: FTEs × device cost
A28: Annual Radio / Device Cost | B28: =IFERROR(C27*(12/B13),0) -> 1100 | C28: =B28 -> 1100 | D28: $ / year | E28: Annualized by useful life
A29: Initial Badge / ID / Misc. Issue | B29: =B5*B14 -> 540 | C29: =B29 -> 540 | D29: $ | E29: FTEs × issue cost
A30: Annual Badge / ID / Misc. Cost | B30: =IFERROR(C29*(12/B15),0) -> 540 | C30: =B30 -> 540 | D30: $ / year | E30: Annualized by useful life
A31: Annual Consumables | B31: =B5*B16 -> 1020 | C31: =B31 -> 1020 | D31: $ / year | E31: Direct annual cost
A32: Subtotal Annual Equipment Cost | B32: =SUM(C24,C26,C28,C30,C31) -> 16748 | C32: =B32 -> 16748 | D32: $ / year | E32: Before reserve and logistics
A33: Spare / Float Inventory Cost | B33: =C32*B17 -> 1674.8 | C33: =B33 -> 1674.8 | D33: $ / year | E33: Reserve factor
A34: Program Management / Logistics | B34: =SUM(C32:C33)*B18 -> 921.14 | C34: =B34 -> 921.14 | D34: $ / year | E34: Sizing, shipping, admin
A35: Total Annual Uniform & Equipment Cost | B35: =SUM(C32:C34) -> 19343.94 | C35: =B35 -> 19343.94 | D35: $ / year | E35: Feeds Operations tab
A36: Uniform & Equipment Cost per Labor Hour | B36: =IFERROR(C35/B6,0) -> 1.1071394 | C36: =B36 -> 1.1071394 | D36: $ / labor hour | E36: Feeds Operations hourly rate
A39: Module Checks
A40: Check | B40: Formula | C40: Result | D40: Status
A41: FTE link populated | B41: =IF(B5>0,"OK","CHECK") -> OK | C41: =B41 -> OK | D41: Scope link
A42: Annual labor hours populated | B42: =IF(B6>0,"OK","CHECK") -> OK | C42: =B42 -> OK | D42: Scope link
A43: Hourly cost available | B43: =IF(C36>=0,"OK","CHECK") -> OK | C43: =B43 -> OK | D43: Operations feed
A46: This replacement module annualizes uniforms, duty gear, devices, ID issue, and consumables, then converts the total into a cost per labor hour for the Operations tab.

Sheet Vehicle
A1: GASQ Vehicle / Patrol Cost Model
A2: GASQ-branded operating model worksheet
A3: Vehicle Assumptions
A4: Line Item | B4: Input / Formula | C4: Units | D4: Notes
A5: Vehicles Required | B5: 1 | C5: vehicles | D5: User input
A6: Average Miles per Vehicle per Day | B6: 365 | C6: miles/day | D6: User input
A7: Operating Days per Week | B7: 7 | C7: days/week | D7: User input
A8: Weeks of Coverage | B8: 52 | C8: weeks/year | D8: User input
A9: Fuel Economy | B9: 22 | C9: mpg | D9: User input
A10: Fuel Cost per Gallon | B10: 4 | C10: $/gallon | D10: User input
A11: Maintenance Cost per Mile | B11: 0.18 | C11: $/mile | D11: User input
A12: Monthly Lease / Payment per Vehicle | B12: 850 | C12: $/month | D12: User input
A13: Monthly Insurance per Vehicle | B13: 225 | C13: $/month | D13: User input
A14: Monthly GPS / Telematics per Vehicle | B14: 1 | C14: $/month | D14: User input
A15: Annual Registration / Tags per Vehicle | B15: 250 | C15: $/year | D15: User input
A18: Vehicle Cost Calculations
A19: Metric | B19: Formula | C19: Result | D19: Units
A20: Daily Fleet Miles | B20: =B5*B6 -> 365 | C20: =B20 -> 365 | D20: miles/day
A21: Annual Fleet Miles | B21: =C20*B7*B8 -> 132860 | C21: =B21 -> 132860 | D21: miles/year
A22: Annual Fuel Gallons | B22: =IFERROR(C21/B9,0) -> 6039.0909 | C22: =B22 -> 6039.0909 | D22: gallons/year
A23: Annual Fuel Cost | B23: =C22*B10 -> 24156.364 | C23: =B23 -> 24156.364 | D23: $/year
A24: Annual Maintenance Cost | B24: =C21*B11 -> 23914.8 | C24: =B24 -> 23914.8 | D24: $/year
A25: Annual Lease / Payment Cost | B25: =B5*B12*12 -> 10200 | C25: =B25 -> 10200 | D25: $/year
A26: Annual Insurance Cost | B26: =B5*B13*12 -> 2700 | C26: =B26 -> 2700 | D26: $/year
A27: Annual GPS / Telematics Cost | B27: =B5*B14*12 -> 12 | C27: =B27 -> 12 | D27: $/year
A28: Annual Registration / Tags | B28: =B5*B15 -> 250 | C28: =B28 -> 250 | D28: $/year
A29: Total Annual Vehicle Cost | B29: =SUM(C23:C28) -> 61233.164 | C29: =B29 -> 61233.164 | D29: $/year
A30: Vehicle Cost per Annual Labor Hour | B30: =IFERROR(C29/_Calc_Backend!$X$37,0) -> 3.5046454 | C30: =B30 -> 3.5046454 | D30: $/labor hr
A31: Vehicle Cost per Productive Coverage Hour | B31: =IFERROR(C29/_Calc_Backend!$X$33,0) -> 15.8425 | C31: =B31 -> 15.8425 | D31: $/coverage hr
A34: This tab calculates annual fleet cost and converts it into an hourly rate that feeds the Operations tab. Yellow cells are user inputs.

Sheet Training_Module
A1: Training Description | B1: Hours | C1: Training Wage | D1: Training Cost Per Hour | E1: Employees Trained | F1: Instructor Cost | G1: Equipment Cost | H1: Certification Fee | I1: Travel Cost | J1: Edit highlighted assumptions only
A2: CPR / First Aid / AED | B2: 8 | C2: 21 | D2: =C2/0.7 -> 30 | E2: =IFERROR(ROUNDUP(_Calc_Backend!$E$22/28,0),"") -> 12 | F2: 200 | G2: 600 | H2: 0 | I2: 0 | J2: =B2*D2*E2+F2+G2+H2+I2 -> 3680
A3: Pre‑Assignment Training | B3: 16 | C3: 25 | D3: =C3/0.7 -> 35.714286 | E3: =IFERROR(ROUNDUP(_Calc_Backend!$E$22/28,0),"") -> 12 | F3: 0 | G3: 0 | H3: 0 | I3: 0 | J3: =B3*D3*E3+F3+G3+H3+I3 -> 6857.1429
A4: Field Training | B4: 40 | C4: 21 | D4: =C4/0.7 -> 30 | E4: =IFERROR(ROUNDUP(_Calc_Backend!$E$22/28,0),"") -> 12 | F4: 0 | G4: 0 | H4: 0 | I4: 0 | J4: =B4*D4*E4+F4+G4+H4+I4 -> 14400
A5: Weapons Training | B5: 8 | C5: 21 | D5: =C5/0.7 -> 30 | E5: =IFERROR(ROUNDUP(_Calc_Backend!$E$22/28,0),"") -> 12 | F5: 0 | G5: 0 | H5: 0 | I5: 0 | J5: =B5*D5*E5+F5+G5+H5+I5 -> 2880
A6: Site Specific Training | B6: 8 | C6: 21 | D6: =C6/0.7 -> 30 | E6: =IFERROR(ROUNDUP(_Calc_Backend!$E$22/28,0),"") -> 12 | F6: 0 | G6: 0 | H6: 0 | I6: 0 | J6: =B6*D6*E6+F6+G6+H6+I6 -> 2880
A7: Supervisor Training | B7: 12 | C7: 25 | D7: =C7/0.7 -> 35.714286 | E7: =IFERROR(ROUNDUP(_Calc_Backend!$E$22/28,0),"") -> 12 | F7: 0 | G7: 0 | H7: 0 | I7: 0 | J7: =B7*D7*E7+F7+G7+H7+I7 -> 5142.8571
A8: Annual Refresher | B8: 8 | C8: 21 | D8: =C8/0.7 -> 30 | E8: =IFERROR(ROUNDUP(_Calc_Backend!$E$22/28,0),"") -> 12 | F8: 0 | G8: 0 | H8: 0 | I8: 0 | J8: =B8*D8*E8+F8+G8+H8+I8 -> 2880
I9: Total Training Cost | J9: =SUM(J2:J8) -> 38720

Sheet Equipment_Uniform_Module
A1: Item | B1: Cost Per Unit | C1: Quantity | D1: Replacement Cycle (Years) | E1: Annualized Cost
A2: Uniform | B2: 250 | C2: 4 | D2: 1 | E2: =B2*C2/D2 -> 1000
A3: Radio | B3: 600 | C3: 1 | D3: 3 | E3: =B3*C3/D3 -> 200
A4: Body Armor | B4: 800 | C4: 1 | D4: 5 | E4: =B4*C4/D4 -> 160
A5: Flashlight | B5: 75 | C5: 1 | D5: 2 | E5: =B5*C5/D5 -> 37.5
A6: Duty Belt | B6: 150 | C6: 1 | D6: 3 | E6: =B6*C6/D6 -> 50
D7: Total Annual Equipment Cost | E7: =SUM(E2:E6) -> 1447.5

Sheet Workforce_Maintenance_Module
A1: Category | B1: Days/Hours | C1: Employees | D1: Cost Per Hour | E1: Total Cost
A2: Vacation Days | B2: 80 | C2: 1 | D2: 28.04 | E2: =B2*C2*D2 -> 2243.2
A3: Sick Days | B3: 56 | C3: 2 | D3: 28.04 | E3: =B3*C3*D3 -> 3140.48
A4: Holiday Pay | B4: 88 | C4: 2 | D4: 42.06 | E4: =B4*C4*D4 -> 7402.56
A5: Turnover Replacement | B5: 40 | C5: 2 | D5: 28.04 | E5: =B5*C5*D5 -> 2243.2
A6: Recruiting / Hiring | B6: 0 | C6: 0 | D6: 0 | E6: =B6*C6*D6 -> 0
D7: Total Workforce Maintenance Cost | E7: =SUM(E2:E6) -> 15029.44

Sheet Direct_Labor
A1: GASQ Direct Labor Build-Up
A2: GASQ-branded operating model worksheet
A3: Line Item | B3: Input / Formula | C3: Hourly Amount | D3: Annual Amount
A4: Base Consolidated Blended Direct Labor Wage | B4: =IFERROR(IF(Post_Positions!$C$12>0,Post_Positions!$C$12,Inputs!$B$4),Inputs!$B$4) -> 33.74 | C4: =B4 -> 33.74 | D4: =C4*_Calc_Backend!$X$37 -> 589505.28
A5: Locality Pay | B5: =C4*Inputs!$B$7 -> 0 | C5: =B5 -> 0 | D5: =C5*_Calc_Backend!$X$37 -> 0
A6: Labor Market Adjustment | B6: =C4*Inputs!$B$10 -> 0 | C6: =B6 -> 0 | D6: =C6*_Calc_Backend!$X$37 -> 0
A7: H&W (Cash) | B7: =Inputs!$B$11 -> 4.22 | C7: =B7 -> 4.22 | D7: =C7*_Calc_Backend!$X$37 -> 73731.84
A8: Shift Differential | B8: =C4*Inputs!$B$8 -> 0 | C8: =B8 -> 0 | D8: =C8*_Calc_Backend!$X$37 -> 0
A9: OT/Holiday Premium | B9: =C4*Inputs!$B$9 -> 2.6992 | C9: =B9 -> 2.6992 | D9: =C9*_Calc_Backend!$X$37 -> 47160.422
A10: DON/DOFF | B10: =IFERROR(IF(Inputs!$B$21>0,SUM(C4:C9)*(Inputs!$B$21/480),0),0) -> 1.2706 | C10: =B10 -> 1.2706 | D10: =C10*_Calc_Backend!$X$37 -> 22199.923
A11: Total Direct Labor | C11: =SUM(C4:C10) -> 41.9298 | D11: =SUM(D4:D10) -> 732597.47
A12: Input (or weighted blended pay wage from Post_Positions only), plus locality, labor market, other direct-pay premiums, and DON/DOFF before burden is applied. | C12: =C11 -> 41.9298 | D12: =D11 -> 732597.47
A14: GASQ Fringe & Employer Burden
A15: GASQ-branded operating model worksheet
A16: Line Item | B16: Input / Formula | C16: Hourly Amount | D16: Annual Amount
A17: FICA / Medicare | B17: =Direct_Labor!$C$11*Inputs!$B$13 -> 3.2076297 | C17: =B17 -> 3.2076297 | D17: =C17*_Calc_Backend!$X$37 -> 56043.706
A18: FUTA | B18: =Direct_Labor!$C$11*Inputs!$B$14 -> 0.2515788 | C18: =B18 -> 0.2515788 | D18: =C18*_Calc_Backend!$X$37 -> 4395.5848
A19: SUTA | B19: =Direct_Labor!$C$11*Inputs!$B$15 -> 0.838596 | C19: =B19 -> 0.838596 | D19: =C19*_Calc_Backend!$X$37 -> 14651.949
A20: Workers Compensation | B20: =Direct_Labor!$C$11*Inputs!$B$16 -> 0.6708768 | C20: =B20 -> 0.6708768 | D20: =C20*_Calc_Backend!$X$37 -> 11721.559
A21: Health & Welfare | B21: =Inputs!$B$17 -> 0 | C21: =B21 -> 0 | D21: =C21*_Calc_Backend!$X$37 -> 0
A22: Vacation | B22: =Direct_Labor!$C$11*Inputs!$B$18 -> 0.838596 | C22: =B22 -> 0.838596 | D22: =C22*_Calc_Backend!$X$37 -> 14651.949
A23: Paid Holidays | B23: =Direct_Labor!$C$11*Inputs!$B$19 -> 1.677192 | C23: =B23 -> 1.677192 | D23: =C23*_Calc_Backend!$X$37 -> 29303.899
A24: Sick Leave | B24: =Direct_Labor!$C$11*Inputs!$B$20 -> 1.1321046 | C24: =B24 -> 1.1321046 | D24: =C24*_Calc_Backend!$X$37 -> 19780.132
A25: Total Fringe / Burden | C25: =SUM(C17:C24) -> 8.6165739 | D25: =SUM(D17:D24) -> 150548.78
A26: Total Direct Labor + Fringe | C26: =C11+C25 -> 50.546374 | D26: =D11+D25 -> 883146.24
A27: GASQ Operations & Contract Support (Integrated)
A28: GASQ-branded operating model worksheet
A29: Line Item | B29: Input / Formula | C29: Hourly Amount | D29: Annual Amount
A30: Recruiting / Hiring | B30: =Direct_Labor!$C$11*Inputs!$B$23 -> 0 | C30: =B30 -> 0 | D30: =C30*_Calc_Backend!$X$37 -> 0
A31: Training / Certification | B31: =Direct_Labor!$C$11*Inputs!$B$24 -> 0.628947 | C31: =B31 -> 0.628947 | D31: =C31*_Calc_Backend!$X$37 -> 10988.962
A32: Uniforms / Equipment | B32: =Uniform_Equipment!$C$36 -> 1.1071394 | C32: =B32 -> 1.1071394 | D32: =Uniform_Equipment!$C$35 -> 19343.94
A33: Field Supervision | B33: =Direct_Labor!$C$11*Inputs!$B$26 -> 0 | C33: =B33 -> 0 | D33: =C33*_Calc_Backend!$X$37 -> 0
A34: Contract Management | B34: =Direct_Labor!$C$11*Inputs!$B$27 -> 0 | C34: =B34 -> 0 | D34: =C34*_Calc_Backend!$X$37 -> 0
A35: Quality Assurance | B35: =Direct_Labor!$C$11*Inputs!$B$28 -> 0 | C35: =B35 -> 0 | D35: =C35*_Calc_Backend!$X$37 -> 0
A36: Vehicles / Patrol | B36: =Vehicle!$C$30 -> 3.5046454 | C36: =B36 -> 3.5046454 | D36: =Vehicle!$C$29 -> 61233.164
A37: Technology / Systems | B37: =Direct_Labor!$C$11*Inputs!$B$30 -> 0.419298 | C37: =B37 -> 0.419298 | D37: =C37*_Calc_Backend!$X$37 -> 7325.9747
A38: General Liability Insurance | B38: =Direct_Labor!$C$11*Inputs!$B$31 -> 3.7401382 | C38: =B38 -> 3.7401382 | D38: =C38*_Calc_Backend!$X$37 -> 65347.694
A39: Umbrella / Other Insurance | B39: =Direct_Labor!$C$11*Inputs!$B$32 -> 0.3144735 | C39: =B39 -> 0.3144735 | D39: =C39*_Calc_Backend!$X$37 -> 5494.481
A40: Total Operations / Support | C40: =SUM(C30:C39) -> 9.7146414 | D40: =SUM(D30:D39) -> 169734.22
A42: GASQ Overhead, G&A, and Profit (Integrated)
A43: GASQ-branded operating model worksheet
A44: Line Item | B44: Input / Formula | C44: Hourly Amount | D44: Annual Amount
A45: Administrative / HR / Payroll | B45: =Direct_Labor!$C$11*Inputs!$B$35 -> 0 | C45: =B45 -> 0 | D45: =C45*_Calc_Backend!$X$37 -> 0
A46: Accounting / Legal | B46: =Direct_Labor!$C$11*Inputs!$B$36 -> 0 | C46: =B46 -> 0 | D46: =C46*_Calc_Backend!$X$37 -> 0
A47: Corporate Overhead | B47: =Direct_Labor!$C$11*Inputs!$B$37 -> 4.19298 | C47: =B47 -> 4.19298 | D47: =C47*_Calc_Backend!$X$37 -> 73259.747
A48: G&A | B48: =Direct_Labor!$C$11*Inputs!$B$38 -> 3.354384 | C48: =B48 -> 3.354384 | D48: =C48*_Calc_Backend!$X$37 -> 58607.797
A49: Profit / Fee | B49: =IFERROR((Appraisal_Full_Scope_Report!$H$19*Inputs!$B$39)/Appraisal_Full_Scope_Report!$F$15,0) -> 19.106529 | C49: =B49 -> 19.106529 | D49: =C49*_Calc_Backend!$X$37 -> 333829.28
A50: Total Overhead / G&A / Profit | C50: =SUM(C45:C49) -> 26.653893 | D50: =SUM(D45:D49) -> 465696.82
A52: Total Fully Burdened Labor Cost Stack | C52: =C26+C40+C50 -> 86.914909 | D52: =D26+D40+D50 -> 1518577.3
A53: Master hourly / annual total feeding CFO | C53: =C52 -> 86.914909 | D53: =D52 -> 1518577.3

Sheet Appraisal_Full_Scope_Report
B1: GASQ Workforce-to-Post™ Capital Recovery Appraisal Full Scope Report
B2: Workforce Total Cost of Ownership (TCO) -vs- Vendor Outsourced Security Services
B3: Prepared for: | G3: =TODAY( ) -> 46118
B5: Appraisal Comparison Summary
B6: DESCRIPTION | F6: SERVICE REQUESTER INTERNAL TCO | H6: VENDOR TCO TO OUTSOURCE | J6: DIFFERENCE SAVED
B7: Workforce Baseline Assumption Labor Rate + Fringe Benefits | F7: =CFO_Bill_Rate_Breakdown!$B$24 -> 50.546374 | H7: =CFO_Bill_Rate_Breakdown!$B$24 -> 50.546374 | J7: =""
B8: Workforce Hourly Cost Per Security Professional | F8: =IFERROR(($F$7*Inputs!$B$44)/Inputs!$B$5,0) -> 129.97639 | H8: =IFERROR($F$8*Inputs!$B$40,0) -> 90.983473 | J8: =F8-H8 -> 38.992917
B9: Overtime/Holiday Rate | F9: =IFERROR(F8*1.5,0) -> 194.96459 | H9: =IFERROR(H8*1.5,0) -> 136.47521 | J9: =F9-H9 -> 58.489376
B10: Workforce Annual Cost per Security Professional | F10: =IFERROR(F8*Inputs!$B$5,0) -> 189245.62 | H10: =IFERROR(H8*Inputs!$B$5,0) -> 132471.94 | J10: =F10-H10 -> 56773.687
B11: Total Weekly Hours of Coverage | F11: =_Calc_Backend!$X$36 -> 336 | H11: =F11 -> 336 | J11: =""
B12: Total Monthly Hours of Coverage | F12: =Post_Positions!$F$12 -> 1456 | H12: =F12 -> 1456 | J12: =""
B13: Total Annual Hours of Coverage | F13: =_Calc_Backend!$X$33 -> 3865.12 | H13: =F13 -> 3865.12 | J13: =""
B14: Total Weeks of Coverage | F14: =Post_Positions!$D$12 -> 336 | H14: =F14 -> 336 | J14: =""
B15: Total Annual Hours of Coverage | F15: =Post_Positions!$H$12 -> 17472 | H15: =F15 -> 17472 | J15: =""
B16: Total Workforce Required for Coverage | F16: =_Calc_Backend!$X$38 -> 12 | H16: =F16 -> 12 | J16: =""
B17: Total Weekly Cost | F17: =IFERROR(F11*F8,0) -> 43672.067 | H17: =IFERROR(H11*H8,0) -> 30570.447 | J17: =F17-H17 -> 13101.62
B18: Total Monthly Cost | F18: =IFERROR(F12*F8,0) -> 189245.62 | H18: =IFERROR(H12*H8,0) -> 132471.94 | J18: =F18-H18 -> 56773.687
B19: Total Annual Cost | F19: =IFERROR(F8*F15,0) -> 2270947.5 | H19: =IFERROR(H8*H15,0) -> 1589663.2 | J19: =F19-H19 -> 681284.25
B20: Operational Capital Recovered | F20: ="" | H20: =J19 -> 681284.25 | J20: =""
B21: Operational Capital Recovered (%) | F21: ="" | H21: =IFERROR(H20/F19,0) -> 0.3 | J21: =""
B22: Payback & Recovery Period | H22: =IFERROR(H19/F18,0) -> 8.4 | J22: =""
B24: Coverage Statement
B25: All price calculations include the full cost of workforce staffing and support services, including but not limited to: livable base wages, employer-paid payroll taxes (FICA, FUTA, SUTA), workers’ compensation, general liability insurance, unemployment insurance, paid time off, healthcare and fringe benefits, uniforms and equipment, onboarding and training, site supervision, quality assurance oversight, management and administrative support, 24/7 dispatch capability, compliance with local, state, and federal labor laws, and all service-level guarantees (including open post protection, vendor replacement, and price lock guarantees) unless otherwise specified.
B28: "CFO Tested. CFO Approved"
B29: (470) 633-2816 | info@getasecurityquote.com | getasecurityquotenow.com
B30: Key Components of the GetASecurityQuote Security Capital Recovery Report
B31: Direct Labor Costs
B32: • Wages: Hourly pay for each guard (based on market, union scale, or livable wage rates)
B33: • Overtime: If scheduling exceeds 40 hours/week per guard or during holidays
B34: • Paid Non-Worked Hours: Includes holidays, sick leave, vacation, training
B35: Mandatory Payroll Burden
B36: • Employer Taxes: FICA, FUTA, SUTA, Medicare
B37: • Workers’ Compensation Insurance: Risk-rated by job classification (high for security)
... B68: Notes:

Sheet Additional Cost
A1: GASQ Additional Cost Stack
A2: Merged view of Vehicle, Uniform & Equipment, and Workforce Maintenance costs
A4: Module | B4: Source Tab | C4: Hourly Cost | D4: Annual Cost
A5: Vehicle / Patrol | B5: Vehicle | C5: =Vehicle!$C$30 -> 3.5046454 | D5: =Vehicle!$C$29 -> 61233.164
A6: Uniform & Equipment | B6: Uniform_Equipment | C6: =Uniform_Equipment!$C$36 -> 1.1071394 | D6: =Uniform_Equipment!$C$35 -> 19343.94
A7: Workforce Maintenance | B7: Workforce_Maintenance_Module | C7: =IFERROR(Workforce_Maintenance_Module!$E$7/_Calc_Backend!$X$37,0) -> 0.86020147 | D7: =Workforce_Maintenance_Module!$E$7 -> 15029.44
A8: Training | B8: Training_Module | C8: =IFERROR(Training_Module!$J$9/_Calc_Backend!$X$37,0) -> 2.2161172 | D8: =Training_Module!$J$9 -> 38720
A9: Total Additional Cost | C9: =SUM(C5:C8) -> 7.6881035 | D9: =SUM(D5:D8) -> 134326.54
A11: Note | B11: Source tabs remain in the workbook for audit support. Additional Cost is the consolidated operating view.

Sheet Option Year
A1: GASQ Option Year Analysis
A2: Base Year + Option Years 1-4 with hourly and annual cost by line item
A3: Escalation Scenario | B3: Medium | D3: Custom Escalation % | E3: =Inputs!$B$56 -> 0.03 | G3: Base Annual Hours | H3: =Appraisal_Full_Scope_Report!$F$15 -> 17472
A4: Applied Escalation % | B4: =IF($B$3="Low",Inputs!$B$58,IF($B$3="High",Inputs!$B$60,IF($B$3="Custom",Inputs!$B$56,Inputs!$B$59))) -> 0.03 | D4: Vendor Benchmark $/Hr | E4: =Appraisal_Full_Scope_Report!$F$8 -> 129.97639 | G4: Appraisal Vendor $/Hr | H4: =Appraisal_Full_Scope_Report!$H$8 -> 90.983473
A6: Description | B6: Base $/Hr | C6: Base Annual | D6: Opt Yr 1 $/Hr | E6: Opt Yr 1 Annual | F6: Opt Yr 2 $/Hr | G6: Opt Yr 2 Annual | H6: Opt Yr 3 $/Hr | I6: Opt Yr 3 Annual | J6: Opt Yr 4 $/Hr | K6: Opt Yr 4 Annual | L6: Total Contract Value | M6: Total Contract Value Avg $/Hr
A7: Direct Labor
A8: =CFO_Bill_Rate_Breakdown!A5 -> Base Consolidated Blended Direct Labor Wage | B8: =CFO_Bill_Rate_Breakdown!B5 -> 33.74 | C8: =CFO_Bill_Rate_Breakdown!C5 -> 589505.28 | D8: =IF(Inputs!$C$64="Manual",IF(OR($B8="",Inputs!$B$65=0,Inputs!$C$65=""),"",$B8*(Inputs!$C$65/Inputs!$B$65)),IF(OR($B8="",$B8=0),"",$B8*(1+$B$4)^1)) -> 34.7522 | E8: =IF(OR(D8="",D8=0,Inputs!$C$71=""),"",D8*Inputs!$C$71) -> 607190.44 | F8: =IF(Inputs!$D$64="Manual",IF(OR($B8="",Inputs!$B$65=0,Inputs!$D$65=""),"",$B8*(Inputs!$D$65/Inputs!$B$65)),IF(OR($B8="",$B8=0),"",$B8*(1+$B$4)^2)) -> 35.794766 | G8: =IF(OR(F8="",F8=0,Inputs!$D$71=""),"",F8*Inputs!$D$71) -> 625406.15 | H8: =IF(Inputs!$E$64="Manual",IF(OR($B8="",Inputs!$B$65=0,Inputs!$E$65=""),"",$B8*(Inputs!$E$65/Inputs!$B$65)),IF(OR($B8="",$B8=0),"",$B8*(1+$B$4)^3)) -> 36.868609 | I8: =IF(OR(H8="",H8=0,Inputs!$E$71=""),"",H8*Inputs!$E$71) -> 644168.34 | J8: =IF(Inputs!$F$64="Manual",IF(OR($B8="",Inputs!$B$65=0,Inputs!$F$65=""),"",$B8*(Inputs!$F$65/Inputs!$B$65)),IF(OR($B8="",$B8=0),"",$B8*(1+$B$4)^4)) -> 37.974667 | K8: =IF(OR(J8="",J8=0,Inputs!$F$71=""),"",J8*Inputs!$F$71) -> 663493.39 | L8: =SUM(C8,E8,G8,I8,K8) -> 3129763.6 | M8: =AVERAGE(B8,D8,F8,H8,J8) -> 35.826048
A9: =CFO_Bill_Rate_Breakdown!A6 -> Locality Pay | B9: =CFO_Bill_Rate_Breakdown!B6 -> 0 | C9: =CFO_Bill_Rate_Breakdown!C6 -> 0 | D9: =IF(Inputs!$C$64="Manual",IF(OR($B9="",Inputs!$B$65=0,Inputs!$C$65=""),"",$B9*(Inputs!$C$65/Inputs!$B$65)),IF(OR($B9="",$B9=0),"",$B9*(1+$B$4)^1)) | E9: =IF(OR(D9="",D9=0,Inputs!$C$71=""),"",D9*Inputs!$C$71) | F9: =IF(Inputs!$D$64="Manual",IF(OR($B9="",Inputs!$B$65=0,Inputs!$D$65=""),"",$B9*(Inputs!$D$65/Inputs!$B$65)),IF(OR($B9="",$B9=0),"",$B9*(1+$B$4)^2)) | G9: =IF(OR(F9="",F9=0,Inputs!$D$71=""),"",F9*Inputs!$D$71) | H9: =IF(Inputs!$E$64="Manual",IF(OR($B9="",Inputs!$B$65=0,Inputs!$E$65=""),"",$B9*(Inputs!$E$65/Inputs!$B$65)),IF(OR($B9="",$B9=0),"",$B9*(1+$B$4)^3)) | I9: =IF(OR(H9="",H9=0,Inputs!$E$71=""),"",H9*Inputs!$E$71) | J9: =IF(Inputs!$F$64="Manual",IF(OR($B9="",Inputs!$B$65=0,Inputs!$F$65=""),"",$B9*(Inputs!$F$65/Inputs!$B$65)),IF(OR($B9="",$B9=0),"",$B9*(1+$B$4)^4)) | K9: =IF(OR(J9="",J9=0,Inputs!$F$71=""),"",J9*Inputs!$F$71) | L9: =SUM(C9,E9,G9,I9,K9) -> 0 | M9: =AVERAGE(B9,D9,F9,H9,J9) -> 0
A10: =CFO_Bill_Rate_Breakdown!A7 -> Labor Market Adjustment | B10: =CFO_Bill_Rate_Breakdown!B7 -> 0 | C10: =CFO_Bill_Rate_Breakdown!C7 -> 0 | D10: =IF(Inputs!$C$64="Manual",IF(OR($B10="",Inputs!$B$65=0,Inputs!$C$65=""),"",$B10*(Inputs!$C$65/Inputs!$B$65)),IF(OR($B10="",$B10=0),"",$B10*(1+$B$4)^1)) | E10: =IF(OR(D10="",D10=0,Inputs!$C$71=""),"",D10*Inputs!$C$71) | F10: =IF(Inputs!$D$64="Manual",IF(OR($B10="",Inputs!$B$65=0,Inputs!$D$65=""),"",$B10*(Inputs!$D$65/Inputs!$B$65)),IF(OR($B10="",$B10=0),"",$B10*(1+$B$4)^2)) | G10: =IF(OR(F10="",F10=0,Inputs!$D$71=""),"",F10*Inputs!$D$71) | H10: =IF(Inputs!$E$64="Manual",IF(OR($B10="",Inputs!$B$65=0,Inputs!$E$65=""),"",$B10*(Inputs!$E$65/Inputs!$B$65)),IF(OR($B10="",$B10=0),"",$B10*(1+$B$4)^3)) | I10: =IF(OR(H10="",H10=0,Inputs!$E$71=""),"",H10*Inputs!$E$71) | J10: =IF(Inputs!$F$64="Manual",IF(OR($B10="",Inputs!$B$65=0,Inputs!$F$65=""),"",$B10*(Inputs!$F$65/Inputs!$B$65)),IF(OR($B10="",$B10=0),"",$B10*(1+$B$4)^4)) | K10: =IF(OR(J10="",J10=0,Inputs!$F$71=""),"",J10*Inputs!$F$71) | L10: =SUM(C10,E10,G10,I10,K10) -> 0 | M10: =AVERAGE(B10,D10,F10,H10,J10) -> 0
A11: =CFO_Bill_Rate_Breakdown!A8 -> H&W (Cash) | B11: =CFO_Bill_Rate_Breakdown!B8 -> 4.22 | C11: =CFO_Bill_Rate_Breakdown!C8 -> 73731.84 | D11: =IF(Inputs!$C$64="Manual",IF(OR($B11="",Inputs!$B$65=0,Inputs!$C$65=""),"",$B11*(Inputs!$C$65/Inputs!$B$65)),IF(OR($B11="",$B11=0),"",$B11*(1+$B$4)^1)) -> 4.3466 | E11: =IF(OR(D11="",D11=0,Inputs!$C$71=""),"",D11*Inputs!$C$71) -> 75943.795 | F11: =IF(Inputs!$D$64="Manual",IF(OR($B11="",Inputs!$B$65=0,Inputs!$D$65=""),"",$B11*(Inputs!$D$65/Inputs!$B$65)),IF(OR($B11="",$B11=0),"",$B11*(1+$B$4)^2)) -> 4.476998 | G11: =IF(OR(F11="",F11=0,Inputs!$D$71=""),"",F11*Inputs!$D$71) -> 78222.109 | H11: =IF(Inputs!$E$64="Manual",IF(OR($B11="",Inputs!$B$65=0,Inputs!$E$65=""),"",$B11*(Inputs!$E$65/Inputs!$B$65)),IF(OR($B11="",$B11=0),"",$B11*(1+$B$4)^3)) -> 4.6113079 | I11: =IF(OR(H11="",H11=0,Inputs!$E$71=""),"",H11*Inputs!$E$71) -> 80568.772 | J11: =IF(Inputs!$F$64="Manual",IF(OR($B11="",Inputs!$B$65=0,Inputs!$F$65=""),"",$B11*(Inputs!$F$65/Inputs!$B$65)),IF(OR($B11="",$B11=0),"",$B11*(1+$B$4)^4)) -> 4.7496472 | K11: =IF(OR(J11="",J11=0,Inputs!$F$71=""),"",J11*Inputs!$F$71) -> 82985.835 | L11: =SUM(C11,E11,G11,I11,K11) -> 391452.35 | M11: =AVERAGE(B11,D11,F11,H11,J11) -> 4.4809106
A12: =CFO_Bill_Rate_Breakdown!A9 -> Shift Differential | B12: =CFO_Bill_Rate_Breakdown!B9 -> 0 | C12: =CFO_Bill_Rate_Breakdown!C9 -> 0 | D12: =IF(Inputs!$C$64="Manual",IF(OR($B12="",Inputs!$B$65=0,Inputs!$C$65=""),"",$B12*(Inputs!$C$65/Inputs!$B$65)),IF(OR($B12="",$B12=0),"",$B12*(1+$B$4)^1)) | E12: =IF(OR(D12="",D12=0,Inputs!$C$71=""),"",D12*Inputs!$C$71) | F12: =IF(Inputs!$D$64="Manual",IF(OR($B12="",Inputs!$B$65=0,Inputs!$D$65=""),"",$B12*(Inputs!$D$65/Inputs!$B$65)),IF(OR($B12="",$B12=0),"",$B12*(1+$B$4)^2)) | G12: =IF(OR(F12="",F12=0,Inputs!$D$71=""),"",F12*Inputs!$D$71) | H12: =IF(Inputs!$E$64="Manual",IF(OR($B12="",Inputs!$B$65=0,Inputs!$E$65=""),"",$B12*(Inputs!$E$65/Inputs!$B$65)),IF(OR($B12="",$B12=0),"",$B12*(1+$B$4)^3)) | I12: =IF(OR(H12="",H12=0,Inputs!$E$71=""),"",H12*Inputs!$E$71) | J12: =IF(Inputs!$F$64="Manual",IF(OR($B12="",Inputs!$B$65=0,Inputs!$F$65=""),"",$B12*(Inputs!$F$65/Inputs!$B$65)),IF(OR($B12="",$B12=0),"",$B12*(1+$B$4)^4)) | K12: =IF(OR(J12="",J12=0,Inputs!$F$71=""),"",J12*Inputs!$F$71) | L12: =SUM(C12,E12,G12,I12,K12) -> 0 | M12: =AVERAGE(B12,D12,F12,H12,J12) -> 0
A13: =CFO_Bill_Rate_Breakdown!A10 -> OT/Holiday Premium | B13: =CFO_Bill_Rate_Breakdown!B10 -> 2.6992 | C13: =CFO_Bill_Rate_Breakdown!C10 -> 47160.422 | D13: =IF(Inputs!$C$64="Manual",IF(OR($B13="",Inputs!$B$65=0,Inputs!$C$65=""),"",$B13*(Inputs!$C$65/Inputs!$B$65)),IF(OR($B13="",$B13=0),"",$B13*(1+$B$4)^1)) -> 2.780176 | E13: =IF(OR(D13="",D13=0,Inputs!$C$71=""),"",D13*Inputs!$C$71) -> 48575.235 | F13: =IF(Inputs!$D$64="Manual",IF(OR($B13="",Inputs!$B$65=0,Inputs!$D$65=""),"",$B13*(Inputs!$D$65/Inputs!$B$65)),IF(OR($B13="",$B13=0),"",$B13*(1+$B$4)^2)) -> 2.8635813 | G13: =IF(OR(F13="",F13=0,Inputs!$D$71=""),"",F13*Inputs!$D$71) -> 50032.492 | H13: =IF(Inputs!$E$64="Manual",IF(OR($B13="",Inputs!$B$65=0,Inputs!$E$65=""),"",$B13*(Inputs!$E$65/Inputs!$B$65)),IF(OR($B13="",$B13=0),"",$B13*(1+$B$4)^3)) -> 2.9494887 | I13: =IF(OR(H13="",H13=0,Inputs!$E$71=""),"",H13*Inputs!$E$71) -> 51533.467 | J13: =IF(Inputs!$F$64="Manual",IF(OR($B13="",Inputs!$B$65=0,Inputs!$F$65=""),"",$B13*(Inputs!$F$65/Inputs!$B$65)),IF(OR($B13="",$B13=0),"",$B13*(1+$B$4)^4)) -> 3.0379734 | K13: =IF(OR(J13="",J13=0,Inputs!$F$71=""),"",J13*Inputs!$F$71) -> 53079.471 | L13: =SUM(C13,E13,G13,I13,K13) -> 250381.09 | M13: =AVERAGE(B13,D13,F13,H13,J13) -> 2.8660839
A14: =CFO_Bill_Rate_Breakdown!A11 -> DON/DOFF | B14: =CFO_Bill_Rate_Breakdown!B11 -> 1.2706 | C14: =CFO_Bill_Rate_Breakdown!C11 -> 22199.923 | D14: =IF(Inputs!$C$64="Manual",IF(OR($B14="",Inputs!$B$65=0,Inputs!$C$65=""),"",$B14*(Inputs!$C$65/Inputs!$B$65)),IF(OR($B14="",$B14=0),"",$B14*(1+$B$4)^1)) -> 1.308718 | E14: =IF(OR(D14="",D14=0,Inputs!$C$71=""),"",D14*Inputs!$C$71) -> 22865.921 | F14: =IF(Inputs!$D$64="Manual",IF(OR($B14="",Inputs!$B$65=0,Inputs!$D$65=""),"",$B14*(Inputs!$D$65/Inputs!$B$65)),IF(OR($B14="",$B14=0),"",$B14*(1+$B$4)^2)) -> 1.3479795 | G14: =IF(OR(F14="",F14=0,Inputs!$D$71=""),"",F14*Inputs!$D$71) -> 23551.899 | H14: =IF(Inputs!$E$64="Manual",IF(OR($B14="",Inputs!$B$65=0,Inputs!$E$65=""),"",$B14*(Inputs!$E$65/Inputs!$B$65)),IF(OR($B14="",$B14=0),"",$B14*(1+$B$4)^3)) -> 1.3884189 | I14: =IF(OR(H14="",H14=0,Inputs!$E$71=""),"",H14*Inputs!$E$71) -> 24258.455 | J14: =IF(Inputs!$F$64="Manual",IF(OR($B14="",Inputs!$B$65=0,Inputs!$F$65=""),"",$B14*(Inputs!$F$65/Inputs!$B$65)),IF(OR($B14="",$B14=0),"",$B14*(1+$B$4)^4)) -> 1.4300715 | K14: =IF(OR(J14="",J14=0,Inputs!$F$71=""),"",J14*Inputs!$F$71) -> 24986.209 | L14: =SUM(C14,E14,G14,I14,K14) -> 117862.41 | M14: =AVERAGE(B14,D14,F14,H14,J14) -> 1.3491576
A15: =CFO_Bill_Rate_Breakdown!A12 -> Total Direct Labor | B15: =CFO_Bill_Rate_Breakdown!B12 -> 41.9298 | C15: =CFO_Bill_Rate_Breakdown!C12 -> 732597.47 | D15: =IF(Inputs!$C$64="Manual",IF(OR($B15="",Inputs!$B$65=0,Inputs!$C$65=""),"",$B15*(Inputs!$C$65/Inputs!$B$65)),IF(OR($B15="",$B15=0),"",$B15*(1+$B$4)^1)) -> 43.187694 | E15: =IF(OR(D15="",D15=0,Inputs!$C$71=""),"",D15*Inputs!$C$71) -> 754575.39 | F15: =IF(Inputs!$D$64="Manual",IF(OR($B15="",Inputs!$B$65=0,Inputs!$D$65=""),"",$B15*(Inputs!$D$65/Inputs!$B$65)),IF(OR($B15="",$B15=0),"",$B15*(1+$B$4)^2)) -> 44.483325 | G15: =IF(OR(F15="",F15=0,Inputs!$D$71=""),"",F15*Inputs!$D$71) -> 777212.65 | H15: =IF(Inputs!$E$64="Manual",IF(OR($B15="",Inputs!$B$65=0,Inputs!$E$65=""),"",$B15*(Inputs!$E$65/Inputs!$B$65)),IF(OR($B15="",$B15=0),"",$B15*(1+$B$4)^3)) -> 45.817825 | I15: =IF(OR(H15="",H15=0,Inputs!$E$71=""),"",H15*Inputs!$E$71) -> 800529.03 | J15: =IF(Inputs!$F$64="Manual",IF(OR($B15="",Inputs!$B$65=0,Inputs!$F$65=""),"",$B15*(Inputs!$F$65/Inputs!$B$65)),IF(OR($B15="",$B15=0),"",$B15*(1+$B$4)^4)) -> 47.192359 | K15: =IF(OR(J15="",J15=0,Inputs!$F$71=""),"",J15*Inputs!$F$71) -> 824544.9 | L15: =SUM(C15,E15,G15,I15,K15) -> 3889459.4 | M15: =AVERAGE(B15,D15,F15,H15,J15) -> 44.522201
A16: Fringe / Employer Burden
A17: =CFO_Bill_Rate_Breakdown!A15 -> FICA / Medicare | B17: =CFO_Bill_Rate_Breakdown!B15 -> 3.2076297 | C17: =CFO_Bill_Rate_Breakdown!C15 -> 56043.706 | D17: =IF(Inputs!$C$64="Manual",IF(OR($B17="",Inputs!$B$65=0,Inputs!$C$65=""),"",$B17*(Inputs!$C$65/Inputs!$B$65)),IF(OR($B17="",$B17=0),"",$B17*(1+$B$4)^1)) -> 3.3038586 | E17: =IF(OR(D17="",D17=0,Inputs!$C$71=""),"",D17*Inputs!$C$71) -> 57725.017 | F17: =IF(Inputs!$D$64="Manual",IF(OR($B17="",Inputs!$B$65=0,Inputs!$D$65=""),"",$B17*(Inputs!$D$65/Inputs!$B$65)),IF(OR($B17="",$B17=0),"",$B17*(1+$B$4)^2)) -> 3.4029743 | G17: =IF(OR(F17="",F17=0,Inputs!$D$71=""),"",F17*Inputs!$D$71) -> 59456.768 | H17: =IF(Inputs!$E$64="Manual",IF(OR($B17="",Inputs!$B$65=0,Inputs!$E$65=""),"",$B17*(Inputs!$E$65/Inputs!$B$65)),IF(OR($B17="",$B17=0),"",$B17*(1+$B$4)^3)) -> 3.5050636 | I17: =IF(OR(H17="",H17=0,Inputs!$E$71=""),"",H17*Inputs!$E$71) -> 61240.471 | J17: =IF(Inputs!$F$64="Manual",IF(OR($B17="",Inputs!$B$65=0,Inputs!$F$65=""),"",$B17*(Inputs!$F$65/Inputs!$B$65)),IF(OR($B17="",$B17=0),"",$B17*(1+$B$4)^4)) -> 3.6102155 | K17: =IF(OR(J17="",J17=0,Inputs!$F$71=""),"",J17*Inputs!$F$71) -> 63077.685 | L17: =SUM(C17,E17,G17,I17,K17) -> 297543.65 | M17: =AVERAGE(B17,D17,F17,H17,J17) -> 3.4059483
A18: =CFO_Bill_Rate_Breakdown!A16 -> FUTA | B18: =CFO_Bill_Rate_Breakdown!B16 -> 0.2515788 | C18: =CFO_Bill_Rate_Breakdown!C16 -> 4395.5848 | D18: =IF(Inputs!$C$64="Manual",IF(OR($B18="",Inputs!$B$65=0,Inputs!$C$65=""),"",$B18*(Inputs!$C$65/Inputs!$B$65)),IF(OR($B18="",$B18=0),"",$B18*(1+$B$4)^1)) -> 0.25912616 | E18: =IF(OR(D18="",D18=0,Inputs!$C$71=""),"",D18*Inputs!$C$71) -> 4527.4523 | F18: =IF(Inputs!$D$64="Manual",IF(OR($B18="",Inputs!$B$65=0,Inputs!$D$65=""),"",$B18*(Inputs!$D$65/Inputs!$B$65)),IF(OR($B18="",$B18=0),"",$B18*(1+$B$4)^2)) -> 0.26689995 | G18: =IF(OR(F18="",F18=0,Inputs!$D$71=""),"",F18*Inputs!$D$71) -> 4663.2759 | H18: =IF(Inputs!$E$64="Manual",IF(OR($B18="",Inputs!$B$65=0,Inputs!$E$65=""),"",$B18*(Inputs!$E$65/Inputs!$B$65)),IF(OR($B18="",$B18=0),"",$B18*(1+$B$4)^3)) -> 0.27490695 | I18: =IF(OR(H18="",H18=0,Inputs!$E$71=""),"",H18*Inputs!$E$71) -> 4803.1742 | J18: =IF(Inputs!$F$64="Manual",IF(OR($B18="",Inputs!$B$65=0,Inputs!$F$65=""),"",$B18*(Inputs!$F$65/Inputs!$B$65)),IF(OR($B18="",$B18=0),"",$B18*(1+$B$4)^4)) -> 0.28315416 | K18: =IF(OR(J18="",J18=0,Inputs!$F$71=""),"",J18*Inputs!$F$71) -> 4947.2694 | L18: =SUM(C18,E18,G18,I18,K18) -> 23336.757 | M18: =AVERAGE(B18,D18,F18,H18,J18) -> 0.2671332
A19: =CFO_Bill_Rate_Breakdown!A17 -> SUTA | B19: =CFO_Bill_Rate_Breakdown!B17 -> 0.838596 | C19: =CFO_Bill_Rate_Breakdown!C17 -> 14651.949 | D19: =IF(Inputs!$C$64="Manual",IF(OR($B19="",Inputs!$B$65=0,Inputs!$C$65=""),"",$B19*(Inputs!$C$65/Inputs!$B$65)),IF(OR($B19="",$B19=0),"",$B19*(1+$B$4)^1)) -> 0.86375388 | E19: =IF(OR(D19="",D19=0,Inputs!$C$71=""),"",D19*Inputs!$C$71) -> 15091.508 | F19: =IF(Inputs!$D$64="Manual",IF(OR($B19="",Inputs!$B$65=0,Inputs!$D$65=""),"",$B19*(Inputs!$D$65/Inputs!$B$65)),IF(OR($B19="",$B19=0),"",$B19*(1+$B$4)^2)) -> 0.8896665 | G19: =IF(OR(F19="",F19=0,Inputs!$D$71=""),"",F19*Inputs!$D$71) -> 15544.253 | H19: =IF(Inputs!$E$64="Manual",IF(OR($B19="",Inputs!$B$65=0,Inputs!$E$65=""),"",$B19*(Inputs!$E$65/Inputs!$B$65)),IF(OR($B19="",$B19=0),"",$B19*(1+$B$4)^3)) -> 0.91635649 | I19: =IF(OR(H19="",H19=0,Inputs!$E$71=""),"",H19*Inputs!$E$71) -> 16010.581 | J19: =IF(Inputs!$F$64="Manual",IF(OR($B19="",Inputs!$B$65=0,Inputs!$F$65=""),"",$B19*(Inputs!$F$65/Inputs!$B$65)),IF(OR($B19="",$B19=0),"",$B19*(1+$B$4)^4)) -> 0.94384719 | K19: =IF(OR(J19="",J19=0,Inputs!$F$71=""),"",J19*Inputs!$F$71) -> 16490.898 | L19: =SUM(C19,E19,G19,I19,K19) -> 77789.189 | M19: =AVERAGE(B19,D19,F19,H19,J19) -> 0.89044401
A20: =CFO_Bill_Rate_Breakdown!A18 -> Workers Compensation | B20: =CFO_Bill_Rate_Breakdown!B18 -> 0.6708768 | C20: =CFO_Bill_Rate_Breakdown!C18 -> 11721.559 | D20: =IF(Inputs!$C$64="Manual",IF(OR($B20="",Inputs!$B$65=0,Inputs!$C$65=""),"",$B20*(Inputs!$C$65/Inputs!$B$65)),IF(OR($B20="",$B20=0),"",$B20*(1+$B$4)^1)) -> 0.6910031 | E20: =IF(OR(D20="",D20=0,Inputs!$C$71=""),"",D20*Inputs!$C$71) -> 12073.206 | F20: =IF(Inputs!$D$64="Manual",IF(OR($B20="",Inputs!$B$65=0,Inputs!$D$65=""),"",$B20*(Inputs!$D$65/Inputs!$B$65)),IF(OR($B20="",$B20=0),"",$B20*(1+$B$4)^2)) -> 0.7117332 | G20: =IF(OR(F20="",F20=0,Inputs!$D$71=""),"",F20*Inputs!$D$71) -> 12435.402 | H20: =IF(Inputs!$E$64="Manual",IF(OR($B20="",Inputs!$B$65=0,Inputs!$E$65=""),"",$B20*(Inputs!$E$65/Inputs!$B$65)),IF(OR($B20="",$B20=0),"",$B20*(1+$B$4)^3)) -> 0.73308519 | I20: =IF(OR(H20="",H20=0,Inputs!$E$71=""),"",H20*Inputs!$E$71) -> 12808.464 | J20: =IF(Inputs!$F$64="Manual",IF(OR($B20="",Inputs!$B$65=0,Inputs!$F$65=""),"",$B20*(Inputs!$F$65/Inputs!$B$65)),IF(OR($B20="",$B20=0),"",$B20*(1+$B$4)^4)) -> 0.75507775 | K20: =IF(OR(J20="",J20=0,Inputs!$F$71=""),"",J20*Inputs!$F$71) -> 13192.718 | L20: =SUM(C20,E20,G20,I20,K20) -> 62231.351 | M20: =AVERAGE(B20,D20,F20,H20,J20) -> 0.71235521
A21: =CFO_Bill_Rate_Breakdown!A19 -> Health & Welfare | B21: =CFO_Bill_Rate_Breakdown!B19 -> 0 | C21: =CFO_Bill_Rate_Breakdown!C19 -> 0 | D21: =IF(Inputs!$C$64="Manual",IF(OR($B21="",Inputs!$B$65=0,Inputs!$C$65=""),"",$B21*(Inputs!$C$65/Inputs!$B$65)),IF(OR($B21="",$B21=0),"",$B21*(1+$B$4)^1)) | E21: =IF(OR(D21="",D21=0,Inputs!$C$71=""),"",D21*Inputs!$C$71) | F21: =IF(Inputs!$D$64="Manual",IF(OR($B21="",Inputs!$B$65=0,Inputs!$D$65=""),"",$B21*(Inputs!$D$65/Inputs!$B$65)),IF(OR($B21="",$B21=0),"",$B21*(1+$B$4)^2)) | G21: =IF(OR(F21="",F21=0,Inputs!$D$71=""),"",F21*Inputs!$D$71) | H21: =IF(Inputs!$E$64="Manual",IF(OR($B21="",Inputs!$B$65=0,Inputs!$E$65=""),"",$B21*(Inputs!$E$65/Inputs!$B$65)),IF(OR($B21="",$B21=0),"",$B21*(1+$B$4)^3)) | I21: =IF(OR(H21="",H21=0,Inputs!$E$71=""),"",H21*Inputs!$E$71) | J21: =IF(Inputs!$F$64="Manual",IF(OR($B21="",Inputs!$B$65=0,Inputs!$F$65=""),"",$B21*(Inputs!$F$65/Inputs!$B$65)),IF(OR($B21="",$B21=0),"",$B21*(1+$B$4)^4)) | K21: =IF(OR(J21="",J21=0,Inputs!$F$71=""),"",J21*Inputs!$F$71) | L21: =SUM(C21,E21,G21,I21,K21) -> 0 | M21: =AVERAGE(B21,D21,F21,H21,J21) -> 0
A22: =CFO_Bill_Rate_Breakdown!A20 -> Vacation | B22: =CFO_Bill_Rate_Breakdown!B20 -> 0.838596 | C22: =CFO_Bill_Rate_Breakdown!C20 -> 14651.949 | D22: =IF(Inputs!$C$64="Manual",IF(OR($B22="",Inputs!$B$65=0,Inputs!$C$65=""),"",$B22*(Inputs!$C$65/Inputs!$B$65)),IF(OR($B22="",$B22=0),"",$B22*(1+$B$4)^1)) -> 0.86375388 | E22: =IF(OR(D22="",D22=0,Inputs!$C$71=""),"",D22*Inputs!$C$71) -> 15091.508 | F22: =IF(Inputs!$D$64="Manual",IF(OR($B22="",Inputs!$B$65=0,Inputs!$D$65=""),"",$B22*(Inputs!$D$65/Inputs!$B$65)),IF(OR($B22="",$B22=0),"",$B22*(1+$B$4)^2)) -> 0.8896665 | G22: =IF(OR(F22="",F22=0,Inputs!$D$71=""),"",F22*Inputs!$D$71) -> 15544.253 | H22: =IF(Inputs!$E$64="Manual",IF(OR($B22="",Inputs!$B$65=0,Inputs!$E$65=""),"",$B22*(Inputs!$E$65/Inputs!$B$65)),IF(OR($B22="",$B22=0),"",$B22*(1+$B$4)^3)) -> 0.91635649 | I22: =IF(OR(H22="",H22=0,Inputs!$E$71=""),"",H22*Inputs!$E$71) -> 16010.581 | J22: =IF(Inputs!$F$64="Manual",IF(OR($B22="",Inputs!$B$65=0,Inputs!$F$65=""),"",$B22*(Inputs!$F$65/Inputs!$B$65)),IF(OR($B22="",$B22=0),"",$B22*(1+$B$4)^4)) -> 0.94384719 | K22: =IF(OR(J22="",J22=0,Inputs!$F$71=""),"",J22*Inputs!$F$71) -> 16490.898 | L22: =SUM(C22,E22,G22,I22,K22) -> 77789.189 | M22: =AVERAGE(B22,D22,F22,H22,J22) -> 0.89044401
A23: =CFO_Bill_Rate_Breakdown!A21 -> Paid Holidays | B23: =CFO_Bill_Rate_Breakdown!B21 -> 1.677192 | C23: =CFO_Bill_Rate_Breakdown!C21 -> 29303.899 | D23: =IF(Inputs!$C$64="Manual",IF(OR($B23="",Inputs!$B$65=0,Inputs!$C$65=""),"",$B23*(Inputs!$C$65/Inputs!$B$65)),IF(OR($B23="",$B23=0),"",$B23*(1+$B$4)^1)) -> 1.7275078 | E23: =IF(OR(D23="",D23=0,Inputs!$C$71=""),"",D23*Inputs!$C$71) -> 30183.016 | F23: =IF(Inputs!$D$64="Manual",IF(OR($B23="",Inputs!$B$65=0,Inputs!$D$65=""),"",$B23*(Inputs!$D$65/Inputs!$B$65)),IF(OR($B23="",$B23=0),"",$B23*(1+$B$4)^2)) -> 1.779333 | G23: =IF(OR(F23="",F23=0,Inputs!$D$71=""),"",F23*Inputs!$D$71) -> 31088.506 | H23: =IF(Inputs!$E$64="Manual",IF(OR($B23="",Inputs!$B$65=0,Inputs!$E$65=""),"",$B23*(Inputs!$E$65/Inputs!$B$65)),IF(OR($B23="",$B23=0),"",$B23*(1+$B$4)^3)) -> 1.832713 | I23: =IF(OR(H23="",H23=0,Inputs!$E$71=""),"",H23*Inputs!$E$71) -> 32021.161 | J23: =IF(Inputs!$F$64="Manual",IF(OR($B23="",Inputs!$B$65=0,Inputs!$F$65=""),"",$B23*(Inputs!$F$65/Inputs!$B$65)),IF(OR($B23="",$B23=0),"",$B23*(1+$B$4)^4)) -> 1.8876944 | K23: =IF(OR(J23="",J23=0,Inputs!$F$71=""),"",J23*Inputs!$F$71) -> 32981.796 | L23: =SUM(C23,E23,G23,I23,K23) -> 155578.38 | M23: =AVERAGE(B23,D23,F23,H23,J23) -> 1.780888
A24: =CFO_Bill_Rate_Breakdown!A22 -> Sick Leave | B24: =CFO_Bill_Rate_Breakdown!B22 -> 1.1321046 | C24: =CFO_Bill_Rate_Breakdown!C22 -> 19780.132 | D24: =IF(Inputs!$C$64="Manual",IF(OR($B24="",Inputs!$B$65=0,Inputs!$C$65=""),"",$B24*(Inputs!$C$65/Inputs!$B$65)),IF(OR($B24="",$B24=0),"",$B24*(1+$B$4)^1)) -> 1.1660677 | E24: =IF(OR(D24="",D24=0,Inputs!$C$71=""),"",D24*Inputs!$C$71) -> 20373.536 | F24: =IF(Inputs!$D$64="Manual",IF(OR($B24="",Inputs!$B$65=0,Inputs!$D$65=""),"",$B24*(Inputs!$D$65/Inputs!$B$65)),IF(OR($B24="",$B24=0),"",$B24*(1+$B$4)^2)) -> 1.2010498 | G24: =IF(OR(F24="",F24=0,Inputs!$D$71=""),"",F24*Inputs!$D$71) -> 20984.742 | H24: =IF(Inputs!$E$64="Manual",IF(OR($B24="",Inputs!$B$65=0,Inputs!$E$65=""),"",$B24*(Inputs!$E$65/Inputs!$B$65)),IF(OR($B24="",$B24=0),"",$B24*(1+$B$4)^3)) -> 1.2370813 | I24: =IF(OR(H24="",H24=0,Inputs!$E$71=""),"",H24*Inputs!$E$71) -> 21614.284 | J24: =IF(Inputs!$F$64="Manual",IF(OR($B24="",Inputs!$B$65=0,Inputs!$F$65=""),"",$B24*(Inputs!$F$65/Inputs!$B$65)),IF(OR($B24="",$B24=0),"",$B24*(1+$B$4)^4)) -> 1.2741937 | K24: =IF(OR(J24="",J24=0,Inputs!$F$71=""),"",J24*Inputs!$F$71) -> 22262.712 | L24: =SUM(C24,E24,G24,I24,K24) -> 105015.4 | M24: =AVERAGE(B24,D24,F24,H24,J24) -> 1.2020994
A25: =CFO_Bill_Rate_Breakdown!A23 -> Total Fringe / Burden | B25: =CFO_Bill_Rate_Breakdown!B23 -> 8.6165739 | C25: =CFO_Bill_Rate_Breakdown!C23 -> 150548.78 | D25: =IF(Inputs!$C$64="Manual",IF(OR($B25="",Inputs!$B$65=0,Inputs!$C$65=""),"",$B25*(Inputs!$C$65/Inputs!$B$65)),IF(OR($B25="",$B25=0),"",$B25*(1+$B$4)^1)) -> 8.8750711 | E25: =IF(OR(D25="",D25=0,Inputs!$C$71=""),"",D25*Inputs!$C$71) -> 155065.24 | F25: =IF(Inputs!$D$64="Manual",IF(OR($B25="",Inputs!$B$65=0,Inputs!$D$65=""),"",$B25*(Inputs!$D$65/Inputs!$B$65)),IF(OR($B25="",$B25=0),"",$B25*(1+$B$4)^2)) -> 9.1413233 | G25: =IF(OR(F25="",F25=0,Inputs!$D$71=""),"",F25*Inputs!$D$71) -> 159717.2 | H25: =IF(Inputs!$E$64="Manual",IF(OR($B25="",Inputs!$B$65=0,Inputs!$E$65=""),"",$B25*(Inputs!$E$65/Inputs!$B$65)),IF(OR($B25="",$B25=0),"",$B25*(1+$B$4)^3)) -> 9.4155629 | I25: =IF(OR(H25="",H25=0,Inputs!$E$71=""),"",H25*Inputs!$E$71) -> 164508.72 | J25: =IF(Inputs!$F$64="Manual",IF(OR($B25="",Inputs!$B$65=0,Inputs!$F$65=""),"",$B25*(Inputs!$F$65/Inputs!$B$65)),IF(OR($B25="",$B25=0),"",$B25*(1+$B$4)^4)) -> 9.6980298 | K25: =IF(OR(J25="",J25=0,Inputs!$F$71=""),"",J25*Inputs!$F$71) -> 169443.98 | L25: =SUM(C25,E25,G25,I25,K25) -> 799283.91 | M25: =AVERAGE(B25,D25,F25,H25,J25) -> 9.1493122
A26: =CFO_Bill_Rate_Breakdown!A24 -> Total Direct Labor + Fringe | B26: =CFO_Bill_Rate_Breakdown!B24 -> 50.546374 | C26: =CFO_Bill_Rate_Breakdown!C24 -> 883146.24 | D26: =IF(Inputs!$C$64="Manual",IF(OR($B26="",Inputs!$B$65=0,Inputs!$C$65=""),"",$B26*(Inputs!$C$65/Inputs!$B$65)),IF(OR($B26="",$B26=0),"",$B26*(1+$B$4)^1)) -> 52.062765 | E26: =IF(OR(D26="",D26=0,Inputs!$C$71=""),"",D26*Inputs!$C$71) -> 909640.63 | F26: =IF(Inputs!$D$64="Manual",IF(OR($B26="",Inputs!$B$65=0,Inputs!$D$65=""),"",$B26*(Inputs!$D$65/Inputs!$B$65)),IF(OR($B26="",$B26=0),"",$B26*(1+$B$4)^2)) -> 53.624648 | G26: =IF(OR(F26="",F26=0,Inputs!$D$71=""),"",F26*Inputs!$D$71) -> 936929.85 | H26: =IF(Inputs!$E$64="Manual",IF(OR($B26="",Inputs!$B$65=0,Inputs!$E$65=""),"",$B26*(Inputs!$E$65/Inputs!$B$65)),IF(OR($B26="",$B26=0),"",$B26*(1+$B$4)^3)) -> 55.233388 | I26: =IF(OR(H26="",H26=0,Inputs!$E$71=""),"",H26*Inputs!$E$71) -> 965037.75 | J26: =IF(Inputs!$F$64="Manual",IF(OR($B26="",Inputs!$B$65=0,Inputs!$F$65=""),"",$B26*(Inputs!$F$65/Inputs!$B$65)),IF(OR($B26="",$B26=0),"",$B26*(1+$B$4)^4)) -> 56.890389 | K26: =IF(OR(J26="",J26=0,Inputs!$F$71=""),"",J26*Inputs!$F$71) -> 993988.88 | L26: =SUM(C26,E26,G26,I26,K26) -> 4688743.4 | M26: =AVERAGE(B26,D26,F26,H26,J26) -> 53.671513
A27: Operations / Support | L27: =IFERROR(SUM(C27:G27),0) -> 0 | M27: =IFERROR(L27/H27,0) -> 0
A28: =CFO_Bill_Rate_Breakdown!A27 -> Recruiting / Hiring | B28: =CFO_Bill_Rate_Breakdown!B27 -> 0 | C28: =CFO_Bill_Rate_Breakdown!C27 -> 0 | D28: =IF(Inputs!$C$64="Manual",IF(OR($B28="",Inputs!$B$65=0,Inputs!$C$65=""),"",$B28*(Inputs!$C$65/Inputs!$B$65)),IF(OR($B28="",$B28=0),"",$B28*(1+$B$4)^1)) | E28: =IF(OR(D28="",D28=0,Inputs!$C$71=""),"",D28*Inputs!$C$71) | F28: =IF(Inputs!$D$64="Manual",IF(OR($B28="",Inputs!$B$65=0,Inputs!$D$65=""),"",$B28*(Inputs!$D$65/Inputs!$B$65)),IF(OR($B28="",$B28=0),"",$B28*(1+$B$4)^2)) | G28: =IF(OR(F28="",F28=0,Inputs!$D$71=""),"",F28*Inputs!$D$71) | H28: =IF(Inputs!$E$64="Manual",IF(OR($B28="",Inputs!$B$65=0,Inputs!$E$65=""),"",$B28*(Inputs!$E$65/Inputs!$B$65)),IF(OR($B28="",$B28=0),"",$B28*(1+$B$4)^3)) | I28: =IF(OR(H28="",H28=0,Inputs!$E$71=""),"",H28*Inputs!$E$71) | J28: =IF(Inputs!$F$64="Manual",IF(OR($B28="",Inputs!$B$65=0,Inputs!$F$65=""),"",$B28*(Inputs!$F$65/Inputs!$B$65)),IF(OR($B28="",$B28=0),"",$B28*(1+$B$4)^4)) | K28: =IF(OR(J28="",J28=0,Inputs!$F$71=""),"",J28*Inputs!$F$71) | L28: =SUM(C28,E28,G28,I28,K28) -> 0 | M28: =AVERAGE(B28,D28,F28,H28,J28) -> 0
A29: =CFO_Bill_Rate_Breakdown!A28 -> Training / Certification | B29: =CFO_Bill_Rate_Breakdown!B28 -> 0.628947 | C29: =CFO_Bill_Rate_Breakdown!C28 -> 10988.962 | D29: =IF(Inputs!$C$64="Manual",IF(OR($B29="",Inputs!$B$65=0,Inputs!$C$65=""),"",$B29*(Inputs!$C$65/Inputs!$B$65)),IF(OR($B29="",$B29=0),"",$B29*(1+$B$4)^1)) -> 0.64781541 | E29: =IF(OR(D29="",D29=0,Inputs!$C$71=""),"",D29*Inputs!$C$71) -> 11318.631 | F29: =IF(Inputs!$D$64="Manual",IF(OR($B29="",Inputs!$B$65=0,Inputs!$D$65=""),"",$B29*(Inputs!$D$65/Inputs!$B$65)),IF(OR($B29="",$B29=0),"",$B29*(1+$B$4)^2)) -> 0.66724987 | G29: =IF(OR(F29="",F29=0,Inputs!$D$71=""),"",F29*Inputs!$D$71) -> 11658.19 | H29: =IF(Inputs!$E$64="Manual",IF(OR($B29="",Inputs!$B$65=0,Inputs!$E$65=""),"",$B29*(Inputs!$E$65/Inputs!$B$65)),IF(OR($B29="",$B29=0),"",$B29*(1+$B$4)^3)) -> 0.68726737 | I29: =IF(OR(H29="",H29=0,Inputs!$E$71=""),"",H29*Inputs!$E$71) -> 12007.935 | J29: =IF(Inputs!$F$64="Manual",IF(OR($B29="",Inputs!$B$65=0,Inputs!$F$65=""),"",$B29*(Inputs!$F$65/Inputs!$B$65)),IF(OR($B29="",$B29=0),"",$B29*(1+$B$4)^4)) -> 0.70788539 | K29: =IF(OR(J29="",J29=0,Inputs!$F$71=""),"",J29*Inputs!$F$71) -> 12368.174 | L29: =SUM(C29,E29,G29,I29,K29) -> 58341.892 | M29: =AVERAGE(B29,D29,F29,H29,J29) -> 0.66783301
A30: =CFO_Bill_Rate_Breakdown!A29 -> Uniforms / Equipment | B30: =CFO_Bill_Rate_Breakdown!B29 -> 1.1071394 | C30: =CFO_Bill_Rate_Breakdown!C29 -> 19343.94 | D30: =IF(Inputs!$C$64="Manual",IF(OR($B30="",Inputs!$B$65=0,Inputs!$C$65=""),"",$B30*(Inputs!$C$65/Inputs!$B$65)),IF(OR($B30="",$B30=0),"",$B30*(1+$B$4)^1)) -> 1.1403536 | E30: =IF(OR(D30="",D30=0,Inputs!$C$71=""),"",D30*Inputs!$C$71) -> 19924.258 | F30: =IF(Inputs!$D$64="Manual",IF(OR($B30="",Inputs!$B$65=0,Inputs!$D$65=""),"",$B30*(Inputs!$D$65/Inputs!$B$65)),IF(OR($B30="",$B30=0),"",$B30*(1+$B$4)^2)) -> 1.1745642 | G30: =IF(OR(F30="",F30=0,Inputs!$D$71=""),"",F30*Inputs!$D$71) -> 20521.986 | H30: =IF(Inputs!$E$64="Manual",IF(OR($B30="",Inputs!$B$65=0,Inputs!$E$65=""),"",$B30*(Inputs!$E$65/Inputs!$B$65)),IF(OR($B30="",$B30=0),"",$B30*(1+$B$4)^3)) -> 1.2098011 | I30: =IF(OR(H30="",H30=0,Inputs!$E$71=""),"",H30*Inputs!$E$71) -> 21137.646 | J30: =IF(Inputs!$F$64="Manual",IF(OR($B30="",Inputs!$B$65=0,Inputs!$F$65=""),"",$B30*(Inputs!$F$65/Inputs!$B$65)),IF(OR($B30="",$B30=0),"",$B30*(1+$B$4)^4)) -> 1.2460952 | K30: =IF(OR(J30="",J30=0,Inputs!$F$71=""),"",J30*Inputs!$F$71) -> 21771.775 | L30: =SUM(C30,E30,G30,I30,K30) -> 102699.6 | M30: =AVERAGE(B30,D30,F30,H30,J30) -> 1.1755907
A31: =CFO_Bill_Rate_Breakdown!A30 -> Field Supervision | B31: =CFO_Bill_Rate_Breakdown!B30 -> 0 | C31: =CFO_Bill_Rate_Breakdown!C30 -> 0 | D31: =IF(Inputs!$C$64="Manual",IF(OR($B31="",Inputs!$B$65=0,Inputs!$C$65=""),"",$B31*(Inputs!$C$65/Inputs!$B$65)),IF(OR($B31="",$B31=0),"",$B31*(1+$B$4)^1)) | E31: =IF(OR(D31="",D31=0,Inputs!$C$71=""),"",D31*Inputs!$C$71) | F31: =IF(Inputs!$D$64="Manual",IF(OR($B31="",Inputs!$B$65=0,Inputs!$D$65=""),"",$B31*(Inputs!$D$65/Inputs!$B$65)),IF(OR($B31="",$B31=0),"",$B31*(1+$B$4)^2)) | G31: =IF(OR(F31="",F31=0,Inputs!$D$71=""),"",F31*Inputs!$D$71) | H31: =IF(Inputs!$E$64="Manual",IF(OR($B31="",Inputs!$B$65=0,Inputs!$E$65=""),"",$B31*(Inputs!$E$65/Inputs!$B$65)),IF(OR($B31="",$B31=0),"",$B31*(1+$B$4)^3)) | I31: =IF(OR(H31="",H31=0,Inputs!$E$71=""),"",H31*Inputs!$E$71) | J31: =IF(Inputs!$F$64="Manual",IF(OR($B31="",Inputs!$B$65=0,Inputs!$F$65=""),"",$B31*(Inputs!$F$65/Inputs!$B$65)),IF(OR($B31="",$B31=0),"",$B31*(1+$B$4)^4)) | K31: =IF(OR(J31="",J31=0,Inputs!$F$71=""),"",J31*Inputs!$F$71) | L31: =SUM(C31,E31,G31,I31,K31) -> 0 | M31: =AVERAGE(B31,D31,F31,H31,J31) -> 0
A32: =CFO_Bill_Rate_Breakdown!A31 -> Contract Management | B32: =CFO_Bill_Rate_Breakdown!B31 -> 0 | C32: =CFO_Bill_Rate_Breakdown!C31 -> 0 | D32: =IF(Inputs!$C$64="Manual",IF(OR($B32="",Inputs!$B$65=0,Inputs!$C$65=""),"",$B32*(Inputs!$C$65/Inputs!$B$65)),IF(OR($B32="",$B32=0),"",$B32*(1+$B$4)^1)) | E32: =IF(OR(D32="",D32=0,Inputs!$C$71=""),"",D32*Inputs!$C$71) | F32: =IF(Inputs!$D$64="Manual",IF(OR($B32="",Inputs!$B$65=0,Inputs!$D$65=""),"",$B32*(Inputs!$D$65/Inputs!$B$65)),IF(OR($B32="",$B32=0),"",$B32*(1+$B$4)^2)) | G32: =IF(OR(F32="",F32=0,Inputs!$D$71=""),"",F32*Inputs!$D$71) | H32: =IF(Inputs!$E$64="Manual",IF(OR($B32="",Inputs!$B$65=0,Inputs!$E$65=""),"",$B32*(Inputs!$E$65/Inputs!$B$65)),IF(OR($B32="",$B32=0),"",$B32*(1+$B$4)^3)) | I32: =IF(OR(H32="",H32=0,Inputs!$E$71=""),"",H32*Inputs!$E$71) | J32: =IF(Inputs!$F$64="Manual",IF(OR($B32="",Inputs!$B$65=0,Inputs!$F$65=""),"",$B32*(Inputs!$F$65/Inputs!$B$65)),IF(OR($B32="",$B32=0),"",$B32*(1+$B$4)^4)) | K32: =IF(OR(J32="",J32=0,Inputs!$F$71=""),"",J32*Inputs!$F$71) | L32: =SUM(C32,E32,G32,I32,K32) -> 0 | M32: =AVERAGE(B32,D32,F32,H32,J32) -> 0
A33: =CFO_Bill_Rate_Breakdown!A32 -> Quality Assurance | B33: =CFO_Bill_Rate_Breakdown!B32 -> 0 | C33: =CFO_Bill_Rate_Breakdown!C32 -> 0 | D33: =IF(Inputs!$C$64="Manual",IF(OR($B33="",Inputs!$B$65=0,Inputs!$C$65=""),"",$B33*(Inputs!$C$65/Inputs!$B$65)),IF(OR($B33="",$B33=0),"",$B33*(1+$B$4)^1)) | E33: =IF(OR(D33="",D33=0,Inputs!$C$71=""),"",D33*Inputs!$C$71) | F33: =IF(Inputs!$D$64="Manual",IF(OR($B33="",Inputs!$B$65=0,Inputs!$D$65=""),"",$B33*(Inputs!$D$65/Inputs!$B$65)),IF(OR($B33="",$B33=0),"",$B33*(1+$B$4)^2)) | G33: =IF(OR(F33="",F33=0,Inputs!$D$71=""),"",F33*Inputs!$D$71) | H33: =IF(Inputs!$E$64="Manual",IF(OR($B33="",Inputs!$B$65=0,Inputs!$E$65=""),"",$B33*(Inputs!$E$65/Inputs!$B$65)),IF(OR($B33="",$B33=0),"",$B33*(1+$B$4)^3)) | I33: =IF(OR(H33="",H33=0,Inputs!$E$71=""),"",H33*Inputs!$E$71) | J33: =IF(Inputs!$F$64="Manual",IF(OR($B33="",Inputs!$B$65=0,Inputs!$F$65=""),"",$B33*(Inputs!$F$65/Inputs!$B$65)),IF(OR($B33="",$B33=0),"",$B33*(1+$B$4)^4)) | K33: =IF(OR(J33="",J33=0,Inputs!$F$71=""),"",J33*Inputs!$F$71) | L33: =SUM(C33,E33,G33,I33,K33) -> 0 | M33: =AVERAGE(B33,D33,F33,H33,J33) -> 0
A34: =CFO_Bill_Rate_Breakdown!A33 -> Vehicles / Patrol | B34: =CFO_Bill_Rate_Breakdown!B33 -> 3.5046454 | C34: =CFO_Bill_Rate_Breakdown!C33 -> 61233.164 | D34: =IF(Inputs!$C$64="Manual",IF(OR($B34="",Inputs!$B$65=0,Inputs!$C$65=""),"",$B34*(Inputs!$C$65/Inputs!$B$65)),IF(OR($B34="",$B34=0),"",$B34*(1+$B$4)^1)) -> 3.6097847 | E34: =IF(OR(D34="",D34=0,Inputs!$C$71=""),"",D34*Inputs!$C$71) -> 63070.159 | F34: =IF(Inputs!$D$64="Manual",IF(OR($B34="",Inputs!$B$65=0,Inputs!$D$65=""),"",$B34*(Inputs!$D$65/Inputs!$B$65)),IF(OR($B34="",$B34=0),"",$B34*(1+$B$4)^2)) -> 3.7180783 | G34: =IF(OR(F34="",F34=0,Inputs!$D$71=""),"",F34*Inputs!$D$71) -> 64962.263 | H34: =IF(Inputs!$E$64="Manual",IF(OR($B34="",Inputs!$B$65=0,Inputs!$E$65=""),"",$B34*(Inputs!$E$65/Inputs!$B$65)),IF(OR($B34="",$B34=0),"",$B34*(1+$B$4)^3)) -> 3.8296206 | I34: =IF(OR(H34="",H34=0,Inputs!$E$71=""),"",H34*Inputs!$E$71) -> 66911.131 | J34: =IF(Inputs!$F$64="Manual",IF(OR($B34="",Inputs!$B$65=0,Inputs!$F$65=""),"",$B34*(Inputs!$F$65/Inputs!$B$65)),IF(OR($B34="",$B34=0),"",$B34*(1+$B$4)^4)) -> 3.9445092 | K34: =IF(OR(J34="",J34=0,Inputs!$F$71=""),"",J34*Inputs!$F$71) -> 68918.465 | L34: =SUM(C34,E34,G34,I34,K34) -> 325095.18 | M34: =AVERAGE(B34,D34,F34,H34,J34) -> 3.7213276
A35: =CFO_Bill_Rate_Breakdown!A34 -> Technology / Systems | B35: =CFO_Bill_Rate_Breakdown!B34 -> 0.419298 | C35: =CFO_Bill_Rate_Breakdown!C34 -> 7325.9747 | D35: =IF(Inputs!$C$64="Manual",IF(OR($B35="",Inputs!$B$65=0,Inputs!$C$65=""),"",$B35*(Inputs!$C$65/Inputs!$B$65)),IF(OR($B35="",$B35=0),"",$B35*(1+$B$4)^1)) -> 0.43187694 | E35: =IF(OR(D35="",D35=0,Inputs!$C$71=""),"",D35*Inputs!$C$71) -> 7545.7539 | F35: =IF(Inputs!$D$64="Manual",IF(OR($B35="",Inputs!$B$65=0,Inputs!$D$65=""),"",$B35*(Inputs!$D$65/Inputs!$B$65)),IF(OR($B35="",$B35=0),"",$B35*(1+$B$4)^2)) -> 0.44483325 | G35: =IF(OR(F35="",F35=0,Inputs!$D$71=""),"",F35*Inputs!$D$71) -> 7772.1265 | H35: =IF(Inputs!$E$64="Manual",IF(OR($B35="",Inputs!$B$65=0,Inputs!$E$65=""),"",$B35*(Inputs!$E$65/Inputs!$B$65)),IF(OR($B35="",$B35=0),"",$B35*(1+$B$4)^3)) -> 0.45817825 | I35: =IF(OR(H35="",H35=0,Inputs!$E$71=""),"",H35*Inputs!$E$71) -> 8005.2903 | J35: =IF(Inputs!$F$64="Manual",IF(OR($B35="",Inputs!$B$65=0,Inputs!$F$65=""),"",$B35*(Inputs!$F$65/Inputs!$B$65)),IF(OR($B35="",$B35=0),"",$B35*(1+$B$4)^4)) -> 0.47192359 | K35: =IF(OR(J35="",J35=0,Inputs!$F$71=""),"",J35*Inputs!$F$71) -> 8245.449 | L35: =SUM(C35,E35,G35,I35,K35) -> 38894.594 | M35: =AVERAGE(B35,D35,F35,H35,J35) -> 0.44522201
A36: =CFO_Bill_Rate_Breakdown!A35 -> General Liability Insurance | B36: =CFO_Bill_Rate_Breakdown!B35 -> 3.7401382 | C36: =CFO_Bill_Rate_Breakdown!C35 -> 65347.694 | D36: =IF(Inputs!$C$64="Manual",IF(OR($B36="",Inputs!$B$65=0,Inputs!$C$65=""),"",$B36*(Inputs!$C$65/Inputs!$B$65)),IF(OR($B36="",$B36=0),"",$B36*(1+$B$4)^1)) -> 3.8523423 | E36: =IF(OR(D36="",D36=0,Inputs!$C$71=""),"",D36*Inputs!$C$71) -> 67308.125 | F36: =IF(Inputs!$D$64="Manual",IF(OR($B36="",Inputs!$B$65=0,Inputs!$D$65=""),"",$B36*(Inputs!$D$65/Inputs!$B$65)),IF(OR($B36="",$B36=0),"",$B36*(1+$B$4)^2)) -> 3.9679126 | G36: =IF(OR(F36="",F36=0,Inputs!$D$71=""),"",F36*Inputs!$D$71) -> 69327.368 | H36: =IF(Inputs!$E$64="Manual",IF(OR($B36="",Inputs!$B$65=0,Inputs!$E$65=""),"",$B36*(Inputs!$E$65/Inputs!$B$65)),IF(OR($B36="",$B36=0),"",$B36*(1+$B$4)^3)) -> 4.08695 | I36: =IF(OR(H36="",H36=0,Inputs!$E$71=""),"",H36*Inputs!$E$71) -> 71407.19 | J36: =IF(Inputs!$F$64="Manual",IF(OR($B36="",Inputs!$B$65=0,Inputs!$F$65=""),"",$B36*(Inputs!$F$65/Inputs!$B$65)),IF(OR($B36="",$B36=0),"",$B36*(1+$B$4)^4)) -> 4.2095584 | K36: =IF(OR(J36="",J36=0,Inputs!$F$71=""),"",J36*Inputs!$F$71) -> 73549.405 | L36: =SUM(C36,E36,G36,I36,K36) -> 346939.78 | M36: =AVERAGE(B36,D36,F36,H36,J36) -> 3.9713803
A37: =CFO_Bill_Rate_Breakdown!A36 -> Umbrella / Other Insurance | B37: =CFO_Bill_Rate_Breakdown!B36 -> 0.3144735 | C37: =CFO_Bill_Rate_Breakdown!C36 -> 5494.481 | D37: =IF(Inputs!$C$64="Manual",IF(OR($B37="",Inputs!$B$65=0,Inputs!$C$65=""),"",$B37*(Inputs!$C$65/Inputs!$B$65)),IF(OR($B37="",$B37=0),"",$B37*(1+$B$4)^1)) -> 0.32390771 | E37: =IF(OR(D37="",D37=0,Inputs!$C$71=""),"",D37*Inputs!$C$71) -> 5659.3154 | F37: =IF(Inputs!$D$64="Manual",IF(OR($B37="",Inputs!$B$65=0,Inputs!$D$65=""),"",$B37*(Inputs!$D$65/Inputs!$B$65)),IF(OR($B37="",$B37=0),"",$B37*(1+$B$4)^2)) -> 0.33362494 | G37: =IF(OR(F37="",F37=0,Inputs!$D$71=""),"",F37*Inputs!$D$71) -> 5829.0949 | H37: =IF(Inputs!$E$64="Manual",IF(OR($B37="",Inputs!$B$65=0,Inputs!$E$65=""),"",$B37*(Inputs!$E$65/Inputs!$B$65)),IF(OR($B37="",$B37=0),"",$B37*(1+$B$4)^3)) -> 0.34363368 | I37: =IF(OR(H37="",H37=0,Inputs!$E$71=""),"",H37*Inputs!$E$71) -> 6003.9677 | J37: =IF(Inputs!$F$64="Manual",IF(OR($B37="",Inputs!$B$65=0,Inputs!$F$65=""),"",$B37*(Inputs!$F$65/Inputs!$B$65)),IF(OR($B37="",$B37=0),"",$B37*(1+$B$4)^4)) -> 0.35394269 | K37: =IF(OR(J37="",J37=0,Inputs!$F$71=""),"",J37*Inputs!$F$71) -> 6184.0868 | L37: =SUM(C37,E37,G37,I37,K37) -> 29170.946 | M37: =AVERAGE(B37,D37,F37,H37,J37) -> 0.3339165
A38: =CFO_Bill_Rate_Breakdown!A37 -> Total Operations / Support | B38: =CFO_Bill_Rate_Breakdown!B37 -> 9.7146414 | C38: =CFO_Bill_Rate_Breakdown!C37 -> 169734.22 | D38: =IF(Inputs!$C$64="Manual",IF(OR($B38="",Inputs!$B$65=0,Inputs!$C$65=""),"",$B38*(Inputs!$C$65/Inputs!$B$65)),IF(OR($B38="",$B38=0),"",$B38*(1+$B$4)^1)) -> 10.006081 | E38: =IF(OR(D38="",D38=0,Inputs!$C$71=""),"",D38*Inputs!$C$71) -> 174826.24 | F38: =IF(Inputs!$D$64="Manual",IF(OR($B38="",Inputs!$B$65=0,Inputs!$D$65=""),"",$B38*(Inputs!$D$65/Inputs!$B$65)),IF(OR($B38="",$B38=0),"",$B38*(1+$B$4)^2)) -> 10.306263 | G38: =IF(OR(F38="",F38=0,Inputs!$D$71=""),"",F38*Inputs!$D$71) -> 180071.03 | H38: =IF(Inputs!$E$64="Manual",IF(OR($B38="",Inputs!$B$65=0,Inputs!$E$65=""),"",$B38*(Inputs!$E$65/Inputs!$B$65)),IF(OR($B38="",$B38=0),"",$B38*(1+$B$4)^3)) -> 10.615451 | I38: =IF(OR(H38="",H38=0,Inputs!$E$71=""),"",H38*Inputs!$E$71) -> 185473.16 | J38: =IF(Inputs!$F$64="Manual",IF(OR($B38="",Inputs!$B$65=0,Inputs!$F$65=""),"",$B38*(Inputs!$F$65/Inputs!$B$65)),IF(OR($B38="",$B38=0),"",$B38*(1+$B$4)^4)) -> 10.933915 | K38: =IF(OR(J38="",J38=0,Inputs!$F$71=""),"",J38*Inputs!$F$71) -> 191037.35 | L38: =SUM(C38,E38,G38,I38,K38) -> 901142 | M38: =AVERAGE(B38,D38,F38,H38,J38) -> 10.31527
A39: Overhead / G&A / Profit
A40: =CFO_Bill_Rate_Breakdown!A40 -> Administrative / HR / Payroll | B40: =CFO_Bill_Rate_Breakdown!B40 -> 0 | C40: =CFO_Bill_Rate_Breakdown!C40 -> 0 | D40: =IF(Inputs!$C$64="Manual",IF(OR($B40="",Inputs!$B$65=0,Inputs!$C$65=""),"",$B40*(Inputs!$C$65/Inputs!$B$65)),IF(OR($B40="",$B40=0),"",$B40*(1+$B$4)^1)) | E40: =IF(OR(D40="",D40=0,Inputs!$C$71=""),"",D40*Inputs!$C$71) | F40: =IF(Inputs!$D$64="Manual",IF(OR($B40="",Inputs!$B$65=0,Inputs!$D$65=""),"",$B40*(Inputs!$D$65/Inputs!$B$65)),IF(OR($B40="",$B40=0),"",$B40*(1+$B$4)^2)) | G40: =IF(OR(F40="",F40=0,Inputs!$D$71=""),"",F40*Inputs!$D$71) | H40: =IF(Inputs!$E$64="Manual",IF(OR($B40="",Inputs!$B$65=0,Inputs!$E$65=""),"",$B40*(Inputs!$E$65/Inputs!$B$65)),IF(OR($B40="",$B40=0),"",$B40*(1+$B$4)^3)) | I40: =IF(OR(H40="",H40=0,Inputs!$E$71=""),"",H40*Inputs!$E$71) | J40: =IF(Inputs!$F$64="Manual",IF(OR($B40="",Inputs!$B$65=0,Inputs!$F$65=""),"",$B40*(Inputs!$F$65/Inputs!$B$65)),IF(OR($B40="",$B40=0),"",$B40*(1+$B$4)^4)) | K40: =IF(OR(J40="",J40=0,Inputs!$F$71=""),"",J40*Inputs!$F$71) | L40: =SUM(C40,E40,G40,I40,K40) -> 0 | M40: =AVERAGE(B40,D40,F40,H40,J40) -> 0
A41: =CFO_Bill_Rate_Breakdown!A41 -> Accounting / Legal | B41: =CFO_Bill_Rate_Breakdown!B41 -> 0 | C41: =CFO_Bill_Rate_Breakdown!C41 -> 0 | D41: =IF(Inputs!$C$64="Manual",IF(OR($B41="",Inputs!$B$65=0,Inputs!$C$65=""),"",$B41*(Inputs!$C$65/Inputs!$B$65)),IF(OR($B41="",$B41=0),"",$B41*(1+$B$4)^1)) | E41: =IF(OR(D41="",D41=0,Inputs!$C$71=""),"",D41*Inputs!$C$71) | F41: =IF(Inputs!$D$64="Manual",IF(OR($B41="",Inputs!$B$65=0,Inputs!$D$65=""),"",$B41*(Inputs!$D$65/Inputs!$B$65)),IF(OR($B41="",$B41=0),"",$B41*(1+$B$4)^2)) | G41: =IF(OR(F41="",F41=0,Inputs!$D$71=""),"",F41*Inputs!$D$71) | H41: =IF(Inputs!$E$64="Manual",IF(OR($B41="",Inputs!$B$65=0,Inputs!$E$65=""),"",$B41*(Inputs!$E$65/Inputs!$B$65)),IF(OR($B41="",$B41=0),"",$B41*(1+$B$4)^3)) | I41: =IF(OR(H41="",H41=0,Inputs!$E$71=""),"",H41*Inputs!$E$71) | J41: =IF(Inputs!$F$64="Manual",IF(OR($B41="",Inputs!$B$65=0,Inputs!$F$65=""),"",$B41*(Inputs!$F$65/Inputs!$B$65)),IF(OR($B41="",$B41=0),"",$B41*(1+$B$4)^4)) | K41: =IF(OR(J41="",J41=0,Inputs!$F$71=""),"",J41*Inputs!$F$71) | L41: =SUM(C41,E41,G41,I41,K41) -> 0 | M41: =AVERAGE(B41,D41,F41,H41,J41) -> 0
A42: =CFO_Bill_Rate_Breakdown!A42 -> Corporate Overhead | B42: =CFO_Bill_Rate_Breakdown!B42 -> 4.19298 | C42: =CFO_Bill_Rate_Breakdown!C42 -> 73259.747 | D42: =IF(Inputs!$C$64="Manual",IF(OR($B42="",Inputs!$B$65=0,Inputs!$C$65=""),"",$B42*(Inputs!$C$65/Inputs!$B$65)),IF(OR($B42="",$B42=0),"",$B42*(1+$B$4)^1)) -> 4.3187694 | E42: =IF(OR(D42="",D42=0,Inputs!$C$71=""),"",D42*Inputs!$C$71) -> 75457.539 | F42: =IF(Inputs!$D$64="Manual",IF(OR($B42="",Inputs!$B$65=0,Inputs!$D$65=""),"",$B42*(Inputs!$D$65/Inputs!$B$65)),IF(OR($B42="",$B42=0),"",$B42*(1+$B$4)^2)) -> 4.4483325 | G42: =IF(OR(F42="",F42=0,Inputs!$D$71=""),"",F42*Inputs!$D$71) -> 77721.265 | H42: =IF(Inputs!$E$64="Manual",IF(OR($B42="",Inputs!$B$65=0,Inputs!$E$65=""),"",$B42*(Inputs!$E$65/Inputs!$B$65)),IF(OR($B42="",$B42=0),"",$B42*(1+$B$4)^3)) -> 4.5817825 | I42: =IF(OR(H42="",H42=0,Inputs!$E$71=""),"",H42*Inputs!$E$71) -> 80052.903 | J42: =IF(Inputs!$F$64="Manual",IF(OR($B42="",Inputs!$B$65=0,Inputs!$F$65=""),"",$B42*(Inputs!$F$65/Inputs!$B$65)),IF(OR($B42="",$B42=0),"",$B42*(1+$B$4)^4)) -> 4.7192359 | K42: =IF(OR(J42="",J42=0,Inputs!$F$71=""),"",J42*Inputs!$F$71) -> 82454.49 | L42: =SUM(C42,E42,G42,I42,K42) -> 388945.94 | M42: =AVERAGE(B42,D42,F42,H42,J42) -> 4.4522201
A43: =CFO_Bill_Rate_Breakdown!A43 -> G&A | B43: =CFO_Bill_Rate_Breakdown!B43 -> 3.354384 | C43: =CFO_Bill_Rate_Breakdown!C43 -> 58607.797 | D43: =IF(Inputs!$C$64="Manual",IF(OR($B43="",Inputs!$B$65=0,Inputs!$C$65=""),"",$B43*(Inputs!$C$65/Inputs!$B$65)),IF(OR($B43="",$B43=0),"",$B43*(1+$B$4)^1)) -> 3.4550155 | E43: =IF(OR(D43="",D43=0,Inputs!$C$71=""),"",D43*Inputs!$C$71) -> 60366.031 | F43: =IF(Inputs!$D$64="Manual",IF(OR($B43="",Inputs!$B$65=0,Inputs!$D$65=""),"",$B43*(Inputs!$D$65/Inputs!$B$65)),IF(OR($B43="",$B43=0),"",$B43*(1+$B$4)^2)) -> 3.558666 | G43: =IF(OR(F43="",F43=0,Inputs!$D$71=""),"",F43*Inputs!$D$71) -> 62177.012 | H43: =IF(Inputs!$E$64="Manual",IF(OR($B43="",Inputs!$B$65=0,Inputs!$E$65=""),"",$B43*(Inputs!$E$65/Inputs!$B$65)),IF(OR($B43="",$B43=0),"",$B43*(1+$B$4)^3)) -> 3.665426 | I43: =IF(OR(H43="",H43=0,Inputs!$E$71=""),"",H43*Inputs!$E$71) -> 64042.322 | J43: =IF(Inputs!$F$64="Manual",IF(OR($B43="",Inputs!$B$65=0,Inputs!$F$65=""),"",$B43*(Inputs!$F$65/Inputs!$B$65)),IF(OR($B43="",$B43=0),"",$B43*(1+$B$4)^4)) -> 3.7753887 | K43: =IF(OR(J43="",J43=0,Inputs!$F$71=""),"",J43*Inputs!$F$71) -> 65963.592 | L43: =SUM(C43,E43,G43,I43,K43) -> 311156.76 | M43: =AVERAGE(B43,D43,F43,H43,J43) -> 3.561776
A44: =CFO_Bill_Rate_Breakdown!A44 -> Profit / Fee | B44: =CFO_Bill_Rate_Breakdown!B44 -> 19.106529 | C44: =CFO_Bill_Rate_Breakdown!C44 -> 333829.28 | D44: =IF(Inputs!$C$64="Manual",IF(OR($B44="",Inputs!$B$65=0,Inputs!$C$65=""),"",$B44*(Inputs!$C$65/Inputs!$B$65)),IF(OR($B44="",$B44=0),"",$B44*(1+$B$4)^1)) -> 19.679725 | E44: =IF(OR(D44="",D44=0,Inputs!$C$71=""),"",D44*Inputs!$C$71) -> 343844.16 | F44: =IF(Inputs!$D$64="Manual",IF(OR($B44="",Inputs!$B$65=0,Inputs!$D$65=""),"",$B44*(Inputs!$D$65/Inputs!$B$65)),IF(OR($B44="",$B44=0),"",$B44*(1+$B$4)^2)) -> 20.270117 | G44: =IF(OR(F44="",F44=0,Inputs!$D$71=""),"",F44*Inputs!$D$71) -> 354159.48 | H44: =IF(Inputs!$E$64="Manual",IF(OR($B44="",Inputs!$B$65=0,Inputs!$E$65=""),"",$B44*(Inputs!$E$65/Inputs!$B$65)),IF(OR($B44="",$B44=0),"",$B44*(1+$B$4)^3)) -> 20.87822 | I44: =IF(OR(H44="",H44=0,Inputs!$E$71=""),"",H44*Inputs!$E$71) -> 364784.27 | J44: =IF(Inputs!$F$64="Manual",IF(OR($B44="",Inputs!$B$65=0,Inputs!$F$65=""),"",$B44*(Inputs!$F$65/Inputs!$B$65)),IF(OR($B44="",$B44=0),"",$B44*(1+$B$4)^4)) -> 21.504567 | K44: =IF(OR(J44="",J44=0,Inputs!$F$71=""),"",J44*Inputs!$F$71) -> 375727.8 | L44: =SUM(C44,E44,G44,I44,K44) -> 1772345 | M44: =AVERAGE(B44,D44,F44,H44,J44) -> 20.287832
A45: =CFO_Bill_Rate_Breakdown!A45 -> Total Overhead / G&A / Profit | B45: =CFO_Bill_Rate_Breakdown!B45 -> 26.653893 | C45: =CFO_Bill_Rate_Breakdown!C45 -> 465696.82 | D45: =IF(Inputs!$C$64="Manual",IF(OR($B45="",Inputs!$B$65=0,Inputs!$C$65=""),"",$B45*(Inputs!$C$65/Inputs!$B$65)),IF(OR($B45="",$B45=0),"",$B45*(1+$B$4)^1)) -> 27.45351 | E45: =IF(OR(D45="",D45=0,Inputs!$C$71=""),"",D45*Inputs!$C$71) -> 479667.73 | F45: =IF(Inputs!$D$64="Manual",IF(OR($B45="",Inputs!$B$65=0,Inputs!$D$65=""),"",$B45*(Inputs!$D$65/Inputs!$B$65)),IF(OR($B45="",$B45=0),"",$B45*(1+$B$4)^2)) -> 28.277115 | G45: =IF(OR(F45="",F45=0,Inputs!$D$71=""),"",F45*Inputs!$D$71) -> 494057.76 | H45: =IF(Inputs!$E$64="Manual",IF(OR($B45="",Inputs!$B$65=0,Inputs!$E$65=""),"",$B45*(Inputs!$E$65/Inputs!$B$65)),IF(OR($B45="",$B45=0),"",$B45*(1+$B$4)^3)) -> 29.125429 | I45: =IF(OR(H45="",H45=0,Inputs!$E$71=""),"",H45*Inputs!$E$71) -> 508879.49 | J45: =IF(Inputs!$F$64="Manual",IF(OR($B45="",Inputs!$B$65=0,Inputs!$F$65=""),"",$B45*(Inputs!$F$65/Inputs!$B$65)),IF(OR($B45="",$B45=0),"",$B45*(1+$B$4)^4)) -> 29.999192 | K45: =IF(OR(J45="",J45=0,Inputs!$F$71=""),"",J45*Inputs!$F$71) -> 524145.88 | L45: =SUM(C45,E45,G45,I45,K45) -> 2472447.7 | M45: =AVERAGE(B45,D45,F45,H45,J45) -> 28.301828
A46: Module Feeds (Memo Only - Included Above Where Applicable) | L46: =IFERROR(SUM(C46:G46),0) -> 0 | M46: =IFERROR(L46/H46,0) -> 0
A47: =CFO_Bill_Rate_Breakdown!A48 -> Vehicle Cost per Labor Hour | B47: =CFO_Bill_Rate_Breakdown!B48 -> 3.5046454 | C47: =CFO_Bill_Rate_Breakdown!C48 -> 61233.164 | D47: =IF(Inputs!$C$64="Manual",IF(OR($B47="",Inputs!$B$65=0,Inputs!$C$65=""),"",$B47*(Inputs!$C$65/Inputs!$B$65)),IF(OR($B47="",$B47=0),"",$B47*(1+$B$4)^1)) -> 3.6097847 | E47: =IF(OR(D47="",D47=0,Inputs!$C$71=""),"",D47*Inputs!$C$71) -> 63070.159 | F47: =IF(Inputs!$D$64="Manual",IF(OR($B47="",Inputs!$B$65=0,Inputs!$D$65=""),"",$B47*(Inputs!$D$65/Inputs!$B$65)),IF(OR($B47="",$B47=0),"",$B47*(1+$B$4)^2)) -> 3.7180783 | G47: =IF(OR(F47="",F47=0,Inputs!$D$71=""),"",F47*Inputs!$D$71) -> 64962.263 | H47: =IF(Inputs!$E$64="Manual",IF(OR($B47="",Inputs!$B$65=0,Inputs!$E$65=""),"",$B47*(Inputs!$E$65/Inputs!$B$65)),IF(OR($B47="",$B47=0),"",$B47*(1+$B$4)^3)) -> 3.8296206 | I47: =IF(OR(H47="",H47=0,Inputs!$E$71=""),"",H47*Inputs!$E$71) -> 66911.131 | J47: =IF(Inputs!$F$64="Manual",IF(OR($B47="",Inputs!$B$65=0,Inputs!$F$65=""),"",$B47*(Inputs!$F$65/Inputs!$B$65)),IF(OR($B47="",$B47=0),"",$B47*(1+$B$4)^4)) -> 3.9445092 | K47: =IF(OR(J47="",J47=0,Inputs!$F$71=""),"",J47*Inputs!$F$71) -> 68918.465 | L47: =SUM(C47,E47,G47,I47,K47) -> 325095.18 | M47: =AVERAGE(B47,D47,F47,H47,J47) -> 3.7213276
A48: =CFO_Bill_Rate_Breakdown!A49 -> Uniform & Equipment Cost per Labor Hour | B48: =CFO_Bill_Rate_Breakdown!B49 -> 1.1071394 | C48: =CFO_Bill_Rate_Breakdown!C49 -> 19343.94 | D48: =IF(Inputs!$C$64="Manual",IF(OR($B48="",Inputs!$B$65=0,Inputs!$C$65=""),"",$B48*(Inputs!$C$65/Inputs!$B$65)),IF(OR($B48="",$B48=0),"",$B48*(1+$B$4)^1)) -> 1.1403536 | E48: =IF(OR(D48="",D48=0,Inputs!$C$71=""),"",D48*Inputs!$C$71) -> 19924.258 | F48: =IF(Inputs!$D$64="Manual",IF(OR($B48="",Inputs!$B$65=0,Inputs!$D$65=""),"",$B48*(Inputs!$D$65/Inputs!$B$65)),IF(OR($B48="",$B48=0),"",$B48*(1+$B$4)^2)) -> 1.1745642 | G48: =IF(OR(F48="",F48=0,Inputs!$D$71=""),"",F48*Inputs!$D$71) -> 20521.986 | H48: =IF(Inputs!$E$64="Manual",IF(OR($B48="",Inputs!$B$65=0,Inputs!$E$65=""),"",$B48*(Inputs!$E$65/Inputs!$B$65)),IF(OR($B48="",$B48=0),"",$B48*(1+$B$4)^3)) -> 1.2098011 | I48: =IF(OR(H48="",H48=0,Inputs!$E$71=""),"",H48*Inputs!$E$71) -> 21137.646 | J48: =IF(Inputs!$F$64="Manual",IF(OR($B48="",Inputs!$B$65=0,Inputs!$F$65=""),"",$B48*(Inputs!$F$65/Inputs!$B$65)),IF(OR($B48="",$B48=0),"",$B48*(1+$B$4)^4)) -> 1.2460952 | K48: =IF(OR(J48="",J48=0,Inputs!$F$71=""),"",J48*Inputs!$F$71) -> 21771.775 | L48: =SUM(C48,E48,G48,I48,K48) -> 102699.6 | M48: =AVERAGE(B48,D48,F48,H48,J48) -> 1.1755907
A49: =CFO_Bill_Rate_Breakdown!A50 -> Training Program Cost per Labor Hour | B49: =CFO_Bill_Rate_Breakdown!B50 -> 2.2161172 | C49: =CFO_Bill_Rate_Breakdown!C50 -> 38720 | D49: =IF(Inputs!$C$64="Manual",IF(OR($B49="",Inputs!$B$65=0,Inputs!$C$65=""),"",$B49*(Inputs!$C$65/Inputs!$B$65)),IF(OR($B49="",$B49=0),"",$B49*(1+$B$4)^1)) -> 2.2826007 | E49: =IF(OR(D49="",D49=0,Inputs!$C$71=""),"",D49*Inputs!$C$71) -> 39881.6 | F49: =IF(Inputs!$D$64="Manual",IF(OR($B49="",Inputs!$B$65=0,Inputs!$D$65=""),"",$B49*(Inputs!$D$65/Inputs!$B$65)),IF(OR($B49="",$B49=0),"",$B49*(1+$B$4)^2)) -> 2.3510788 | G49: =IF(OR(F49="",F49=0,Inputs!$D$71=""),"",F49*Inputs!$D$71) -> 41078.048 | H49: =IF(Inputs!$E$64="Manual",IF(OR($B49="",Inputs!$B$65=0,Inputs!$E$65=""),"",$B49*(Inputs!$E$65/Inputs!$B$65)),IF(OR($B49="",$B49=0),"",$B49*(1+$B$4)^3)) -> 2.4216111 | I49: =IF(OR(H49="",H49=0,Inputs!$E$71=""),"",H49*Inputs!$E$71) -> 42310.389 | J49: =IF(Inputs!$F$64="Manual",IF(OR($B49="",Inputs!$B$65=0,Inputs!$F$65=""),"",$B49*(Inputs!$F$65/Inputs!$B$65)),IF(OR($B49="",$B49=0),"",$B49*(1+$B$4)^4)) -> 2.4942595 | K49: =IF(OR(J49="",J49=0,Inputs!$F$71=""),"",J49*Inputs!$F$71) -> 43579.701 | L49: =SUM(C49,E49,G49,I49,K49) -> 205569.74 | M49: =AVERAGE(B49,D49,F49,H49,J49) -> 2.3531335
A50: Key Totals & Market Comparison | L50: =IFERROR(SUM(C50:G50),0) -> 0 | M50: =IFERROR(L50/H50,0) -> 0
A51: =CFO_Bill_Rate_Breakdown!A52 -> Total Bill Rate | B51: =CFO_Bill_Rate_Breakdown!B52 -> 86.914909 | C51: =CFO_Bill_Rate_Breakdown!C52 -> 1518577.3 | D51: =IF(Inputs!$C$64="Manual",IF(OR($B51="",Inputs!$B$65=0,Inputs!$C$65=""),"",$B51*(Inputs!$C$65/Inputs!$B$65)),IF(OR($B51="",$B51=0),"",$B51*(1+$B$4)^1)) -> 89.522356 | E51: =IF(OR(D51="",D51=0,Inputs!$C$71=""),"",D51*Inputs!$C$71) -> 1564134.6 | F51: =IF(Inputs!$D$64="Manual",IF(OR($B51="",Inputs!$B$65=0,Inputs!$D$65=""),"",$B51*(Inputs!$D$65/Inputs!$B$65)),IF(OR($B51="",$B51=0),"",$B51*(1+$B$4)^2)) -> 92.208027 | G51: =IF(OR(F51="",F51=0,Inputs!$D$71=""),"",F51*Inputs!$D$71) -> 1611058.6 | H51: =IF(Inputs!$E$64="Manual",IF(OR($B51="",Inputs!$B$65=0,Inputs!$E$65=""),"",$B51*(Inputs!$E$65/Inputs!$B$65)),IF(OR($B51="",$B51=0),"",$B51*(1+$B$4)^3)) -> 94.974267 | I51: =IF(OR(H51="",H51=0,Inputs!$E$71=""),"",H51*Inputs!$E$71) -> 1659390.4 | J51: =IF(Inputs!$F$64="Manual",IF(OR($B51="",Inputs!$B$65=0,Inputs!$F$65=""),"",$B51*(Inputs!$F$65/Inputs!$B$65)),IF(OR($B51="",$B51=0),"",$B51*(1+$B$4)^4)) -> 97.823495 | K51: =IF(OR(J51="",J51=0,Inputs!$F$71=""),"",J51*Inputs!$F$71) -> 1709172.1 | L51: =SUM(C51,E51,G51,I51,K51) -> 8062333 | M51: =AVERAGE(B51,D51,F51,H51,J51) -> 92.288611
A52: Appraisal Benchmark Driver (Rate × Annual Hours) | B52: =Appraisal_Full_Scope_Report!$F$8 -> 129.97639 | C52: =B52*Inputs!$B$71 -> 2270947.5 | D52: =IF(Inputs!$C$64="Manual",IF(OR($B52="",Inputs!$B$65=0,Inputs!$C$65=""),"",$B52*(Inputs!$C$65/Inputs!$B$65)),IF(OR($B52="",$B52=0),"",$B52*(1+$B$4)^1)) -> 133.87568 | E52: =IF(OR(D52="",D52=0,Inputs!$C$71=""),"",D52*Inputs!$C$71) -> 2339075.9 | F52: =IF(Inputs!$D$64="Manual",IF(OR($B52="",Inputs!$B$65=0,Inputs!$D$65=""),"",$B52*(Inputs!$D$65/Inputs!$B$65)),IF(OR($B52="",$B52=0),"",$B52*(1+$B$4)^2)) -> 137.89195 | G52: =IF(OR(F52="",F52=0,Inputs!$D$71=""),"",F52*Inputs!$D$71) -> 2409248.2 | H52: =IF(Inputs!$E$64="Manual",IF(OR($B52="",Inputs!$B$65=0,Inputs!$E$65=""),"",$B52*(Inputs!$E$65/Inputs!$B$65)),IF(OR($B52="",$B52=0),"",$B52*(1+$B$4)^3)) -> 142.02871 | I52: =IF(OR(H52="",H52=0,Inputs!$E$71=""),"",H52*Inputs!$E$71) -> 2481525.6 | J52: =IF(Inputs!$F$64="Manual",IF(OR($B52="",Inputs!$B$65=0,Inputs!$F$65=""),"",$B52*(Inputs!$F$65/Inputs!$B$65)),IF(OR($B52="",$B52=0),"",$B52*(1+$B$4)^4)) -> 146.28957 | K52: =IF(OR(J52="",J52=0,Inputs!$F$71=""),"",J52*Inputs!$F$71) -> 2555971.4 | L52: =SUM(C52,E52,G52,I52,K52) -> 12056769 | M52: =AVERAGE(B52,D52,F52,H52,J52) -> 138.01246
A53: Benchmark Delta vs Total Bill Rate | B53: =B52-B51 -> 43.061481 | C53: =B53*Inputs!$B$71 -> 752370.2 | D53: =IF(Inputs!$C$64="Manual",IF(OR($B53="",Inputs!$B$65=0,Inputs!$C$65=""),"",$B53*(Inputs!$C$65/Inputs!$B$65)),IF(OR($B53="",$B53=0),"",$B53*(1+$B$4)^1)) -> 44.353326 | E53: =IF(OR(D53="",D53=0,Inputs!$C$71=""),"",D53*Inputs!$C$71) -> 774941.31 | F53: =IF(Inputs!$D$64="Manual",IF(OR($B53="",Inputs!$B$65=0,Inputs!$D$65=""),"",$B53*(Inputs!$D$65/Inputs!$B$65)),IF(OR($B53="",$B53=0),"",$B53*(1+$B$4)^2)) -> 45.683926 | G53: =IF(OR(F53="",F53=0,Inputs!$D$71=""),"",F53*Inputs!$D$71) -> 798189.55 | H53: =IF(Inputs!$E$64="Manual",IF(OR($B53="",Inputs!$B$65=0,Inputs!$E$65=""),"",$B53*(Inputs!$E$65/Inputs!$B$65)),IF(OR($B53="",$B53=0),"",$B53*(1+$B$4)^3)) -> 47.054443 | I53: =IF(OR(H53="",H53=0,Inputs!$E$71=""),"",H53*Inputs!$E$71) -> 822135.23 | J53: =IF(Inputs!$F$64="Manual",IF(OR($B53="",Inputs!$B$65=0,Inputs!$F$65=""),"",$B53*(Inputs!$F$65/Inputs!$B$65)),IF(OR($B53="",$B53=0),"",$B53*(1+$B$4)^4)) -> 48.466077 | K53: =IF(OR(J53="",J53=0,Inputs!$F$71=""),"",J53*Inputs!$F$71) -> 846799.29 | L53: =SUM(C53,E53,G53,I53,K53) -> 3994435.6 | M53: =AVERAGE(B53,D53,F53,H53,J53) -> 45.723851
A55: Contract Economics Summary
A56: Total Bill Rate (5-Year Annual Total) | B56: =L51 -> 8062333
A57: Should-Cost Benchmark (5-Year Annual Total) | B57: =L52 -> 12056769
A58: Capital Recovery Opportunity (5-Year Annual Total) | B58: =L53 -> 3994435.6
A59: Vendor Premium / (Discount) vs GASQ (5-Year Annual Total) | B59: =B56-B57 -> -3994435.6
A61: Option Year Driver Summary
B62: Base | C62: Option Yr 1 | D62: Option Yr 2 | E62: Option Yr 3 | F62: Option Yr 4
A63: Effective Wage ($/Hr) | B63: =Inputs!B65 -> 27.48 | C63: =Inputs!C65 -> 28.3044 | D63: =Inputs!D65 -> 29.153532 | E63: =Inputs!E65 -> 30.028138 | F63: =Inputs!F65 -> 30.928982
A64: Weekly Hours | B64: =Inputs!B67 -> 336 | C64: =Inputs!C67 -> 336 | D64: =Inputs!D67 -> 336 | E64: =Inputs!E67 -> 336 | F64: =Inputs!F67 -> 336
A65: Number of Weeks | B65: =Inputs!B69 -> 336 | C65: =Inputs!C69 -> 336 | D65: =Inputs!D69 -> 336 | E65: =Inputs!E69 -> 336 | F65: =Inputs!F69 -> 336
A66: Total Annual Hours | B66: =Inputs!B71 -> 17472 | C66: =Inputs!C71 -> 17472 | D66: =Inputs!D71 -> 17472 | E66: =Inputs!E71 -> 17472 | F66: =Inputs!F71 -> 17472
A67: Staff Required | B67: =Inputs!B73 -> 12 | C67: =Inputs!C73 -> 12 | D67: =Inputs!D73 -> 12 | E67: =Inputs!E73 -> 12 | F67: =Inputs!F73 -> 12
A68: Override Mode | B68: =Inputs!B64 -> Auto | C68: =Inputs!C64 -> Auto | D68: =Inputs!D64 -> Auto | E68: =Inputs!E64 -> Auto | F68: =Inputs!F64 -> Auto
A69: Edit overrides on Inputs!A62:F75.

Sheet CLIN Pricing
A1: GASQ CLIN Pricing Template
A2: Directly mapped to Option Year calculator logic for Base Year and Option Years 1-4
J3: Benchmark Driver | K3: ='Option Year'!A52 -> Appraisal Benchmark Driver (Rate × Annual Hours)
A4: Escalation Scenario | B4: ='Option Year'!$B$3 -> Medium | D4: Applied Escalation % | E4: ='Option Year'!$B$4 -> 0.03 | G4: Base Annual Hours | H4: ='Option Year'!$H$3 -> 17472 | J4: Base $/Hr | K4: ='Option Year'!B52 -> 129.97639
J5: Base Annual | K5: ='Option Year'!C52 -> 2270947.5
A6: CLIN | B6: Line Item | C6: Base $/Hr | D6: Base Annual | E6: Opt Yr 1 $/Hr | F6: Opt Yr 1 Annual | G6: Opt Yr 2 $/Hr | H6: Opt Yr 2 Annual | I6: Opt Yr 3 $/Hr | J6: Opt Yr 3 Annual | K6: Opt Yr 4 $/Hr | L6: Opt Yr 4 Annual | M6: Total Contract Value | N6: Total Contract Value Avg $/Hr | O6: Base Recovery Alloc | P6: Opt Yr 1 Recovery Alloc | Q6: Opt Yr 2 Recovery Alloc | R6: Opt Yr 3 Recovery Alloc | S6: Opt Yr 4 Recovery Alloc | T6: 5-Yr Recovery Alloc
A7: CLIN-0001 | B7: ='Option Year'!A8 -> Base Consolidated Blended Direct Labor Wage | C7: ='Option Year'!B8 -> 33.74 | D7: ='Option Year'!C8 -> 589505.28 | E7: ='Option Year'!D8 -> 34.7522 | F7: ='Option Year'!E8 -> 607190.44 | G7: ='Option Year'!F8 -> 35.794766 | H7: ='Option Year'!G8 -> 625406.15 | I7: ='Option Year'!H8 -> 36.868609 | ... N7: ='Option Year'!M8 -> 35.826048 | O7: =IFERROR(D7/$D$45*D$47,0) -> 292066.93 | P7: =IFERROR(F7/$F$45*F$47,0) -> 300828.94 | Q7: =IFERROR(H7/$H$45*H$47,0) -> 309853.81 | R7: =IFERROR(J7/$J$45*J$47,0) -> 319149.42 | S7: =IFERROR(L7/$L$45*L$47,0) -> 328723.9 | T7: =SUM(O7:S7) -> 1550623
A8: CLIN-0002 | B8: ='Option Year'!A9 -> Locality Pay | C8: ='Option Year'!B9 -> 0 | D8: ='Option Year'!C9 -> 0 | E8: ='Option Year'!D9 | F8: ='Option Year'!E9 | G8: ='Option Year'!F9 | H8: ='Option Year'!G9 | I8: ='Option Year'!H9 | ... N8: ='Option Year'!M9 -> 0 | O8: =IFERROR(D8/$D$45*D$47,0) -> 0 | P8: =IFERROR(F8/$F$45*F$47,0) -> 0 | Q8: =IFERROR(H8/$H$45*H$47,0) -> 0 | R8: =IFERROR(J8/$J$45*J$47,0) -> 0 | S8: =IFERROR(L8/$L$45*L$47,0) -> 0 | T8: =SUM(O8:S8) -> 0
A9: CLIN-0003 | B9: ='Option Year'!A10 -> Labor Market Adjustment | C9: ='Option Year'!B10 -> 0 | D9: ='Option Year'!C10 -> 0 | E9: ='Option Year'!D10 | F9: ='Option Year'!E10 | G9: ='Option Year'!F10 | H9: ='Option Year'!G10 | I9: ='Option Year'!H10 | ... N9: ='Option Year'!M10 -> 0 | O9: =IFERROR(D9/$D$45*D$47,0) -> 0 | P9: =IFERROR(F9/$F$45*F$47,0) -> 0 | Q9: =IFERROR(H9/$H$45*H$47,0) -> 0 | R9: =IFERROR(J9/$J$45*J$47,0) -> 0 | S9: =IFERROR(L9/$L$45*L$47,0) -> 0 | T9: =SUM(O9:S9) -> 0
A10: CLIN-0004 | B10: ='Option Year'!A11 -> H&W (Cash) | C10: ='Option Year'!B11 -> 4.22 | D10: ='Option Year'!C11 -> 73731.84 | E10: ='Option Year'!D11 -> 4.3466 | F10: ='Option Year'!E11 -> 75943.795 | G10: ='Option Year'!F11 -> 4.476998 | H10: ='Option Year'!G11 -> 78222.109 | I10: ='Option Year'!H11 -> 4.6113079 | ... N10: ='Option Year'!M11 -> 4.4809106 | O10: =IFERROR(D10/$D$45*D$47,0) -> 36530.007 | P10: =IFERROR(F10/$F$45*F$47,0) -> 37625.908 | Q10: =IFERROR(H10/$H$45*H$47,0) -> 38754.685 | R10: =IFERROR(J10/$J$45*J$47,0) -> 39917.325 | S10: =IFERROR(L10/$L$45*L$47,0) -> 41114.845 | T10: =SUM(O10:S10) -> 193942.77
A11: CLIN-0005 | B11: ='Option Year'!A12 -> Shift Differential | C11: ='Option Year'!B12 -> 0 | D11: ='Option Year'!C12 -> 0 | E11: ='Option Year'!D12 | F11: ='Option Year'!E12 | G11: ='Option Year'!F12 | H11: ='Option Year'!G12 | I11: ='Option Year'!H12 | ... N11: ='Option Year'!M12 -> 0 | O11: =IFERROR(D11/$D$45*D$47,0) -> 0 | P11: =IFERROR(F11/$F$45*F$47,0) -> 0 | Q11: =IFERROR(H11/$H$45*H$47,0) -> 0 | R11: =IFERROR(J11/$J$45*J$47,0) -> 0 | S11: =IFERROR(L11/$L$45*L$47,0) -> 0 | T11: =SUM(O11:S11) -> 0
A12: CLIN-0006 | B12: ='Option Year'!A13 -> OT/Holiday Premium | C12: ='Option Year'!B13 -> 2.6992 | D12: ='Option Year'!C13 -> 47160.422 | E12: ='Option Year'!D13 -> 2.780176 | F12: ='Option Year'!E13 -> 48575.235 | G12: ='Option Year'!F13 -> 2.8635813 | H12: ='Option Year'!G13 -> 50032.492 | I12: ='Option Year'!H13 -> 2.9494887 | ... N12: ='Option Year'!M13 -> 2.8660839 | O12: =IFERROR(D12/$D$45*D$47,0) -> 23365.354 | P12: =IFERROR(F12/$F$45*F$47,0) -> 24066.315 | Q12: =IFERROR(H12/$H$45*H$47,0) -> 24788.305 | R12: =IFERROR(J12/$J$45*J$47,0) -> 25531.954 | S12: =IFERROR(L12/$L$45*L$47,0) -> 26297.912 | T12: =SUM(O12:S12) -> 124049.84
A13: CLIN-0007 | B13: ='Option Year'!A14 -> DON/DOFF | C13: ='Option Year'!B14 -> 1.2706 | D13: ='Option Year'!C14 -> 22199.923 | E13: ='Option Year'!D14 -> 1.308718 | F13: ='Option Year'!E14 -> 22865.921 | G13: ='Option Year'!F14 -> 1.3479795 | H13: ='Option Year'!G14 -> 23551.899 | I13: ='Option Year'!H14 -> 1.3884189 | ... N13: ='Option Year'!M14 -> 1.3491576 | O13: =IFERROR(D13/$D$45*D$47,0) -> 10998.822 | P13: =IFERROR(F13/$F$45*F$47,0) -> 11328.786 | Q13: =IFERROR(H13/$H$45*H$47,0) -> 11668.65 | R13: =IFERROR(J13/$J$45*J$47,0) -> 12018.709 | S13: =IFERROR(L13/$L$45*L$47,0) -> 12379.271 | T13: =SUM(O13:S13) -> 58394.238
A14: CLIN-0008 | B14: ='Option Year'!A15 -> Total Direct Labor | C14: ='Option Year'!B15 -> 41.9298 | D14: ='Option Year'!C15 -> 732597.47 | E14: ='Option Year'!D15 -> 43.187694 | F14: ='Option Year'!E15 -> 754575.39 | G14: ='Option Year'!F15 -> 44.483325 | H14: ='Option Year'!G15 -> 777212.65 | I14: ='Option Year'!H15 -> 45.817825 | ... N14: ='Option Year'!M15 -> 44.522201 | O14: =IFERROR(D14/$D$45*D$47,0) -> 362961.11 | P14: =IFERROR(F14/$F$45*F$47,0) -> 373849.95 | Q14: =IFERROR(H14/$H$45*H$47,0) -> 385065.45 | R14: =IFERROR(J14/$J$45*J$47,0) -> 396617.41 | S14: =IFERROR(L14/$L$45*L$47,0) -> 408515.93 | T14: =SUM(O14:S14) -> 1927009.8
A15: CLIN-0009 | B15: ='Option Year'!A17 -> FICA / Medicare | C15: ='Option Year'!B17 -> 3.2076297 | D15: ='Option Year'!C17 -> 56043.706 | E15: ='Option Year'!D17 -> 3.3038586 | F15: ='Option Year'!E17 -> 57725.017 | G15: ='Option Year'!F17 -> 3.4029743 | H15: ='Option Year'!G17 -> 59456.768 | I15: ='Option Year'!H17 -> 3.5050636 | ... N15: ='Option Year'!M17 -> 3.4059483 | O15: =IFERROR(D15/$D$45*D$47,0) -> 27766.525 | P15: =IFERROR(F15/$F$45*F$47,0) -> 28599.521 | Q15: =IFERROR(H15/$H$45*H$47,0) -> 29457.507 | R15: =IFERROR(J15/$J$45*J$47,0) -> 30341.232 | S15: =IFERROR(L15/$L$45*L$47,0) -> 31251.469 | T15: =SUM(O15:S15) -> 147416.25
A16: CLIN-0010 | B16: ='Option Year'!A18 -> FUTA | C16: ='Option Year'!B18 -> 0.2515788 | D16: ='Option Year'!C18 -> 4395.5848 | E16: ='Option Year'!D18 -> 0.25912616 | F16: ='Option Year'!E18 -> 4527.4523 | G16: ='Option Year'!F18 -> 0.26689995 | H16: ='Option Year'!G18 -> 4663.2759 | I16: ='Option Year'!H18 -> 0.27490695 | ... N16: ='Option Year'!M18 -> 0.2671332 | O16: =IFERROR(D16/$D$45*D$47,0) -> 2177.7667 | P16: =IFERROR(F16/$F$45*F$47,0) -> 2243.0997 | Q16: =IFERROR(H16/$H$45*H$47,0) -> 2310.3927 | R16: =IFERROR(J16/$J$45*J$47,0) -> 2379.7045 | S16: =IFERROR(L16/$L$45*L$47,0) -> 2451.0956 | T16: =SUM(O16:S16) -> 11562.059
A17: CLIN-0011 | B17: ='Option Year'!A19 -> SUTA | C17: ='Option Year'!B19 -> 0.838596 | D17: ='Option Year'!C19 -> 14651.949 | E17: ='Option Year'!D19 -> 0.86375388 | F17: ='Option Year'!E19 -> 15091.508 | G17: ='Option Year'!F19 -> 0.8896665 | H17: ='Option Year'!G19 -> 15544.253 | I17: ='Option Year'!H19 -> 0.91635649 | ... N17: ='Option Year'!M19 -> 0.89044401 | O17: =IFERROR(D17/$D$45*D$47,0) -> 7259.2223 | P17: =IFERROR(F17/$F$45*F$47,0) -> 7476.999 | Q17: =IFERROR(H17/$H$45*H$47,0) -> 7701.3089 | R17: =IFERROR(J17/$J$45*J$47,0) -> 7932.3482 | S17: =IFERROR(L17/$L$45*L$47,0) -> 8170.3186 | T17: =SUM(O17:S17) -> 38540.197
A18: CLIN-0012 | B18: ='Option Year'!A20 -> Workers Compensation | C18: ='Option Year'!B20 -> 0.6708768 | D18: ='Option Year'!C20 -> 11721.559 | E18: ='Option Year'!D20 -> 0.6910031 | F18: ='Option Year'!E20 -> 12073.206 | G18: ='Option Year'!F20 -> 0.7117332 | H18: ='Option Year'!G20 -> 12435.402 | I18: ='Option Year'!H20 -> 0.73308519 | ... N18: ='Option Year'!M20 -> 0.71235521 | O18: =IFERROR(D18/$D$45*D$47,0) -> 5807.3778 | P18: =IFERROR(F18/$F$45*F$47,0) -> 5981.5992 | Q18: =IFERROR(H18/$H$45*H$47,0) -> 6161.0471 | R18: =IFERROR(J18/$J$45*J$47,0) -> 6345.8786 | S18: =IFERROR(L18/$L$45*L$47,0) -> 6536.2549 | T18: =SUM(O18:S18) -> 30832.158
A19: CLIN-0013 | B19: ='Option Year'!A21 -> Health & Welfare | C19: ='Option Year'!B21 -> 0 | D19: ='Option Year'!C21 -> 0 | E19: ='Option Year'!D21 | F19: ='Option Year'!E21 | G19: ='Option Year'!F21 | H19: ='Option Year'!G21 | I19: ='Option Year'!H21 | ... N19: ='Option Year'!M21 -> 0 | O19: =IFERROR(D19/$D$45*D$47,0) -> 0 | P19: =IFERROR(F19/$F$45*F$47,0) -> 0 | Q19: =IFERROR(H19/$H$45*H$47,0) -> 0 | R19: =IFERROR(J19/$J$45*J$47,0) -> 0 | S19: =IFERROR(L19/$L$45*L$47,0) -> 0 | T19: =SUM(O19:S19) -> 0
A20: CLIN-0014 | B20: ='Option Year'!A22 -> Vacation | C20: ='Option Year'!B22 -> 0.838596 | D20: ='Option Year'!C22 -> 14651.949 | E20: ='Option Year'!D22 -> 0.86375388 | F20: ='Option Year'!E22 -> 15091.508 | G20: ='Option Year'!F22 -> 0.8896665 | H20: ='Option Year'!G22 -> 15544.253 | I20: ='Option Year'!H22 -> 0.91635649 | ... N20: ='Option Year'!M22 -> 0.89044401 | O20: =IFERROR(D20/$D$45*D$47,0) -> 7259.2223 | P20: =IFERROR(F20/$F$45*F$47,0) -> 7476.999 | Q20: =IFERROR(H20/$H$45*H$47,0) -> 7701.3089 | R20: =IFERROR(J20/$J$45*J$47,0) -> 7932.3482 | S20: =IFERROR(L20/$L$45*L$47,0) -> 8170.3186 | T20: =SUM(O20:S20) -> 38540.197
A21: CLIN-0015 | B21: ='Option Year'!A23 -> Paid Holidays | C21: ='Option Year'!B23 -> 1.677192 | D21: ='Option Year'!C23 -> 29303.899 | E21: ='Option Year'!D23 -> 1.7275078 | F21: ='Option Year'!E23 -> 30183.016 | G21: ='Option Year'!F23 -> 1.779333 | H21: ='Option Year'!G23 -> 31088.506 | I21: ='Option Year'!H23 -> 1.832713 | ... N21: ='Option Year'!M23 -> 1.780888 | O21: =IFERROR(D21/$D$45*D$47,0) -> 14518.445 | P21: =IFERROR(F21/$F$45*F$47,0) -> 14953.998 | Q21: =IFERROR(H21/$H$45*H$47,0) -> 15402.618 | R21: =IFERROR(J21/$J$45*J$47,0) -> 15864.696 | S21: =IFERROR(L21/$L$45*L$47,0) -> 16340.637 | T21: =SUM(O21:S21) -> 77080.394
A22: CLIN-0016 | B22: ='Option Year'!A24 -> Sick Leave | C22: ='Option Year'!B24 -> 1.1321046 | D22: ='Option Year'!C24 -> 19780.132 | E22: ='Option Year'!D24 -> 1.1660677 | F22: ='Option Year'!E24 -> 20373.536 | G22: ='Option Year'!F24 -> 1.2010498 | H22: ='Option Year'!G24 -> 20984.742 | I22: ='Option Year'!H24 -> 1.2370813 | ... N22: ='Option Year'!M24 -> 1.2020994 | O22: =IFERROR(D22/$D$45*D$47,0) -> 9799.9501 | P22: =IFERROR(F22/$F$45*F$47,0) -> 10093.949 | Q22: =IFERROR(H22/$H$45*H$47,0) -> 10396.767 | R22: =IFERROR(J22/$J$45*J$47,0) -> 10708.67 | S22: =IFERROR(L22/$L$45*L$47,0) -> 11029.93 | T22: =SUM(O22:S22) -> 52029.266
A23: CLIN-0017 | B23: ='Option Year'!A25 -> Total Fringe / Burden | C23: ='Option Year'!B25 -> 8.6165739 | D23: ='Option Year'!C25 -> 150548.78 | E23: ='Option Year'!D25 -> 8.8750711 | F23: ='Option Year'!E25 -> 155065.24 | G23: ='Option Year'!F25 -> 9.1413233 | H23: ='Option Year'!G25 -> 159717.2 | I23: ='Option Year'!H25 -> 9.4155629 | ... N23: ='Option Year'!M25 -> 9.1493122 | O23: =IFERROR(D23/$D$45*D$47,0) -> 74588.509 | P23: =IFERROR(F23/$F$45*F$47,0) -> 76826.164 | Q23: =IFERROR(H23/$H$45*H$47,0) -> 79130.949 | R23: =IFERROR(J23/$J$45*J$47,0) -> 81504.878 | S23: =IFERROR(L23/$L$45*L$47,0) -> 83950.024 | T23: =SUM(O23:S23) -> 396000.52
A24: CLIN-0018 | B24: ='Option Year'!A26 -> Total Direct Labor + Fringe | C24: ='Option Year'!B26 -> 50.546374 | D24: ='Option Year'!C26 -> 883146.24 | E24: ='Option Year'!D26 -> 52.062765 | F24: ='Option Year'!E26 -> 909640.63 | G24: ='Option Year'!F26 -> 53.624648 | H24: ='Option Year'!G26 -> 936929.85 | I24: ='Option Year'!H26 -> 55.233388 | ... N24: ='Option Year'!M26 -> 53.671513 | O24: =IFERROR(D24/$D$45*D$47,0) -> 437549.62 | P24: =IFERROR(F24/$F$45*F$47,0) -> 450676.11 | Q24: =IFERROR(H24/$H$45*H$47,0) -> 464196.4 | R24: =IFERROR(J24/$J$45*J$47,0) -> 478122.29 | S24: =IFERROR(L24/$L$45*L$47,0) -> 492465.96 | T24: =SUM(O24:S24) -> 2323010.4
A25: CLIN-0019 | B25: ='Option Year'!A28 -> Recruiting / Hiring | C25: ='Option Year'!B28 -> 0 | D25: ='Option Year'!C28 -> 0 | E25: ='Option Year'!D28 | F25: ='Option Year'!E28 | G25: ='Option Year'!F28 | H25: ='Option Year'!G28 | I25: ='Option Year'!H28 | ... N25: ='Option Year'!M28 -> 0 | O25: =IFERROR(D25/$D$45*D$47,0) -> 0 | P25: =IFERROR(F25/$F$45*F$47,0) -> 0 | Q25: =IFERROR(H25/$H$45*H$47,0) -> 0 | R25: =IFERROR(J25/$J$45*J$47,0) -> 0 | S25: =IFERROR(L25/$L$45*L$47,0) -> 0 | T25: =SUM(O25:S25) -> 0
A26: CLIN-0020 | B26: ='Option Year'!A29 -> Training / Certification | C26: ='Option Year'!B29 -> 0.628947 | D26: ='Option Year'!C29 -> 10988.962 | E26: ='Option Year'!D29 -> 0.64781541 | F26: ='Option Year'!E29 -> 11318.631 | G26: ='Option Year'!F29 -> 0.66724987 | H26: ='Option Year'!G29 -> 11658.19 | I26: ='Option Year'!H29 -> 0.68726737 | ... N26: ='Option Year'!M29 -> 0.66783301 | O26: =IFERROR(D26/$D$45*D$47,0) -> 5444.4167 | P26: =IFERROR(F26/$F$45*F$47,0) -> 5607.7492 | Q26: =IFERROR(H26/$H$45*H$47,0) -> 5775.9817 | R26: =IFERROR(J26/$J$45*J$47,0) -> 5949.2611 | S26: =IFERROR(L26/$L$45*L$47,0) -> 6127.739 | T26: =SUM(O26:S26) -> 28905.148
A27: CLIN-0021 | B27: ='Option Year'!A30 -> Uniforms / Equipment | C27: ='Option Year'!B30 -> 1.1071394 | D27: ='Option Year'!C30 -> 19343.94 | E27: ='Option Year'!D30 -> 1.1403536 | F27: ='Option Year'!E30 -> 19924.258 | G27: ='Option Year'!F30 -> 1.1745642 | H27: ='Option Year'!G30 -> 20521.986 | I27: ='Option Year'!H30 -> 1.2098011 | ... N27: ='Option Year'!M30 -> 1.1755907 | O27: =IFERROR(D27/$D$45*D$47,0) -> 9583.8415 | P27: =IFERROR(F27/$F$45*F$47,0) -> 9871.3568 | Q27: =IFERROR(H27/$H$45*H$47,0) -> 10167.497 | R27: =IFERROR(J27/$J$45*J$47,0) -> 10472.522 | S27: =IFERROR(L27/$L$45*L$47,0) -> 10786.698 | T27: =SUM(O27:S27) -> 50881.916
A28: CLIN-0022 | B28: ='Option Year'!A31 -> Field Supervision | C28: ='Option Year'!B31 -> 0 | D28: ='Option Year'!C31 -> 0 | E28: ='Option Year'!D31 | F28: ='Option Year'!E31 | G28: ='Option Year'!F31 | H28: ='Option Year'!G31 | I28: ='Option Year'!H31 | ... N28: ='Option Year'!M31 -> 0 | O28: =IFERROR(D28/$D$45*D$47,0) -> 0 | P28: =IFERROR(F28/$F$45*F$47,0) -> 0 | Q28: =IFERROR(H28/$H$45*H$47,0) -> 0 | R28: =IFERROR(J28/$J$45*J$47,0) -> 0 | S28: =IFERROR(L28/$L$45*L$47,0) -> 0 | T28: =SUM(O28:S28) -> 0
A29: CLIN-0023 | B29: ='Option Year'!A32 -> Contract Management | C29: ='Option Year'!B32 -> 0 | D29: ='Option Year'!C32 -> 0 | E29: ='Option Year'!D32 | F29: ='Option Year'!E32 | G29: ='Option Year'!F32 | H29: ='Option Year'!G32 | I29: ='Option Year'!H32 | ... N29: ='Option Year'!M32 -> 0 | O29: =IFERROR(D29/$D$45*D$47,0) -> 0 | P29: =IFERROR(F29/$F$45*F$47,0) -> 0 | Q29: =IFERROR(H29/$H$45*H$47,0) -> 0 | R29: =IFERROR(J29/$J$45*J$47,0) -> 0 | S29: =IFERROR(L29/$L$45*L$47,0) -> 0 | T29: =SUM(O29:S29) -> 0
A30: CLIN-0024 | B30: ='Option Year'!A33 -> Quality Assurance | C30: ='Option Year'!B33 -> 0 | D30: ='Option Year'!C33 -> 0 | E30: ='Option Year'!D33 | F30: ='Option Year'!E33 | G30: ='Option Year'!F33 | H30: ='Option Year'!G33 | I30: ='Option Year'!H33 | ... N30: ='Option Year'!M33 -> 0 | O30: =IFERROR(D30/$D$45*D$47,0) -> 0 | P30: =IFERROR(F30/$F$45*F$47,0) -> 0 | Q30: =IFERROR(H30/$H$45*H$47,0) -> 0 | R30: =IFERROR(J30/$J$45*J$47,0) -> 0 | S30: =IFERROR(L30/$L$45*L$47,0) -> 0 | T30: =SUM(O30:S30) -> 0
A31: CLIN-0025 | B31: ='Option Year'!A34 -> Vehicles / Patrol | C31: ='Option Year'!B34 -> 3.5046454 | D31: ='Option Year'!C34 -> 61233.164 | E31: ='Option Year'!D34 -> 3.6097847 | F31: ='Option Year'!E34 -> 63070.159 | G31: ='Option Year'!F34 -> 3.7180783 | H31: ='Option Year'!G34 -> 64962.263 | I31: ='Option Year'!H34 -> 3.8296206 | ... N31: ='Option Year'!M34 -> 3.7213276 | O31: =IFERROR(D31/$D$45*D$47,0) -> 30337.612 | P31: =IFERROR(F31/$F$45*F$47,0) -> 31247.74 | Q31: =IFERROR(H31/$H$45*H$47,0) -> 32185.172 | R31: =IFERROR(J31/$J$45*J$47,0) -> 33150.727 | S31: =IFERROR(L31/$L$45*L$47,0) -> 34145.249 | T31: =SUM(O31:S31) -> 161066.5
A32: CLIN-0026 | B32: ='Option Year'!A35 -> Technology / Systems | C32: ='Option Year'!B35 -> 0.419298 | D32: ='Option Year'!C35 -> 7325.9747 | E32: ='Option Year'!D35 -> 0.43187694 | F32: ='Option Year'!E35 -> 7545.7539 | G32: ='Option Year'!F35 -> 0.44483325 | H32: ='Option Year'!G35 -> 7772.1265 | I32: ='Option Year'!H35 -> 0.45817825 | ... N32: ='Option Year'!M35 -> 0.44522201 | O32: =IFERROR(D32/$D$45*D$47,0) -> 3629.6111 | P32: =IFERROR(F32/$F$45*F$47,0) -> 3738.4995 | Q32: =IFERROR(H32/$H$45*H$47,0) -> 3850.6545 | R32: =IFERROR(J32/$J$45*J$47,0) -> 3966.1741 | S32: =IFERROR(L32/$L$45*L$47,0) -> 4085.1593 | T32: =SUM(O32:S32) -> 19270.098
A33: CLIN-0027 | B33: ='Option Year'!A36 -> General Liability Insurance | C33: ='Option Year'!B36 -> 3.7401382 | D33: ='Option Year'!C36 -> 65347.694 | E33: ='Option Year'!D36 -> 3.8523423 | F33: ='Option Year'!E36 -> 67308.125 | G33: ='Option Year'!F36 -> 3.9679126 | H33: ='Option Year'!G36 -> 69327.368 | I33: ='Option Year'!H36 -> 4.08695 | ... N33: ='Option Year'!M36 -> 3.9713803 | O33: =IFERROR(D33/$D$45*D$47,0) -> 32376.131 | P33: =IFERROR(F33/$F$45*F$47,0) -> 33347.415 | Q33: =IFERROR(H33/$H$45*H$47,0) -> 34347.838 | R33: =IFERROR(J33/$J$45*J$47,0) -> 35378.273 | S33: =IFERROR(L33/$L$45*L$47,0) -> 36439.621 | T33: =SUM(O33:S33) -> 171889.28
A34: CLIN-0028 | B34: ='Option Year'!A37 -> Umbrella / Other Insurance | C34: ='Option Year'!B37 -> 0.3144735 | D34: ='Option Year'!C37 -> 5494.481 | E34: ='Option Year'!D37 -> 0.32390771 | F34: ='Option Year'!E37 -> 5659.3154 | G34: ='Option Year'!F37 -> 0.33362494 | H34: ='Option Year'!G37 -> 5829.0949 | I34: ='Option Year'!H37 -> 0.34363368 | ... N34: ='Option Year'!M37 -> 0.3339165 | O34: =IFERROR(D34/$D$45*D$47,0) -> 2722.2084 | P34: =IFERROR(F34/$F$45*F$47,0) -> 2803.8746 | Q34: =IFERROR(H34/$H$45*H$47,0) -> 2887.9908 | R34: =IFERROR(J34/$J$45*J$47,0) -> 2974.6306 | S34: =IFERROR(L34/$L$45*L$47,0) -> 3063.8695 | T34: =SUM(O34:S34) -> 14452.574
A35: CLIN-0029 | B35: ='Option Year'!A38 -> Total Operations / Support | C35: ='Option Year'!B38 -> 9.7146414 | D35: ='Option Year'!C38 -> 169734.22 | E35: ='Option Year'!D38 -> 10.006081 | F35: ='Option Year'!E38 -> 174826.24 | G35: ='Option Year'!F38 -> 10.306263 | H35: ='Option Year'!G38 -> 180071.03 | I35: ='Option Year'!H38 -> 10.615451 | ... N35: ='Option Year'!M38 -> 10.31527 | O35: =IFERROR(D35/$D$45*D$47,0) -> 84093.821 | P35: =IFERROR(F35/$F$45*F$47,0) -> 86616.635 | Q35: =IFERROR(H35/$H$45*H$47,0) -> 89215.134 | R35: =IFERROR(J35/$J$45*J$47,0) -> 91891.588 | S35: =IFERROR(L35/$L$45*L$47,0) -> 94648.336 | T35: =SUM(O35:S35) -> 446465.51
A36: CLIN-0030 | B36: ='Option Year'!A40 -> Administrative / HR / Payroll | C36: ='Option Year'!B40 -> 0 | D36: ='Option Year'!C40 -> 0 | E36: ='Option Year'!D40 | F36: ='Option Year'!E40 | G36: ='Option Year'!F40 | H36: ='Option Year'!G40 | I36: ='Option Year'!H40 | ... N36: ='Option Year'!M40 -> 0 | O36: =IFERROR(D36/$D$45*D$47,0) -> 0 | P36: =IFERROR(F36/$F$45*F$47,0) -> 0 | Q36: =IFERROR(H36/$H$45*H$47,0) -> 0 | R36: =IFERROR(J36/$J$45*J$47,0) -> 0 | S36: =IFERROR(L36/$L$45*L$47,0) -> 0 | T36: =SUM(O36:S36) -> 0
A37: CLIN-0031 | B37: ='Option Year'!A41 -> Accounting / Legal | C37: ='Option Year'!B41 -> 0 | D37: ='Option Year'!C41 -> 0 | E37: ='Option Year'!D41 | F37: ='Option Year'!E41 | G37: ='Option Year'!F41 | H37: ='Option Year'!G41 | I37: ='Option Year'!H41 | ... N37: ='Option Year'!M41 -> 0 | O37: =IFERROR(D37/$D$45*D$47,0) -> 0 | P37: =IFERROR(F37/$F$45*F$47,0) -> 0 | Q37: =IFERROR(H37/$H$45*H$47,0) -> 0 | R37: =IFERROR(J37/$J$45*J$47,0) -> 0 | S37: =IFERROR(L37/$L$45*L$47,0) -> 0 | T37: =SUM(O37:S37) -> 0
A38: CLIN-0032 | B38: ='Option Year'!A42 -> Corporate Overhead | C38: ='Option Year'!B42 -> 4.19298 | D38: ='Option Year'!C42 -> 73259.747 | E38: ='Option Year'!D42 -> 4.3187694 | F38: ='Option Year'!E42 -> 75457.539 | G38: ='Option Year'!F42 -> 4.4483325 | H38: ='Option Year'!G42 -> 77721.265 | I38: ='Option Year'!H42 -> 4.5817825 | ... N38: ='Option Year'!M42 -> 4.4522201 | O38: =IFERROR(D38/$D$45*D$47,0) -> 36296.111 | P38: =IFERROR(F38/$F$45*F$47,0) -> 37384.995 | Q38: =IFERROR(H38/$H$45*H$47,0) -> 38506.545 | R38: =IFERROR(J38/$J$45*J$47,0) -> 39661.741 | S38: =IFERROR(L38/$L$45*L$47,0) -> 40851.593 | T38: =SUM(O38:S38) -> 192700.98
A39: CLIN-0033 | B39: ='Option Year'!A43 -> G&A | C39: ='Option Year'!B43 -> 3.354384 | D39: ='Option Year'!C43 -> 58607.797 | E39: ='Option Year'!D43 -> 3.4550155 | F39: ='Option Year'!E43 -> 60366.031 | G39: ='Option Year'!F43 -> 3.558666 | H39: ='Option Year'!G43 -> 62177.012 | I39: ='Option Year'!H43 -> 3.665426 | ... N39: ='Option Year'!M43 -> 3.561776 | O39: =IFERROR(D39/$D$45*D$47,0) -> 29036.889 | P39: =IFERROR(F39/$F$45*F$47,0) -> 29907.996 | Q39: =IFERROR(H39/$H$45*H$47,0) -> 30805.236 | R39: =IFERROR(J39/$J$45*J$47,0) -> 31729.393 | S39: =IFERROR(L39/$L$45*L$47,0) -> 32681.275 | T39: =SUM(O39:S39) -> 154160.79
A40: CLIN-0034 | B40: ='Option Year'!A44 -> Profit / Fee | C40: ='Option Year'!B44 -> 19.106529 | D40: ='Option Year'!C44 -> 333829.28 | E40: ='Option Year'!D44 -> 19.679725 | F40: ='Option Year'!E44 -> 343844.16 | G40: ='Option Year'!F44 -> 20.270117 | H40: ='Option Year'!G44 -> 354159.48 | I40: ='Option Year'!H44 -> 20.87822 | ... N40: ='Option Year'!M44 -> 20.287832 | O40: =IFERROR(D40/$D$45*D$47,0) -> 165393.76 | P40: =IFERROR(F40/$F$45*F$47,0) -> 170355.57 | Q40: =IFERROR(H40/$H$45*H$47,0) -> 175466.24 | R40: =IFERROR(J40/$J$45*J$47,0) -> 180730.22 | S40: =IFERROR(L40/$L$45*L$47,0) -> 186152.13 | T40: =SUM(O40:S40) -> 878097.92
A41: CLIN-0035 | B41: ='Option Year'!A45 -> Total Overhead / G&A / Profit | C41: ='Option Year'!B45 -> 26.653893 | D41: ='Option Year'!C45 -> 465696.82 | E41: ='Option Year'!D45 -> 27.45351 | F41: ='Option Year'!E45 -> 479667.73 | G41: ='Option Year'!F45 -> 28.277115 | H41: ='Option Year'!G45 -> 494057.76 | I41: ='Option Year'!H45 -> 29.125429 | ... N41: ='Option Year'!M45 -> 28.301828 | O41: =IFERROR(D41/$D$45*D$47,0) -> 230726.76 | P41: =IFERROR(F41/$F$45*F$47,0) -> 237648.56 | Q41: =IFERROR(H41/$H$45*H$47,0) -> 244778.02 | R41: =IFERROR(J41/$J$45*J$47,0) -> 252121.36 | S41: =IFERROR(L41/$L$45*L$47,0) -> 259685 | T41: =SUM(O41:S41) -> 1224959.7
A42: CLIN-0036 | B42: ='Option Year'!A47 -> Vehicle Cost per Labor Hour | C42: ='Option Year'!B47 -> 3.5046454 | D42: ='Option Year'!C47 -> 61233.164 | E42: ='Option Year'!D47 -> 3.6097847 | F42: ='Option Year'!E47 -> 63070.159 | G42: ='Option Year'!F47 -> 3.7180783 | H42: ='Option Year'!G47 -> 64962.263 | I42: ='Option Year'!H47 -> 3.8296206 | ... N42: ='Option Year'!M47 -> 3.7213276 | O42: =IFERROR(D42/$D$45*D$47,0) -> 30337.612 | P42: =IFERROR(F42/$F$45*F$47,0) -> 31247.74 | Q42: =IFERROR(H42/$H$45*H$47,0) -> 32185.172 | R42: =IFERROR(J42/$J$45*J$47,0) -> 33150.727 | S42: =IFERROR(L42/$L$45*L$47,0) -> 34145.249 | T42: =SUM(O42:S42) -> 161066.5
A43: CLIN-0037 | B43: ='Option Year'!A48 -> Uniform & Equipment Cost per Labor Hour | C43: ='Option Year'!B48 -> 1.1071394 | D43: ='Option Year'!C48 -> 19343.94 | E43: ='Option Year'!D48 -> 1.1403536 | F43: ='Option Year'!E48 -> 19924.258 | G43: ='Option Year'!F48 -> 1.1745642 | H43: ='Option Year'!G48 -> 20521.986 | I43: ='Option Year'!H48 -> 1.2098011 | ... N43: ='Option Year'!M48 -> 1.1755907 | O43: =IFERROR(D43/$D$45*D$47,0) -> 9583.8415 | P43: =IFERROR(F43/$F$45*F$47,0) -> 9871.3568 | Q43: =IFERROR(H43/$H$45*H$47,0) -> 10167.497 | R43: =IFERROR(J43/$J$45*J$47,0) -> 10472.522 | S43: =IFERROR(L43/$L$45*L$47,0) -> 10786.698 | T43: =SUM(O43:S43) -> 50881.916
A44: CLIN-0038 | B44: ='Option Year'!A49 -> Training Program Cost per Labor Hour | C44: ='Option Year'!B49 -> 2.2161172 | D44: ='Option Year'!C49 -> 38720 | E44: ='Option Year'!D49 -> 2.2826007 | F44: ='Option Year'!E49 -> 39881.6 | G44: ='Option Year'!F49 -> 2.3510788 | H44: ='Option Year'!G49 -> 41078.048 | I44: ='Option Year'!H49 -> 2.4216111 | ... N44: ='Option Year'!M49 -> 2.3531335 | O44: =IFERROR(D44/$D$45*D$47,0) -> 19183.597 | P44: =IFERROR(F44/$F$45*F$47,0) -> 19759.105 | Q44: =IFERROR(H44/$H$45*H$47,0) -> 20351.878 | R44: =IFERROR(J44/$J$45*J$47,0) -> 20962.434 | S44: =IFERROR(L44/$L$45*L$47,0) -> 21591.307 | T44: =SUM(O44:S44) -> 101848.32
A45: CLIN-0039 | B45: ='Option Year'!A51 -> Total Bill Rate | C45: ='Option Year'!B51 -> 86.914909 | D45: ='Option Year'!C51 -> 1518577.3 | E45: ='Option Year'!D51 -> 89.522356 | F45: ='Option Year'!E51 -> 1564134.6 | G45: ='Option Year'!F51 -> 92.208027 | H45: ='Option Year'!G51 -> 1611058.6 | I45: ='Option Year'!H51 -> 94.974267 | ... N45: ='Option Year'!M51 -> 92.288611 | O45: =IFERROR(D45/$D$45*D$47,0) -> 752370.2 | P45: =IFERROR(F45/$F$45*F$47,0) -> 774941.31 | Q45: =IFERROR(H45/$H$45*H$47,0) -> 798189.55 | R45: =IFERROR(J45/$J$45*J$47,0) -> 822135.23 | S45: =IFERROR(L45/$L$45*L$47,0) -> 846799.29 | T45: =SUM(O45:S45) -> 3994435.6
A46: CLIN-0040 | B46: ='Option Year'!A52 -> Appraisal Benchmark Driver (Rate × Annual Hours) | C46: ='Option Year'!B52 -> 129.97639 | D46: ='Option Year'!C52 -> 2270947.5 | E46: ='Option Year'!D52 -> 133.87568 | F46: ='Option Year'!E52 -> 2339075.9 | G46: ='Option Year'!F52 -> 137.89195 | H46: ='Option Year'!G52 -> 2409248.2 | I46: ='Option Year'!H52 -> 142.02871 | ... N46: ='Option Year'!M52 -> 138.01246 | O46: =IFERROR(D46/$D$45*D$47,0) -> 1125127.6 | P46: =IFERROR(F46/$F$45*F$47,0) -> 1158881.4 | Q46: =IFERROR(H46/$H$45*H$47,0) -> 1193647.9 | R46: =IFERROR(J46/$J$45*J$47,0) -> 1229457.3 | S46: =IFERROR(L46/$L$45*L$47,0) -> 1266341 | T46: =SUM(O46:S46) -> 5973455.2
A47: CLIN-0041 | B47: ='Option Year'!A53 -> Benchmark Delta vs Total Bill Rate | C47: ='Option Year'!B53 -> 43.061481 | D47: ='Option Year'!C53 -> 752370.2 | E47: ='Option Year'!D53 -> 44.353326 | F47: ='Option Year'!E53 -> 774941.31 | G47: ='Option Year'!F53 -> 45.683926 | H47: ='Option Year'!G53 -> 798189.55 | I47: ='Option Year'!H53 -> 47.054443 | ... N47: ='Option Year'!M53 -> 45.723851 | O47: =IFERROR(D47/$D$45*D$47,0) -> 372757.4 | P47: =IFERROR(F47/$F$45*F$47,0) -> 383940.12 | Q47: =IFERROR(H47/$H$45*H$47,0) -> 395458.33 | R47: =IFERROR(J47/$J$45*J$47,0) -> 407322.08 | S47: =IFERROR(L47/$L$45*L$47,0) -> 419541.74 | T47: =SUM(O47:S47) -> 1979019.7
A48: TOTAL | B48: Mapped contract totals / allocated recovery check | C48: =C45 -> 86.914909 | D48: =D45 -> 1518577.3 | E48: =E45 -> 89.522356 | F48: =F45 -> 1564134.6 | G48: =G45 -> 92.208027 | H48: =H45 -> 1611058.6 | I48: =I45 -> 94.974267 | J48: =J45 -> 1659390.4 | ... N48: =N45 -> 92.288611 | O48: =SUM(O7:O47) -> 4251650.3 | P48: =SUM(P7:P47) -> 4379199.8 | Q48: =SUM(Q7:Q47) -> 4510575.8 | R48: =SUM(R7:R47) -> 4645893.1 | S48: =SUM(S7:S47) -> 4785269.9 | T48: =SUM(T7:T47) -> 22572589

Sheet Contract Value Waterfall
A1: GASQ Contract Value Waterfall
A2: Base Year through Option Year 4 annual economics
A4: Contract Year | B4: Should-Cost Annual | C4: Benchmark Annual | D4: Capital Recovery | E4: Cumulative Recovery
A5: Base Year | B5: ='Option Year'!C51 -> 1518577.3 | C5: ='Option Year'!C52 -> 2270947.5 | D5: ='Option Year'!C53 -> 752370.2 | E5: =D5 -> 752370.2
A6: Option Year 1 | B6: ='Option Year'!E51 -> 1564134.6 | C6: ='Option Year'!E52 -> 2339075.9 | D6: ='Option Year'!E53 -> 774941.31 | E6: =E5+D6 -> 1527311.5
A7: Option Year 2 | B7: ='Option Year'!G51 -> 1611058.6 | C7: ='Option Year'!G52 -> 2409248.2 | D7: ='Option Year'!G53 -> 798189.55 | E7: =E6+D7 -> 2325501.1
A8: Option Year 3 | B8: ='Option Year'!I51 -> 1659390.4 | C8: ='Option Year'!I52 -> 2481525.6 | D8: ='Option Year'!I53 -> 822135.23 | E8: =E7+D8 -> 3147636.3
A9: Option Year 4 | B9: ='Option Year'!K51 -> 1709172.1 | C9: ='Option Year'!K52 -> 2555971.4 | D9: ='Option Year'!K53 -> 846799.29 | E9: =E8+D9 -> 3994435.6
A12: 5-Year Total | B12: =SUM(B5:B9) -> 8062333 | C12: =SUM(C5:C9) -> 12056769 | D12: =SUM(D5:D9) -> 3994435.6 | E12: =SUM(D5:D9) -> 3994435.6
A14: Scenario | B14: ='Option Year'!B3 -> Medium
A15: Escalation % | B15: ='Option Year'!B4 -> 0.03
A16: Base Annual Hours | B16: ='Option Year'!H3 -> 17472
A18: Line-Item Capital Recovery Detail
A19: Line Item | B19: Base | C19: Opt Yr 1 | D19: Opt Yr 2 | E19: Opt Yr 3 | F19: Opt Yr 4 | G19: 5-Year Total
A20: ='CLIN Pricing'!B7 -> Base Consolidated Blended Direct Labor Wage | B20: ='CLIN Pricing'!O7 -> 292066.93 | C20: ='CLIN Pricing'!P7 -> 300828.94 | D20: ='CLIN Pricing'!Q7 -> 309853.81 | E20: ='CLIN Pricing'!R7 -> 319149.42 | F20: ='CLIN Pricing'!S7 -> 328723.9 | G20: ='CLIN Pricing'!T7 -> 1550623
A21: ='CLIN Pricing'!B8 -> Locality Pay | B21: ='CLIN Pricing'!O8 -> 0 | C21: ='CLIN Pricing'!P8 -> 0 | D21: ='CLIN Pricing'!Q8 -> 0 | E21: ='CLIN Pricing'!R8 -> 0 | F21: ='CLIN Pricing'!S8 -> 0 | G21: ='CLIN Pricing'!T8 -> 0
A22: ='CLIN Pricing'!B9 -> Labor Market Adjustment | B22: ='CLIN Pricing'!O9 -> 0 | C22: ='CLIN Pricing'!P9 -> 0 | D22: ='CLIN Pricing'!Q9 -> 0 | E22: ='CLIN Pricing'!R9 -> 0 | F22: ='CLIN Pricing'!S9 -> 0 | G22: ='CLIN Pricing'!T9 -> 0
A23: ='CLIN Pricing'!B10 -> H&W (Cash) | B23: ='CLIN Pricing'!O10 -> 36530.007 | C23: ='CLIN Pricing'!P10 -> 37625.908 | D23: ='CLIN Pricing'!Q10 -> 38754.685 | E23: ='CLIN Pricing'!R10 -> 39917.325 | F23: ='CLIN Pricing'!S10 -> 41114.845 | G23: ='CLIN Pricing'!T10 -> 193942.77
A24: ='CLIN Pricing'!B11 -> Shift Differential | B24: ='CLIN Pricing'!O11 -> 0 | C24: ='CLIN Pricing'!P11 -> 0 | D24: ='CLIN Pricing'!Q11 -> 0 | E24: ='CLIN Pricing'!R11 -> 0 | F24: ='CLIN Pricing'!S11 -> 0 | G24: ='CLIN Pricing'!T11 -> 0
A25: ='CLIN Pricing'!B12 -> OT/Holiday Premium | B25: ='CLIN Pricing'!O12 -> 23365.354 | C25: ='CLIN Pricing'!P12 -> 24066.315 | D25: ='CLIN Pricing'!Q12 -> 24788.305 | E25: ='CLIN Pricing'!R12 -> 25531.954 | F25: ='CLIN Pricing'!S12 -> 26297.912 | G25: ='CLIN Pricing'!T12 -> 124049.84
A26: ='CLIN Pricing'!B13 -> DON/DOFF | B26: ='CLIN Pricing'!O13 -> 10998.822 | C26: ='CLIN Pricing'!P13 -> 11328.786 | D26: ='CLIN Pricing'!Q13 -> 11668.65 | E26: ='CLIN Pricing'!R13 -> 12018.709 | F26: ='CLIN Pricing'!S13 -> 12379.271 | G26: ='CLIN Pricing'!T13 -> 58394.238
A27: ='CLIN Pricing'!B14 -> Total Direct Labor | B27: ='CLIN Pricing'!O14 -> 362961.11 | C27: ='CLIN Pricing'!P14 -> 373849.95 | D27: ='CLIN Pricing'!Q14 -> 385065.45 | E27: ='CLIN Pricing'!R14 -> 396617.41 | F27: ='CLIN Pricing'!S14 -> 408515.93 | G27: ='CLIN Pricing'!T14 -> 1927009.8
A28: ='CLIN Pricing'!B15 -> FICA / Medicare | B28: ='CLIN Pricing'!O15 -> 27766.525 | C28: ='CLIN Pricing'!P15 -> 28599.521 | D28: ='CLIN Pricing'!Q15 -> 29457.507 | E28: ='CLIN Pricing'!R15 -> 30341.232 | F28: ='CLIN Pricing'!S15 -> 31251.469 | G28: ='CLIN Pricing'!T15 -> 147416.25
A29: ='CLIN Pricing'!B16 -> FUTA | B29: ='CLIN Pricing'!O16 -> 2177.7667 | C29: ='CLIN Pricing'!P16 -> 2243.0997 | D29: ='CLIN Pricing'!Q16 -> 2310.3927 | E29: ='CLIN Pricing'!R16 -> 2379.7045 | F29: ='CLIN Pricing'!S16 -> 2451.0956 | G29: ='CLIN Pricing'!T16 -> 11562.059
A30: ='CLIN Pricing'!B17 -> SUTA | B30: ='CLIN Pricing'!O17 -> 7259.2223 | C30: ='CLIN Pricing'!P17 -> 7476.999 | D30: ='CLIN Pricing'!Q17 -> 7701.3089 | E30: ='CLIN Pricing'!R17 -> 7932.3482 | F30: ='CLIN Pricing'!S17 -> 8170.3186 | G30: ='CLIN Pricing'!T17 -> 38540.197
A31: ='CLIN Pricing'!B18 -> Workers Compensation | B31: ='CLIN Pricing'!O18 -> 5807.3778 | C31: ='CLIN Pricing'!P18 -> 5981.5992 | D31: ='CLIN Pricing'!Q18 -> 6161.0471 | E31: ='CLIN Pricing'!R18 -> 6345.8786 | F31: ='CLIN Pricing'!S18 -> 6536.2549 | G31: ='CLIN Pricing'!T18 -> 30832.158
... A61: ='CLIN Pricing'!B48 -> Mapped contract totals / allocated recovery check | B61: ='CLIN Pricing'!O48 -> 4251650.3 | C61: ='CLIN Pricing'!P48 -> 4379199.8 | D61: ='CLIN Pricing'!Q48 -> 4510575.8 | E61: ='CLIN Pricing'!R48 -> 4645893.1 | F61: ='CLIN Pricing'!S48 -> 4785269.9 | G61: ='CLIN Pricing'!T48 -> 22572589
A62: Total Allocated Recovery | B62: ='CLIN Pricing'!O48 -> 4251650.3 | C62: ='CLIN Pricing'!P48 -> 4379199.8 | D62: ='CLIN Pricing'!Q48 -> 4510575.8 | E62: ='CLIN Pricing'!R48 -> 4645893.1 | F62: ='CLIN Pricing'!S48 -> 4785269.9 | G62: ='CLIN Pricing'!T48 -> 22572589

Sheet Summary
A1: GASQ Executive Summary
A2: GASQ brand refresh | TCO + Capital Recovery model | formulas reviewed and corrected
A3: Key Outputs
A4: Annual Coverage Hours | B4: =Appraisal_Full_Scope_Report!$F$15 -> 17472
A5: FTEs Required | B5: =Appraisal_Full_Scope_Report!$H$16 -> 12
A6: Government /Service Requestor TCO per Hour | B6: =Appraisal_Full_Scope_Report!$F$8 -> 129.97639
A7: Annual Total Cost of Ownership | B7: =Appraisal_Full_Scope_Report!$F$19 -> 2270947.5
A8: Annual Uniform & Equipment Cost | B8: =Uniform_Equipment!C35 -> 19343.94
A9: Vendor TCO Full Burden Rate | B9: =Appraisal_Full_Scope_Report!$H$8 -> 90.983473
A10: Vendor Absorbed Rate | B10: =Vendor_Pricing!B6 -> 63.688431
A11: Vendor Target Rate | B11: =Vendor_Pricing!B7 -> 77.335952
A12: Vendor Ceiling Rate | B12: =Vendor_Pricing!B8 -> 90.983473
A13: Capital Recovery per Hour | B13: =Appraisal_Full_Scope_Report!$J$8 -> 38.992917
A14: Annual Capital Recovery | B14: =Appraisal_Full_Scope_Report!$H$20 -> 681284.25
A15: Annual Vehicle Cost | B15: =Vehicle!C29 -> 61233.164
A16: Annual Capital Recovery Saved (Vendor TCO) | B16: =Appraisal_Full_Scope_Report!$H$20 -> 681284.25
A18: Model Checks & Cross-References
A19: Annual Uniform & Equipment Cost | B19: =Uniform_Equipment!C35 -> 19343.94
A20: Buyer vs Vendor Comparison
A21: Vendor TCO Annual Savings | B21: =Appraisal_Full_Scope_Report!$H$20 -> 681284.25
A22: Vendor Target Annual Savings | B22: =Buyer_Vendor_Comparison!D10 -> 919733.73
A23: Vendor Floor Annual Savings | B23: =Buyer_Vendor_Comparison!E10 -> 1158183.2
A24: Burden Build | B24: =Government_TCO!D37 -> 14.46
A25: Burden Check | B25: =Government_TCO!D39 -> 0
A27: Vendor Pricing Guardrails (Merged from Vendor_Pricing)
A28: Metric | B28: Value | C28: Source | D28: Notes
A29: Government/Buyer Should Cost per Coverage Hour | B29: =Vendor_Pricing!$B$4 -> 129.97639 | C29: Vendor_Pricing!B4 | D29: Benchmark from Appraisal/CFO
A30: Vendor Total Cost of Ownership Rate | B30: =Vendor_Pricing!$B$5 -> 90.983473 | C30: Vendor_Pricing!B5 | D30: Primary vendor benchmark
A31: Vendor LPTA Absorbed Rate | B31: =Vendor_Pricing!$B$6 -> 63.688431 | C31: Vendor_Pricing!B6 | D31: Lowest Price Technically Acceptable
A32: Vendor Target Rate | B32: =Vendor_Pricing!$B$7 -> 77.335952 | C32: Vendor_Pricing!B7 | D32: Midpoint of guardrail range
A33: Vendor TCO Rate | B33: =Vendor_Pricing!$B$8 -> 90.983473 | C33: Vendor_Pricing!B8 | D33: Upper benchmark rate
A34: Capital Recovery Saved per Hour | B34: =Vendor_Pricing!$B$9 -> 38.992917 | C34: Vendor_Pricing!B9 | D34: Savings vs buyer should-cost
A35: Annual Capital Recovery Saved | B35: =Vendor_Pricing!$B$10 -> 681284.25 | C35: Vendor_Pricing!B10 | D35: Annualized savings
A36: Minimum Weekly Hours for Floor Eligibility | B36: =Vendor_Pricing!$B$11 -> 1500 | C36: Vendor_Pricing!B11 | D36: Eligibility threshold
A37: Blended Actual Bill Rate | B37: =Vendor_Pricing!$B$12 -> 64.785 | C37: Vendor_Pricing!B12 | D37: Actual linked or manual rate
A39: Buyer vs Vendor Comparison (Merged from Buyer_Vendor_Comparison)
A40: Metric | B40: Buyer / Government | C40: Vendor TCO | D40: Vendor Target | E40: Vendor LPTA
A41: Annual Coverage Hours | B41: =Buyer_Vendor_Comparison!$B$5 -> 17472 | C41: =Buyer_Vendor_Comparison!$C$5 -> 17472 | D41: =Buyer_Vendor_Comparison!$D$5 -> 17472 | E41: =Buyer_Vendor_Comparison!$E$5 -> 17472
A42: FTEs Required | B42: =Buyer_Vendor_Comparison!$B$6 -> 12 | C42: =Buyer_Vendor_Comparison!$C$6 -> 12 | D42: =Buyer_Vendor_Comparison!$D$6 -> 12 | E42: =Buyer_Vendor_Comparison!$E$6 -> 12
A43: Rate per Productive Coverage Hour | B43: =Buyer_Vendor_Comparison!$B$7 -> 129.97639 | C43: =Buyer_Vendor_Comparison!$C$7 -> 90.983473 | D43: =Buyer_Vendor_Comparison!$D$7 -> 77.335952 | E43: =Buyer_Vendor_Comparison!$E$7 -> 63.688431
A44: Annual Total Cost | B44: =Buyer_Vendor_Comparison!$B$8 -> 2270947.5 | C44: =Buyer_Vendor_Comparison!$C$8 -> 1589663.2 | D44: =Buyer_Vendor_Comparison!$D$8 -> 1351213.8 | E44: =Buyer_Vendor_Comparison!$E$8 -> 1112764.3
A45: Hourly Savings vs Buyer | B45: =IFERROR(B45-C45,"-") -> - | C45: =Buyer_Vendor_Comparison!$C$9 -> 38.992917 | D45: =Buyer_Vendor_Comparison!$D$9 -> 52.640438 | E45: =Buyer_Vendor_Comparison!$E$9 -> 66.287959
A46: Annual Capital Recovery Saved | B46: =IFERROR(B46-C46,"-") -> - | C46: =Buyer_Vendor_Comparison!$C$10 -> 681284.25 | D46: =Buyer_Vendor_Comparison!$D$10 -> 919733.73 | E46: =Buyer_Vendor_Comparison!$E$10 -> 1158183.2
A47: Savings % vs Buyer | C47: =Buyer_Vendor_Comparison!$C$11 -> 0.3 | D47: =Buyer_Vendor_Comparison!$D$11 -> 0.405 | E47: =Buyer_Vendor_Comparison!$E$11 -> 0.51
A49: Comparison Highlights
A50: Buyer annual in-house/government-equivalent cost | B50: =Buyer_Vendor_Comparison!$B$22 -> 2270947.5
A51: Vendor annual cost at TCO rate | B51: =Buyer_Vendor_Comparison!$B$23 -> 1589663.2
A52: Vendor annual cost at target rate | B52: =Buyer_Vendor_Comparison!$B$24 -> 298912.74
A53: Vendor annual cost at floor rate | B53: =Buyer_Vendor_Comparison!$B$25 -> 246163.43
A54: Best annual capital recovery using vendor floor | B54: =Buyer_Vendor_Comparison!$B$26 -> 2024784.1

Sheet GASQ_Dashboard
A1: GASQ Security Cost Dashboard
A3: Cost Comparison | B3: Amount
A4: In-House TCO | B4: =Government_TCO!B12 -> 2270947.5
A5: Outsourced TCO | B5: =Government_TCO!B13 -> 1589663.2
A6: Capital Recovered | B6: =Government_TCO!B15 -> 681284.25
A8: Cost Breakdown
A9: Category | B9: Cost
A10: Direct Labor | B10: =Direct_Labor!D11 -> 732597.47
A11: Employer Burden | B11: =Direct_Labor!D22 -> 14651.949
A12: Workforce Maintenance | B12: =Workforce_Maintenance_Module!E7 -> 15029.44
A13: Training | B13: =Training_Module!J9 -> 38720
A14: Equipment | B14: =Uniform_Equipment!C35 -> 19343.94
A15: Admin | B15: =SUM(Overhead_GA!D4:D7) -> 131867.54
A16: Vendor Price Evaluation
A17: Range | B17: Rate
A18: Vendor Lowest Price Technically Accepted (LPTA) Rate | B18: =Vendor_Pricing!B6 -> 63.688431
A19: Vendor Target Rate | B19: =Vendor_Pricing!B7 -> 77.335952
A20: Vendor Total Cost of Ownership Rate | B20: =Vendor_Pricing!B8 -> 90.983473
A22: Capital Recovery Timeline
A23: Month | B23: Savings
A24: 1 | B24: =Government_TCO!B15*(1/12) -> 56773.687
A25: 3 | B25: =Government_TCO!B15*(3/12) -> 170321.06
A26: 6 | B26: =Government_TCO!B15*(6/12) -> 340642.12
A27: 8 | B27: =Government_TCO!B15*(8/12) -> 454189.5
A28: 12 | B28: =Government_TCO!B15 -> 681284.25

Sheet Contract_Summary
B1: GASQ Workforce-to-Post™ Capital Recovery Contract Summary
B2: Executive contract summary with TCO, pricing guardrails, and capital recovery outputs | J2: =IF(IFERROR(_Calc_Backend!$U$5,0)>0,_Calc_Backend!$U$5,_Calc_Backend!$X$36) -> 336
B3: CONFIDENTIAL | J3: =IF(IFERROR(_Calc_Backend!$U$5,0)>0,_Calc_Backend!$U$15,Vendor_Pricing!B7) -> 64.785
J4: =IF(IFERROR(_Calc_Backend!$U$5,0)>0,_Calc_Backend!$U$14,Direct_Labor!C11) -> 33.74
J5: =Direct_Labor!C5 -> 0
J6: =Direct_Labor!C7 -> 4.22
B7: Contract Economics | J7: =Direct_Labor!C23 -> 1.677192
B8: Weekly Hours | F8: =J2 -> 336 | J8: =IF(IFERROR(_Calc_Backend!$U$5,0)>0,_Calc_Backend!$U$7,J2*J3) -> 21767.76
B9: Weekly Billings (excluding holiday billings) | F9: =J8 -> 21767.76 | J9: =J8*52 -> 1131923.5
B10: Should-Cost Straight Time Pay Rate | F10: =J4 -> 33.74 | J10: =IF(IFERROR(_Calc_Backend!$U$5,0)>0,_Calc_Backend!$U$17+_Calc_Backend!$U$18,Direct_Labor!D23+Operations!D14) -> 589505.28
B11: Blended Straight Time Bill Rate | F11: =J3 -> 64.785 | J11: =Vehicle!C29 -> 61233.164
B12: Overtime Bill Rate | F12: =J20 -> 97.1775 | J12: =Vehicle!C29 -> 61233.164
B13: Holiday Bill Rate | F13: =J21 -> 97.1775 | J13: =J9+J11 -> 1193156.7
B14: Effective Pay Rate | F14: =J7 -> 1.677192 | J14: =J10+J12 -> 650738.44
B15: Effective Bill Rate | F15: =J22 -> 308.69848 | J15: =J13-J14 -> 542418.24
B16: Effective Direct Labor Ratio | F16: =J18 -> 0.025888585 | J16: =IFERROR(J15/J13,0) -> 0.45460772
B17: Effective Markup | F17: =J19 -> 38.627062 | J17: =IFERROR(J15/_Calc_Backend!$X$33,0) -> 140.33671
J18: =IFERROR(J7/J3,0) -> 0.025888585
B19: Revenue & Cost Summary | J19: =IFERROR(J3/J7,0) -> 38.627062
B20: Total Annual Revenue (from hourly billings) * | F20: =J9 -> 1131923.5 | J20: =J3*1.5 -> 97.1775
B21: Vehicle and Other Pass Through Billings | F21: =J11 -> 61233.164 | J21: =J3*1.5 -> 97.1775
B22: Total Annual Contract Revenue * | F22: =Appraisal_Full_Scope_Report!F32 -> 0 | J22: =IFERROR(J13/_Calc_Backend!$X$33,0) -> 308.69848
J23: =Government_TCO!B8 -> 129.97639
B24: Direct Expense | F24: =J10 -> 589505.28 | J24: =Vendor_Pricing!B5 -> 90.983473
B25: Vehicle and Other Pass Through Costs | F25: =J12 -> 61233.164 | J25: =Vendor_Pricing!B6 -> 63.688431
B26: Total Annual Costs * | F26: =J14 -> 650738.44 | J26: =Vendor_Pricing!B7 -> 77.335952
J27: =Vendor_Pricing!B8 -> 90.983473
B28: Contributory Profit | F28: =J15 -> 542418.24 | J28: =Vendor_Pricing!B9 -> 38.992917
B29: Profit as a % of Revenue | F29: =Inputs!B39 -> 0.21 | J29: =Inputs!B39 -> 0.21
B30: Contributory Profit Per Hour | F30: =J17 -> 140.33671 | J30: =Buyer_Vendor_Comparison!C11 -> 0.3
B31: Working Capital Requirement | F31: =J12 -> 61233.164 | J31: =IFERROR(J14/12,0) -> 54228.204
B32: Payback & Recovery Period (months) | F32: =IFERROR(H19/(F19/12),0) -> 0 | J32: =IFERROR(H19/(F19/12),0) -> 0
J33: =IFERROR((J26-J25)/(J27-J25),0) -> 0.5
B34: Total Monthly Hours of Coverage | F34: =Appraisal_Full_Scope_Report!F12 -> 1456
B35: Total Annual Hours of Coverage | F35: =Appraisal_Full_Scope_Report!F13 -> 3865.12
B36: Vendor True Cost of Ownership Rate | F36: =J24 -> 90.983473 | J36: =IFERROR(J29/J35,0) -> 0
B37: Vendor Absorbed Rate | F37: =J25 -> 63.688431
B38: Vendor Target Rate | F38: =J26 -> 77.335952
B39: Vendor True Cost of Ownership Rate | F39: =J27 -> 90.983473
B40: Capital Recovery Saved per Hour | F40: =J28 -> 38.992917
B41: Annual Capital Recovery Saved | F41: =J29 -> 0.21
B42: Savings % vs Buyer | F42: =J30 -> 0.3
B44: Guardrails & Rating
B45: Minimum Weekly Hours for Floor Eligibility | F45: =J31 -> 54228.204
B46: Current Weekly Hours Eligibility Status | F46: =J32 -> 0
B47: Target Position within Floor-to-Ceiling Range | F47: =J33 -> 0.5
B48: GASQ Cost Rating Grade | F48: =J34 -> 0
B49: Total Weeks of Coverage | F49: =Appraisal_Full_Scope_Report!F14 -> 336
B50: Total Months of Coverage
B51: Total Workforce Required for Coverage | F51: =Appraisal_Full_Scope_Report!F16 -> 12
B53: * Total contract amounts shown assume the current annual coverage requirement from the GASQ model. Modify Scope_of_Work inputs to update automatically.

Sheet Government_IGCE_Model
A1: Cost Category | B1: Input | C1: Formula / Notes
A2: Direct Labor Rate | B2: 21 | C2: User Input
A3: Burden Build Up | B3: =IFERROR(B2/Inputs!$B$43,0) -> 30 | C3: =B2/0.7 -> 30
A4: Workforce Maintenance Cost | B4: =Workforce_Maintenance_Module!E7 -> 15029.44 | C4: Linked from Workforce_Maintenance_Module
A5: Training Cost | B5: =Training_Module!J9 -> 38720 | C5: Linked from Training_Module
A6: Equipment Cost | B6: =Equipment_Uniform_Module!E7 -> 1447.5 | C6: Linked from Equipment_Uniform_Module
A7: Total Estimated Cost | B7: =SUM(B3:B6) -> 55226.94 | C7: =SUM(B3:B6) -> 55226.94

Sheet Vendor_Pricing
A1: GASQ Vendor Pricing Guardrails
A2: Rates benchmarked to GASQ government TCO, vendor TCO, floor, and target guardrails.
A3: Pricing Model
A4: Government/Service Requester Should Cost per Security Professional Coverage Hour | B4: =Appraisal_Full_Scope_Report!$F$8 -> 129.97639
A5: Vendor Total Cost of Ownership Rate | B5: =Appraisal_Full_Scope_Report!$H$8 -> 90.983473
A6: Vendor Lowest Price Technically Accepted Absorbed Rate | B6: =B5*Inputs!$B$41 -> 63.688431
A7: Vendor LPTA/BAFO Rate | B7: =B6+((B5-B6)/2) -> 77.335952
A8: Vendor TCO Rate | B8: =B5 -> 90.983473
A9: Capital Recovery Saved per Hour | B9: =Appraisal_Full_Scope_Report!$J$8 -> 38.992917
A10: Annual Capital Recovery Saved | B10: =Appraisal_Full_Scope_Report!$H$20 -> 681284.25
A11: Minimum Weekly Hours for Floor Eligibility | B11: =Inputs!B42 -> 1500
A12: Blended Actual Bill Rate from Post_Positions | B12: =IF(IFERROR(_Calc_Backend!$U$5,0)>0,_Calc_Backend!$U$15,"") -> 64.785 | D12: Feed Status | E12: =IF(_Calc_Backend!$U$5>0,"Linked","Manual") -> Linked
A13: Vendor Evaluation Inputs
A14: Vendor | B14: Bid Rate | C14: Vendor Weekly Hours Billed | D14: Floor Eligible? | E14: Enter bidder rate and weekly hours only | F14: Initial Interpretation
A15: Vendor 1 | B15: 35 | C15: 0 | D15: =IF(C15="","",IF(C15>=B11,"Yes","No")) -> No | E15: =IF(B15="","",IF(B15<B6,"Below Floor",IF(B15<B7,"Between Floor and Target",IF(B15<=B8,"Between Target and Ceiling","Above Ceiling")))) -> Below Floor | F15: =IF(B15="","",IF(B15<B6,"Unrealistic / high performance risk",IF(B15<B7,"Aggressive pricing",IF(B15<=B8,"Competitive and reasonable","Potentially overpriced")))) -> Unrealistic / high performance risk
A16: Vendor 2 | B16: 37 | C16: 0 | D16: =IF(C16="","",IF(C16>=B11,"Yes","No")) -> No | E16: =IF(B16="","",IF(B16<B6,"Below Floor",IF(B16<B7,"Between Floor and Target",IF(B16<=B8,"Between Target and Ceiling","Above Ceiling")))) -> Below Floor | F16: =IF(B16="","",IF(B16<B6,"Unrealistic / high performance risk",IF(B16<B7,"Aggressive pricing",IF(B16<=B8,"Competitive and reasonable","Potentially overpriced")))) -> Unrealistic / high performance risk
A17: Vendor 3 | B17: 41 | C17: 0 | D17: =IF(C17="","",IF(C17>=B11,"Yes","No")) -> No | E17: =IF(B17="","",IF(B17<B6,"Below Floor",IF(B17<B7,"Between Floor and Target",IF(B17<=B8,"Between Target and Ceiling","Above Ceiling")))) -> Below Floor | F17: =IF(B17="","",IF(B17<B6,"Unrealistic / high performance risk",IF(B17<B7,"Aggressive pricing",IF(B17<=B8,"Competitive and reasonable","Potentially overpriced")))) -> Unrealistic / high performance risk
A18: Vendor 4 | B18: 42 | C18: 0 | D18: =IF(C18="","",IF(C18>=B11,"Yes","No")) -> No | E18: =IF(B18="","",IF(B18<B6,"Below Floor",IF(B18<B7,"Between Floor and Target",IF(B18<=B8,"Between Target and Ceiling","Above Ceiling")))) -> Below Floor | F18: =IF(B18="","",IF(B18<B6,"Unrealistic / high performance risk",IF(B18<B7,"Aggressive pricing",IF(B18<=B8,"Competitive and reasonable","Potentially overpriced")))) -> Unrealistic / high performance risk
A19: Vendor 5 | B19: 50 | C19: 0 | D19: =IF(C19="","",IF(C19>=B11,"Yes","No")) -> No | E19: =IF(B19="","",IF(B19<B6,"Below Floor",IF(B19<B7,"Between Floor and Target",IF(B19<=B8,"Between Target and Ceiling","Above Ceiling")))) -> Below Floor | F19: =IF(B19="","",IF(B19<B6,"Unrealistic / high performance risk",IF(B19<B7,"Aggressive pricing",IF(B19<=B8,"Competitive and reasonable","Potentially overpriced")))) -> Unrealistic / high performance risk

Sheet Security_Cost_Rating_Report
A1: GASQ Security Cost Rating Report™
A2: Automated grading of the active roster rate against floor, target, and ceiling guardrails.
A4: Government TCO Benchmark | B4: =Appraisal_Full_Scope_Report!$F$8 -> 129.97639 | D4: Government-style TCO per productive hour.
A5: Vendor Absorbed Floor | B5: =Vendor_Pricing!$B$6 -> 63.688431 | D5: Minimum sustainable absorbed floor.
A6: Vendor Target | B6: =Vendor_Pricing!$B$7 -> 77.335952 | D6: Preferred best-value band midpoint.
A7: Vendor Ceiling | B7: =Appraisal_Full_Scope_Report!$H$8 -> 90.983473 | D7: Upper sustainable range benchmark.
A8: Actual Blended Bill Rate | B8: =IF(_Calc_Backend!U5>0,_Calc_Backend!U15,Vendor_Pricing!B7) -> 64.785 | D8: Current blended rate from roster if active.
A9: Delta vs Gov TCO | B9: =B8-B4 -> -65.19139
A10: Delta vs Target | B10: =B8-B6 -> -12.550952
A11: Security Cost Position | B11: =IF(B8<B5,"Below Floor",IF(B8<B6,"Floor to Target",IF(B8<=B7,"Target to Ceiling","Above Ceiling"))) -> Floor to Target | D11: Used for grade logic.
A12: SCRS Grade | B12: =IF(B11="Below Floor","D",IF(B11="Floor to Target","A",IF(B11="Target to Ceiling","B","C"))) -> A | D12: A = best value; D = high risk underbid.
A13: Executive Recommendation | B13: =IF(B12="A","Strong pricing alignment",IF(B12="B","Acceptable but monitor margin",IF(B12="C","Premium pricing; justify scope or quality","Underpriced; performance risk"))) -> Strong pricing alignment
A14: Annual Capital Recovery Saved | B14: =MAX(0,Appraisal_Full_Scope_Report!$H$20) -> 681284.25
A15: Capital Recovery % | B15: =Appraisal_Full_Scope_Report!$H$21 -> 0.3

Sheet Capital_Recovery_Receipt
A1: GASQ Capital Recovery Receipt™
A2: Point-of-sale style summary of annual and hourly economics for buyer-facing review.
A4: Line Item | B4: Should-Cost View | C4: Vendor / GASQ View | E4: Receipt Notes
A5: Coverage Hours (Annual) | B5: =Appraisal_Full_Scope_Report!$F$15 -> 17472 | C5: =Appraisal_Full_Scope_Report!$F$15 -> 17472 | E5: Shows the government benchmark and GASQ alternative side by side.
A6: Hourly Rate | B6: =Appraisal_Full_Scope_Report!$F$8 -> 129.97639 | C6: =Appraisal_Full_Scope_Report!$H$8 -> 90.983473 | E6: Vendor/GASQ view uses active blended roster rate when available.
A7: Annual Cost | B7: =Appraisal_Full_Scope_Report!$F$19 -> 2270947.5 | C7: =Appraisal_Full_Scope_Report!$H$19 -> 1589663.2 | E7: All-in annual view includes recurring training, maintenance, and equipment.
A8: Training Annual | B8: =Training_Module!J9 -> 38720 | C8: =Training_Module!J9 -> 38720 | E8: Capital recovered = benchmark all-in annual cost less GASQ all-in annual cost.
A9: Workforce Maintenance Annual | B9: =Workforce_Maintenance_Module!E7 -> 15029.44 | C9: =Workforce_Maintenance_Module!E7 -> 15029.44 | E9: Use this sheet as the buyer-safe summary.
A10: Equipment / Uniform Annual | B10: =Equipment_Uniform_Module!E7 -> 1447.5 | C10: =Equipment_Uniform_Module!E7 -> 1447.5
A11: All-In Annual View | B11: =SUM(B7:B10) -> 2326144.4 | C11: =SUM(C7:C10) -> 1644860.2
A12: Capital Recovered ($) | C12: =Appraisal_Full_Scope_Report!$H$20 -> 681284.25
A13: Capital Recovered (%) | C13: =Appraisal_Full_Scope_Report!$H$21 -> 0.3

Sheet Vendor_Price_Evaluation
A1: GASQ Vendor Price Evaluation
A2: Evaluates sample and actual rates against the floor, target, and ceiling bands.
A4: Vendor / Scenario | B4: Bid Rate | C4: Delta vs Gov TCO | D4: Delta % | E4: Band | F4: Recommendation | G4: Annual Cost
A5: Absorbed Floor | B5: =Vendor_Pricing!B6 -> 63.688431 | C5: =B5-Appraisal_Full_Scope_Report!$F$8 -> -66.287959 | D5: =IFERROR(C5/Appraisal_Full_Scope_Report!$F$8,0) -> -0.51 | E5: =IF(B5<Vendor_Pricing!B6,"Below Floor",IF(B5<Vendor_Pricing!B7,"Floor to Target",IF(B5<=Vendor_Pricing!B8,"Target to Ceiling","Above Ceiling"))) -> Floor to Target | F5: =IF(E5="Below Floor","High risk underbid",IF(E5="Floor to Target","Best value",IF(E5="Target to Ceiling","Acceptable","Overpriced"))) -> Best value | G5: =B5*Workforce_to_Post!B5 -> 246163.43
A6: Target | B6: =Vendor_Pricing!B7 -> 77.335952 | C6: =B6-Appraisal_Full_Scope_Report!$F$8 -> -52.640438 | D6: =IFERROR(C6/Appraisal_Full_Scope_Report!$F$8,0) -> -0.405 | E6: =IF(B6<Vendor_Pricing!B6,"Below Floor",IF(B6<Vendor_Pricing!B7,"Floor to Target",IF(B6<=Vendor_Pricing!B8,"Target to Ceiling","Above Ceiling"))) -> Target to Ceiling | F6: =IF(E6="Below Floor","High risk underbid",IF(E6="Floor to Target","Best value",IF(E6="Target to Ceiling","Acceptable","Overpriced"))) -> Acceptable | G6: =B6*Workforce_to_Post!B5 -> 298912.74
A7: Ceiling | B7: =Vendor_Pricing!B8 -> 90.983473 | C7: =B7-Appraisal_Full_Scope_Report!$F$8 -> -38.992917 | D7: =IFERROR(C7/Appraisal_Full_Scope_Report!$F$8,0) -> -0.3 | E7: =IF(B7<Vendor_Pricing!B6,"Below Floor",IF(B7<Vendor_Pricing!B7,"Floor to Target",IF(B7<=Vendor_Pricing!B8,"Target to Ceiling","Above Ceiling"))) -> Target to Ceiling | F7: =IF(E7="Below Floor","High risk underbid",IF(E7="Floor to Target","Best value",IF(E7="Target to Ceiling","Acceptable","Overpriced"))) -> Acceptable | G7: =B7*Workforce_to_Post!B5 -> 351662.04
A8: Actual Blended Rate | B8: =IF(_Calc_Backend!U5>0,_Calc_Backend!U15,Vendor_Pricing!B7) -> 64.785 | C8: =B8-Appraisal_Full_Scope_Report!$F$8 -> -65.19139 | D8: =IFERROR(C8/Appraisal_Full_Scope_Report!$F$8,0) -> -0.50156332 | E8: =IF(B8<Vendor_Pricing!B6,"Below Floor",IF(B8<Vendor_Pricing!B7,"Floor to Target",IF(B8<=Vendor_Pricing!B8,"Target to Ceiling","Above Ceiling"))) -> Floor to Target | F8: =IF(E8="Below Floor","High risk underbid",IF(E8="Floor to Target","Best value",IF(E8="Target to Ceiling","Acceptable","Overpriced"))) -> Best value | G8: =B8*Workforce_to_Post!B5 -> 250401.8

Sheet Government_IGCE_Comparison
A1: GASQ Government IGCE Comparison
A2: Compares the government-style estimate to the active GASQ roster-driven model.
A4: Cost Component | B4: Government IGCE | C4: GASQ Active Model | D4: Variance | E4: Variance % | F4: Notes
A5: Direct Labor Build-Up | B5: =Government_IGCE_Model!B3 -> 30 | C5: =Government_TCO!B7 -> 180460.8 | D5: =C5-B5 -> 180430.8 | E5: =IFERROR(D5/B5,0) -> 6014.36 | F5: Government direct labor build-up vs annual workforce cost.
A6: Training | B6: =Government_IGCE_Model!B5 -> 38720 | C6: =Training_Module!J9 -> 38720 | D6: =C6-B6 -> 0 | E6: =IFERROR(D6/B6,0) -> 0 | F6: Training recurring annual cost.
A7: Workforce Maintenance | B7: =Government_IGCE_Model!B4 -> 15029.44 | C7: =Workforce_Maintenance_Module!E7 -> 15029.44 | D7: =C7-B7 -> 0 | E7: =IFERROR(D7/B7,0) -> 0 | F7: Paid time not worked, turnover, and support labor.
A8: Equipment / Uniform | B8: =Government_IGCE_Model!B6 -> 1447.5 | C8: =Equipment_Uniform_Module!E7 -> 1447.5 | D8: =C8-B8 -> 0 | E8: =IFERROR(D8/B8,0) -> 0 | F8: Uniform, radios, armor, and other annualized gear.
A9: Total Estimate | B9: =Government_IGCE_Model!B7 -> 55226.94 | C9: =Capital_Recovery_Receipt!C11 -> 1644860.2 | D9: =C9-B9 -> 1589633.2 | E9: =IFERROR(D9/B9,0) -> 28.783656 | F9: Top-line comparison of estimate frameworks.

Sheet Capital_Recovery_Dashboard
A1: GASQ Capital Recovery Dashboard
A2: Single-page dashboard for Security Cost Rating, Capital Recovery Receipt, Vendor Price Evaluation, and IGCE comparison.
A4: KPI | B4: Value | D4: Security Cost Rating | G4: Vendor Price Evaluation
A5: Annual Coverage Hours | B5: =Appraisal_Full_Scope_Report!$F$15 -> 17472 | D5: Actual Rate Position | E5: =IF(B8="","No Rate",IF(B8<Vendor_Pricing!B6,"Below Floor",IF(B8<Vendor_Pricing!B7,"Floor to Target",IF(B8<=Vendor_Pricing!B8,"Target to Ceiling","Above Ceiling")))) -> Floor to Target | G5: Scenario | H5: Rate | I5: Interpretation
A6: Government TCO / Hr | B6: =Appraisal_Full_Scope_Report!$F$8 -> 129.97639 | D6: SCRS Grade | E6: =IF(E5="Below Floor","D",IF(E5="Floor to Target","A",IF(E5="Target to Ceiling","B",IF(E5="Above Ceiling","C","NR")))) -> A | G6: Below Floor | H6: =Vendor_Pricing!B6-0.01 -> 63.678431 | I6: Unrealistic / high risk
A7: Vendor TCO / Hr | B7: =Appraisal_Full_Scope_Report!$H$8 -> 90.983473 | D7: Recommendation | E7: =IF(E5="Below Floor","High performance risk / underbid",IF(E5="Floor to Target","Best value zone",IF(E5="Target to Ceiling","Acceptable with justification",IF(E5="Above Ceiling","Premium / likely overpriced","Review inputs")))) -> Best value zone | G7: Floor to Target | H7: =AVERAGE(Vendor_Pricing!B6,Vendor_Pricing!B7) -> 70.512192 | I7: Best value
A8: Actual Bill Rate / Hr | B8: =IF(_Calc_Backend!U5>0,_Calc_Backend!U15,Vendor_Pricing!B7) -> 64.785 | G8: Target to Ceiling | H8: =AVERAGE(Vendor_Pricing!B7,Vendor_Pricing!B8) -> 84.159713 | I8: Acceptable
A9: Annual Government Cost | B9: =Appraisal_Full_Scope_Report!$F$19 -> 2270947.5 | D9: Comparison | G9: Above Ceiling | H9: =Vendor_Pricing!B8+0.01 -> 90.993473 | I9: Likely overpriced
A10: Annual Actual Vendor Cost | B10: =Appraisal_Full_Scope_Report!$H$19 -> 1589663.2 | D10: IGCE Total Estimated Cost | E10: =Government_IGCE_Model!B7 -> 55226.94 | G10: Actual Blended Rate | H10: =IF(_Calc_Backend!U5>0,_Calc_Backend!U15,Vendor_Pricing!B7) -> 64.785 | I10: =E7 -> Best value zone
A11: Annual Capital Recovered | B11: =Appraisal_Full_Scope_Report!$H$20 -> 681284.25 | D11: Training Annual | E11: =Training_Module!J9 -> 38720
A12: Capital Recovery % | B12: =Appraisal_Full_Scope_Report!$H$21 -> 0.3 | D12: Workforce Maintenance Annual | E12: =Workforce_Maintenance_Module!E7 -> 15029.44
D13: Equipment Annual | E13: =Equipment_Uniform_Module!E7 -> 1447.5
D14: Hidden Workforce Cost Total | E14: =Workforce_to_Post!B18 -> 242986.11

Sheet Advanced_Dashboard
A1: GASQ Advanced Analytics Dashboard
A3: Vendor Price Evaluation | B3: Rate
A4: Floor | B4: =Vendor_Pricing!B6 -> 63.688431
A5: Target | B5: =Vendor_Pricing!B7 -> 77.335952
A6: Ceiling | B6: =Vendor_Pricing!B8 -> 90.983473
A8: Workforce Efficiency
A9: Category | B9: Hours
A10: Hours Worked | B10: =Inputs!B6 -> 1456
A11: Paid Not Worked | B11: =Inputs!B44-Inputs!B6 -> 2288
A12: Training Hours | B12: =IFERROR(Training_Module!J9/Workforce_to_Post!B13,0) -> 1147.5993
A15: Post Cost Distribution
A16: Post | B16: Labor | C16: Training | D16: Equipment
A17: =IF(_Calc_Backend!B7="","Post 1",_Calc_Backend!B7) -> Post 1 | B17: =IFERROR(_Calc_Backend!O7*52,0) -> 294752.64 | C17: =IFERROR(_Calc_Backend!Q7*52,0) -> 0 | D17: =IFERROR((_Calc_Backend!S7/_Calc_Backend!U10)*Uniform_Equipment!C35,0) -> 9671.97
A18: =IF(_Calc_Backend!B8="","Post 2",_Calc_Backend!B8) -> Post 2 | B18: =IFERROR(_Calc_Backend!O8*52,0) -> 294752.64 | C18: =IFERROR(_Calc_Backend!Q8*52,0) -> 0 | D18: =IFERROR((_Calc_Backend!S8/_Calc_Backend!U10)*Uniform_Equipment!C35,0) -> 9671.97
A19: =IF(_Calc_Backend!B9="","Post 3",_Calc_Backend!B9) -> Post 3 | B19: =IFERROR(_Calc_Backend!O9*52,0) -> 0 | C19: =IFERROR(_Calc_Backend!Q9*52,0) -> 0 | D19: =IFERROR((_Calc_Backend!S9/_Calc_Backend!U10)*Uniform_Equipment!C35,0) -> 0
A22: Capital Recovery Gauge
A23: Metric | B23: Value
A24: Recovered | B24: =Government_TCO!B15 -> 681284.25
A25: Remaining | B25: =Government_TCO!B13 -> 1589663.2

Sheet Operations
A1: GASQ Operations & Contract Support
A2: GASQ-branded operating model worksheet
A3: Line Item | B3: Input / Formula | C3: Hourly Amount | D3: Annual Amount
A4: Recruiting / Hiring | B4: =Direct_Labor!$C$11*Inputs!B23 -> 0 | C4: =B4 -> 0 | D4: =C4*_Calc_Backend!$X$37 -> 0
A5: Training / Certification | B5: =Direct_Labor!$C$11*Inputs!B24 -> 0.628947 | C5: =B5 -> 0.628947 | D5: =C5*_Calc_Backend!$X$37 -> 10988.962
A6: Uniforms / Equipment | B6: =Uniform_Equipment!$C$36 -> 1.1071394 | C6: =B6 -> 1.1071394 | D6: =Uniform_Equipment!$C$35 -> 19343.94
A7: Field Supervision | B7: =Direct_Labor!$C$11*Inputs!B26 -> 0 | C7: =B7 -> 0 | D7: =C7*_Calc_Backend!$X$37 -> 0
A8: Contract Management | B8: =Direct_Labor!$C$11*Inputs!B27 -> 0 | C8: =B8 -> 0 | D8: =C8*_Calc_Backend!$X$37 -> 0
A9: Quality Assurance | B9: =Direct_Labor!$C$11*Inputs!B28 -> 0 | C9: =B9 -> 0 | D9: =C9*_Calc_Backend!$X$37 -> 0
A10: Vehicles / Patrol | B10: =Vehicle!$C$30 -> 3.5046454 | C10: =B10 -> 3.5046454 | D10: =Vehicle!$C$29 -> 61233.164
A11: Technology / Systems | B11: =Direct_Labor!$C$11*Inputs!B30 -> 0.419298 | C11: =B11 -> 0.419298 | D11: =C11*_Calc_Backend!$X$37 -> 7325.9747
A12: General Liability Insurance | B12: =Direct_Labor!$C$11*Inputs!B31 -> 3.7401382 | C12: =B12 -> 3.7401382 | D12: =C12*_Calc_Backend!$X$37 -> 65347.694
A13: Umbrella / Other Insurance | B13: =Direct_Labor!$C$11*Inputs!B32 -> 0.3144735 | C13: =B13 -> 0.3144735 | D13: =C13*_Calc_Backend!$X$37 -> 5494.481
A14: Total Operations / Support | C14: =SUM(C4:C13) -> 9.7146414 | D14: =SUM(D4:D13) -> 169734.22

Sheet Government_TCO
A1: GASQ Should-Cost TCO & Capital Recovery Engine
A2: Uses the GASQ labor-share framework to translate direct labor into government TCO and capital recovery savings.
A3: Government TCO Formula Engine
A4: Blended Direct Labor Wage / Pay Rate | B4: =IF(IFERROR(_Calc_Backend!$U$5,0)>0,_Calc_Backend!$U$14,Inputs!$B$4) -> 33.74
A5: Full Burdened Hourly Cost | B5: =IFERROR(B4/Inputs!B43,0) -> 48.2
A6: Annual Workforce Hours Basis | B6: =Inputs!B44 -> 3744
A7: Workforce Total Should-Cost of Ownership per Security Professional | B7: =B5*B6 -> 180460.8
A8: Government/Buyer Total Should-Cost of Ownership per Coverage Hour | B8: =Appraisal_Full_Scope_Report!$F$8 -> 129.97639
A9: Vendor Workforce Should-Cost Rate | B9: =Appraisal_Full_Scope_Report!$H$8 -> 90.983473
A10: Capital Recovery Saved per Hour | B10: =Appraisal_Full_Scope_Report!$J$8 -> 38.992917
A11: Annual Coverage Hours Required | B11: =Appraisal_Full_Scope_Report!F15 -> 17472
A12: Annual Government Should Cost for Required Coverage | B12: =Appraisal_Full_Scope_Report!$F$19 -> 2270947.5
A13: Annual Vendor Should-Cost for Required Coverage | B13: =Appraisal_Full_Scope_Report!$H$19 -> 1589663.2
A14: Workforce-to-Post Metrics
A15: Annual Capital Recovery Saved | B15: =Appraisal_Full_Scope_Report!$H$20 -> 681284.25
A16: Direct Labor to Government TCO Multiplier | B16: =IFERROR(B8/B4,0) -> 3.8522937
A17: Direct Labor to Vendor Rate Multiplier | B17: =IFERROR(B9/B4,0) -> 2.6966056
A18: Government Full Burden Labor Share | B18: =Inputs!B43 -> 0.7
A19: Government Workforce Hours Basis | B19: =Inputs!B44 -> 3744
A20: Model Note | B20: This tab uses Total Direct Labor from Direct_Labor!C8, then forces burden to a 70/30 labor-share model.
A22: Automatic Burden Allocation (forced to 30% of total cost)
A23: Line Item | B23: Raw Weight | C23: Normalized Share | D23: Hourly Burden | E23: Annual Burden
A24: FICA / Medicare | B24: =Inputs!B13 -> 0.0765 | C24: =IFERROR(B24/$B$36,0) -> 0.24117276 | D24: =$D$37*C24 -> 3.4873581 | E24: =D24*$B$11 -> 60931.121
A25: FUTA | B25: =Inputs!B14 -> 0.006 | C25: =IFERROR(B25/$B$36,0) -> 0.018915511 | D25: =$D$37*C25 -> 0.27351828 | E25: =D25*$B$11 -> 4778.9115
A26: SUTA | B26: =Inputs!B15 -> 0.02 | C26: =IFERROR(B26/$B$36,0) -> 0.063051702 | D26: =$D$37*C26 -> 0.91172762 | E26: =D26*$B$11 -> 15929.705
A27: Workers Compensation | B27: =Inputs!B16 -> 0.016 | C27: =IFERROR(B27/$B$36,0) -> 0.050441362 | D27: =$D$37*C27 -> 0.72938209 | E27: =D27*$B$11 -> 12743.764
A28: Health & Welfare proxy | B28: =IFERROR(Inputs!B17/$B$4,0) -> 0 | C28: =IFERROR(B28/$B$36,0) -> 0 | D28: =$D$37*C28 -> 0 | E28: =D28*$B$11 -> 0
A29: Vacation | B29: =Inputs!B18 -> 0.02 | C29: =IFERROR(B29/$B$36,0) -> 0.063051702 | D29: =$D$37*C29 -> 0.91172762 | E29: =D29*$B$11 -> 15929.705
A30: Paid Holidays | B30: =Inputs!B19 -> 0.04 | C30: =IFERROR(B30/$B$36,0) -> 0.1261034 | D30: =$D$37*C30 -> 1.8234552 | E30: =D30*$B$11 -> 31859.41
A31: Sick Leave | B31: =Inputs!B20 -> 0.027 | C31: =IFERROR(B31/$B$36,0) -> 0.085119798 | D31: =$D$37*C31 -> 1.2308323 | E31: =D31*$B$11 -> 21505.102
A32: Recruiting / Hiring | B32: =Inputs!B23 -> 0 | C32: =IFERROR(B32/$B$36,0) -> 0 | D32: =$D$37*C32 -> 0 | E32: =D32*$B$11 -> 0
A33: Training / Certification | B33: =Inputs!B24 -> 0.015 | C33: =IFERROR(B33/$B$36,0) -> 0.047288777 | D33: =$D$37*C33 -> 0.68379571 | E33: =D33*$B$11 -> 11947.279
A34: Administrative / HR / Payroll | B34: =Inputs!B35 -> 0 | C34: =IFERROR(B34/$B$36,0) -> 0 | D34: =$D$37*C34 -> 0 | E34: =D34*$B$11 -> 0
A35: Insurance / Misc. | B35: =Inputs!B31+Inputs!B32 -> 0.0967 | C35: =IFERROR(B35/$B$36,0) -> 0.30485498 | D35: =$D$37*C35 -> 4.408203 | E35: =D35*$B$11 -> 77020.123
A36: Total raw weight | B36: =SUM(B24:B35) -> 0.3172
A37: Total burden dollars to allocate | D37: =B5-B4 -> 14.46 | E37: =D37*$B$11 -> 252645.12
A38: Allocated burden check | D38: =SUM(D24:D35) -> 14.46 | E38: =SUM(E24:E35) -> 252645.12
A39: Difference (should be 0) | D39: =D37-D38 -> 0 | E39: =E37-E38 -> 0
A40: Important | B40: If labor is 70% of total cost, the burden add-on equals 30% of total cost, which is 42.857% of direct labor.

Sheet Overhead_GA
A1: GASQ Overhead, G&A, and Profit
A2: GASQ-branded operating model worksheet
A3: Line Item | B3: Input / Formula | C3: Hourly Amount | D3: Annual Amount
A4: Administrative / HR / Payroll | B4: =Direct_Labor!$C$11*Inputs!B35 -> 0 | C4: =B4 -> 0 | D4: =C4*_Calc_Backend!$X$37 -> 0
A5: Accounting / Legal | B5: =Direct_Labor!$C$11*Inputs!B36 -> 0 | C5: =B5 -> 0 | D5: =C5*_Calc_Backend!$X$37 -> 0
A6: Corporate Overhead | B6: =Direct_Labor!$C$11*Inputs!B37 -> 4.19298 | C6: =B6 -> 4.19298 | D6: =C6*_Calc_Backend!$X$37 -> 73259.747
A7: G&A | B7: =Direct_Labor!$C$11*Inputs!B38 -> 3.354384 | C7: =B7 -> 3.354384 | D7: =C7*_Calc_Backend!$X$37 -> 58607.797
A8: Profit / Fee | B8: =IFERROR((Appraisal_Full_Scope_Report!H19*Inputs!B39)/Appraisal_Full_Scope_Report!F15,0) -> 19.106529 | C8: =B8 -> 19.106529 | D8: =C8*_Calc_Backend!$X$37 -> 333829.28
A9: Total Overhead / G&A / Profit | C9: =SUM(C4:C8) -> 26.653893 | D9: =SUM(D4:D8) -> 465696.82

Sheet Buyer_Vendor_Comparison
A1: GASQ Buyer vs Vendor Price Comparison
A2: GASQ-branded operating model worksheet
A3: Core Pricing Comparison
A4: Metric | B4: Buyer / Government | C4: Vendor TCO | D4: Vendor LATP/BAFO Rate | E4: Vendor LPTA
A5: Annual Coverage Hours | B5: =Appraisal_Full_Scope_Report!$F$15 -> 17472 | C5: =Appraisal_Full_Scope_Report!$F$15 -> 17472 | D5: =Appraisal_Full_Scope_Report!$F$15 -> 17472 | E5: =Appraisal_Full_Scope_Report!$F$15 -> 17472
A6: FTEs Required | B6: =_Calc_Backend!$X$38 -> 12 | C6: =_Calc_Backend!$X$38 -> 12 | D6: =_Calc_Backend!$X$38 -> 12 | E6: =_Calc_Backend!$X$38 -> 12
A7: Rate per Productive Coverage Hour | B7: =Appraisal_Full_Scope_Report!$F$8 -> 129.97639 | C7: =Appraisal_Full_Scope_Report!$H$8 -> 90.983473 | D7: =Vendor_Pricing!$B$7 -> 77.335952 | E7: =Vendor_Pricing!B6 -> 63.688431
A8: Annual Total Cost | B8: =Appraisal_Full_Scope_Report!$F$19 -> 2270947.5 | C8: =Appraisal_Full_Scope_Report!$H$19 -> 1589663.2 | D8: =D5*D7 -> 1351213.8 | E8: =E5*E7 -> 1112764.3
A9: Hourly Savings vs Buyer | B9: - | C9: =B7-C7 -> 38.992917 | D9: =B7-D7 -> 52.640438 | E9: =B7-E7 -> 66.287959
A10: Annual Capital Recovery Saved | B10: - | C10: =B8-C8 -> 681284.25 | D10: =B8-D8 -> 919733.73 | E10: =B8-E8 -> 1158183.2
A11: Savings % vs Buyer | B11: - | C11: =IFERROR((B8-C8)/B8,0) -> 0.3 | D11: =IFERROR((B8-D8)/B8,0) -> 0.405 | E11: =IFERROR((B8-E8)/B8,0) -> 0.51
A13: Capital Recovery Highlight
A14: Comparison Point | B14: Formula Output
A15: Buyer Government TCO Rate | B15: =Appraisal_Full_Scope_Report!$F$8 -> 129.97639
A16: Vendor TCO Rate | B16: =Appraisal_Full_Scope_Report!$H$8 -> 90.983473
A17: Capital Recovery Saved per Hour | B17: =Appraisal_Full_Scope_Report!$J$8 -> 38.992917
A18: Annual Capital Recovery Saved | B18: =Appraisal_Full_Scope_Report!$H$20 -> 681284.25
A19: Capital Recovery Savings % | B19: =IFERROR(B18/B8,0) -> 0.3
A21: Buyer-to-Vendor Cost Comparison
A22: Buyer annual in-house/government-equivalent cost | B22: =Appraisal_Full_Scope_Report!$F$19 -> 2270947.5
A23: Vendor annual cost at TCO rate | B23: =Appraisal_Full_Scope_Report!$H$19 -> 1589663.2
A24: Vendor annual cost at target rate | B24: =Vendor_Pricing!$B$7*_Calc_Backend!$X$33 -> 298912.74
A25: Vendor annual cost at floor rate | B25: =Vendor_Pricing!$B$6*_Calc_Backend!$X$33 -> 246163.43
A26: Best annual capital recovery using vendor floor | B26: =B22-B25 -> 2024784.1
A29: This worksheet provides a side-by-side price comparison between the buyer's government-style TCO and vendor pricing, including capital recovery saved.

Sheet Workforce_to_Post
A1: GASQ Workforce-to-Post™ Calculator
A2: Calculates productive coverage, workforce basis, unavailable hours, and relief factor from the active post roster.
A4: Weekly Coverage Hours | B4: =IFERROR(_Calc_Backend!$X$33/_Calc_Backend!$X$29,0) -> 416.5 | D4: Interpretation
A5: Annual Coverage Hours | B5: =_Calc_Backend!$X$33 -> 3865.12 | D5: Coverage hours entered by roster or scope.
A6: Standard Paid Hours per FTE | B6: =2080 -> 2080 | D6: Coverage hours multiplied by 52 weeks.
A7: Relief Factor (Workforce Basis ÷ Productive Basis) | B7: =Inputs!B44/B6 -> 1.8 | D7: Paid hours per FTE basis used by vendor model.
A8: Productive FTEs Required | B8: =IFERROR(B5/B6,0) -> 1.8582308 | D8: Shows productivity loss between coverage and workforce basis.
A9: Paid Workforce FTEs Required | B9: =B8*B7 -> 3.3448154 | D9: Bare-minimum productive staffing requirement.
A10: Government Workforce Hours Basis | B10: =Inputs!B44 -> 3744 | D10: Paid headcount needed to support relief.
A11: Unavailable Hours per FTE | B11: =B10-B6 -> 1664 | D11: Government-style workforce basis used in model.
A12: Unavailable Hours Workforce Cost Basis | B12: =B9*B11 -> 5565.7728 | D12: Hours paid but not worked per FTE.
A13: Blended Pay Rate | B13: =IF(_Calc_Backend!U5>0,_Calc_Backend!U14,Direct_Labor!C11) -> 33.74 | D13: Total unavailable paid hours across the workforce.
A14: Unavailable Hours Workforce Cost | B14: =B12*B13 -> 187789.17 | D14: Active weighted pay rate from roster.
A15: Training Cost Annual | B15: =Training_Module!J9 -> 38720 | D15: Dollar cost of unavailable paid hours.
A16: Equipment / Uniform Annual | B16: =Equipment_Uniform_Module!E7 -> 1447.5
A17: Workforce Maintenance Annual | B17: =Workforce_Maintenance_Module!E7 -> 15029.44
A18: Total Hidden Workforce Cost | B18: =SUM(B14:B17) -> 242986.11

Sheet Contract_Summary_v2
B1: GASQ Workforce-to-Post™ Capital Recovery Contract Summary
B2: Executive contract summary v2 with direct source links for input-driven fields | J2: =IF(IFERROR(_Calc_Backend!$U$5,0)>0,_Calc_Backend!$U$5,_Calc_Backend!$X$36) -> 336
B3: CONFIDENTIAL | J3: =IF(IFERROR(_Calc_Backend!$U$5,0)>0,_Calc_Backend!$U$15,Vendor_Pricing!B7) -> 64.785
J4: =IF(IFERROR(_Calc_Backend!$U$5,0)>0,_Calc_Backend!$U$14,Direct_Labor!C11) -> 33.74
J5: =Direct_Labor!C5 -> 0
J6: =Direct_Labor!C7 -> 4.22
B7: Contract Economics | J7: =Direct_Labor!C23 -> 1.677192
B8: Weekly Hours | F8: =IF(IFERROR(_Calc_Backend!$U$5,0)>0,_Calc_Backend!$U$5,_Calc_Backend!$X$36) -> 336 | J8: =IF(IFERROR(_Calc_Backend!$U$5,0)>0,_Calc_Backend!$U$7,J2*J3) -> 21767.76
B9: Weekly Billings (excluding holiday billings) | F9: =IF(IFERROR(_Calc_Backend!$U$5,0)>0,_Calc_Backend!$U$7,J8*J3) -> 21767.76 | J9: =J8*52 -> 1131923.5
B10: Should-Cost Straight Time Pay Rate | F10: =IF(IFERROR(_Calc_Backend!$U$5,0)>0,_Calc_Backend!$U$17+_Calc_Backend!$U$18,Direct_Labor!D23+Operations!D14) -> 589505.28 | J10: =IF(IFERROR(_Calc_Backend!$U$5,0)>0,_Calc_Backend!$U$17+_Calc_Backend!$U$18,Direct_Labor!D23+Operations!D14) -> 589505.28
B11: Blended Straight Time Bill Rate | F11: =Vehicle!C29 -> 61233.164 | J11: =Vehicle!C29 -> 61233.164
B12: Overtime Bill Rate | F12: =Vehicle!C29 -> 61233.164 | J12: =Vehicle!C29 -> 61233.164
B13: Holiday Bill Rate | F13: =J9+J11 -> 1193156.7 | J13: =J9+J11 -> 1193156.7
B14: Effective Pay Rate | F14: =J10+J12 -> 650738.44 | J14: =J10+J12 -> 650738.44
B15: Effective Bill Rate | F15: =J13-J14 -> 542418.24 | J15: =J13-J14 -> 542418.24
B16: Effective Direct Labor Ratio | F16: =IFERROR(J15/J13,0) -> 0.45460772 | J16: =IFERROR(J15/J13,0) -> 0.45460772
B17: Effective Markup | F17: =IFERROR(J15/_Calc_Backend!$X$33,0) -> 140.33671 | J17: =IFERROR(J15/_Calc_Backend!$X$33,0) -> 140.33671
J18: =IFERROR(J7/J3,0) -> 0.025888585
B19: Revenue & Cost Summary | J19: =IFERROR(J3/J7,0) -> 38.627062
B20: Total Annual Revenue (from hourly billings) * | F20: =J3*1.5 -> 97.1775 | J20: =J3*1.5 -> 97.1775
B21: Vehicle and Other Pass Through Billings | F21: =J11 -> 61233.164 | J21: =J3*1.5 -> 97.1775
B22: Total Annual Contract Revenue * | F22: =Appraisal_Full_Scope_Report!F32 -> 0 | J22: =IFERROR(J13/_Calc_Backend!$X$33,0) -> 308.69848
J23: =Government_TCO!B8 -> 129.97639
B24: Direct Expense | F24: =Vendor_Pricing!B5 -> 90.983473 | J24: =Vendor_Pricing!B5 -> 90.983473
B25: Vehicle and Other Pass Through Costs | F25: =Vendor_Pricing!B6 -> 63.688431 | J25: =Vendor_Pricing!B6 -> 63.688431
B26: Total Annual Costs * | F26: =Vendor_Pricing!B7 -> 77.335952 | J26: =Vendor_Pricing!B7 -> 77.335952
J27: =Vendor_Pricing!B8 -> 90.983473
B28: Contributory Profit | F28: =Vendor_Pricing!B9 -> 38.992917 | J28: =Vendor_Pricing!B9 -> 38.992917
B29: Profit as a % of Revenue | F29: =Inputs!B39 -> 0.21 | J29: =Inputs!B39 -> 0.21
B30: Contributory Profit Per Hour | F30: =Buyer_Vendor_Comparison!C11 -> 0.3 | J30: =Buyer_Vendor_Comparison!C11 -> 0.3
B31: Working Capital Requirement | F31: =IFERROR(J14/12,0) -> 54228.204 | J31: =Inputs!B42 -> 1500
B32: Payback & Recovery Period (months) | F32: =IFERROR(H19/(F19/12),0) -> 0 | J32: =IFERROR(H19/(F19/12),0) -> 0
J33: =IFERROR((J26-J25)/(J27-J25),0) -> 0.5
B34: Total Monthly Hours of Coverage | F34: =Appraisal_Full_Scope_Report!F12 -> 1456
B35: Total Annual Hours of Coverage | F35: =Appraisal_Full_Scope_Report!F15 -> 17472
B36: Vendor True Cost of Ownership Rate | F36: =IFERROR(J29/J35,0) -> 0 | J36: =IFERROR(J29/J35,0) -> 0
B37: Vendor Absorbed Rate | F37: =J25 -> 63.688431
B38: Vendor Target Rate | F38: =J26 -> 77.335952
B39: Vendor True Cost of Ownership Rate | F39: =J27 -> 90.983473
B40: Capital Recovery Saved per Hour | F40: =J28 -> 38.992917
B41: Annual Capital Recovery Saved | F41: =F40*F35 -> 681284.25 | J41: =F40*F35 -> 681284.25
B42: Savings % vs Buyer | F42: =J30 -> 0.3
B44: Guardrails & Rating
B45: Minimum Weekly Hours for Floor Eligibility | F45: =Inputs!B42 -> 1500
B46: Current Weekly Hours Eligibility Status | F46: =J32 -> 0
B47: Target Position within Floor-to-Ceiling Range | F47: =J33 -> 0.5
B48: GASQ Cost Rating Grade | F48: =J34 -> 0
B49: Total Weeks of Coverage | F49: =Appraisal_Full_Scope_Report!F14 -> 336
B50: Total Months of Coverage
B51: Total Workforce Required for Coverage | F51: =Appraisal_Full_Scope_Report!F16 -> 12
B53: * Total contract amounts shown assume the current annual coverage requirement from the GASQ model. Modify Scope_of_Work inputs to update automatically.

Sheet _Calc_Backend
A1: GASQ Posts / Positions / Locations | T1: Controls
A2: Use AUTO mode to activate model-driven billing rates or MANUAL mode to type your own rate. AUTO logic: Auto Bill Rate = (Pay Wage ÷ labor share) × (workforce hours basis ÷ productive coverage hours); Final Bill Rate = Auto Bill Rate × labor share. This section is built as an Excel table so rows can be inserted or removed without breaking formulas. See the integrated Scope of Work block at the lower right of this tab. | T2: Std Hrs / FTE | U2: 28
T3: OT Premium (x) | U3: 1.5
B4: Edit highlighted roster cells only | T4: Summary | V4: AUTO uses Inputs!B4 | W4: MANUAL uses col V
T5: Weekly Hours | U5: =SUBTOTAL(109,_Calc_Backend!$E$7:$E$21) -> 336 | V5: Wage Input | W5: Control
A6: Line Item | B6: Post | C6: Position | D6: Location | E6: Weekly Hours | F6: Pay Wage ($/hr) | G6: Rate Mode | H6: Absorbed Bill Rate ($/hr) | I6: Should Cost Internal Bill Rate ($/hr) | J6: Vendor TCO Bill Rate ($/hr) | K6: Unbilled OT (% Hrs) | L6: Billed OT (% Hrs) | M6: Training Hrs | N6: Training Wage ($/hr) | O6: Weekly Pay Cost | P6: Weekly Billing | Q6: Training Cost | R6: Weekly Margin | S6: Headcount | T6: Weekly Pay Cost | U6: =SUBTOTAL(109,_Calc_Backend!$O$7:$O$21) -> 11336.64 | V6: Manual Pay Wage ($/hr) | W6: Wage Mode
A7: 1 | B7: =IF(Post_Positions!A2="","","Post 1") -> Post 1 | C7: =Post_Positions!A2 -> Unarmed S/O | E7: =IF(Post_Positions!A2="","",Post_Positions!Q2) -> 168 | F7: =IF($B7="","",Post_Positions!$C$12) -> 33.74 | G7: AUTO | I7: =IF(OR(F7="",F7=0),"",((F7*(1+Inputs!$B$45+Inputs!$B$46))/Inputs!$B$43)*(Inputs!$B$44/Inputs!$B$6)) -> 123.94286 | J7: =IF(E7="","",IF(G7="AUTO",I7*Inputs!$B$43,H7)) -> 86.76 | K7: 0 | L7: 0 | M7: 0 | N7: 0 | O7: =IF(OR(E7="",F7=""),"",E7*F7*(1+$U$3*(IF(K7="",0,K7)+IF(L7="",0,L7)))) -> 5668.32 | P7: =IF(OR(E7="",J7=""),"",E7*J7*(1+IF(L7="",0,L7))) -> 14575.68 | Q7: =IF(OR(M7="",N7=""),"",M7*N7) -> 0 | R7: =IF(OR(O7="",P7=""),"",P7-O7-IF(Q7="",0,Q7)) -> 8907.36 | S7: =IF(E7="","",ROUNDUP(E7/28,0)) -> 6 | T7: Weekly Billing | U7: =SUBTOTAL(109,_Calc_Backend!$P$7:$P$21) -> 21767.76 | V7: =IF(Post_Positions!A2="","",Post_Positions!L2) -> 27.48 | W7: MANUAL
A8: 2 | B8: =IF(Post_Positions!A3="","","Post 2") -> Post 2 | C8: =Post_Positions!A3 -> Supervisor | E8: =IF(Post_Positions!A3="","",Post_Positions!Q3) -> 168 | F8: =IF($B8="","",Post_Positions!$C$12) -> 33.74 | G8: AUTO | I8: =IF(OR(F8="",F8=0),"",((F8*(1+Inputs!$B$45+Inputs!$B$46))/Inputs!$B$43)*(Inputs!$B$44/Inputs!$B$6)) -> 123.94286 | J8: 42.81 | K8: 0 | L8: 0 | M8: 0 | N8: 0 | O8: =IF(OR(E8="",F8=""),"",E8*F8*(1+$U$3*(IF(K8="",0,K8)+IF(L8="",0,L8)))) -> 5668.32 | P8: =IF(OR(E8="",J8=""),"",E8*J8*(1+IF(L8="",0,L8))) -> 7192.08 | Q8: =IF(OR(M8="",N8=""),"",M8*N8) -> 0 | R8: =IF(OR(O8="",P8=""),"",P8-O8-IF(Q8="",0,Q8)) -> 1523.76 | S8: =IF(E8="","",ROUNDUP(E8/28,0)) -> 6 | T8: Training Cost | U8: =SUBTOTAL(109,_Calc_Backend!$Q$7:$Q$21) -> 0 | V8: =IF(Post_Positions!A3="","",Post_Positions!L3) -> 40 | W8: MANUAL
A9: 3 | B9: =IF(Post_Positions!A4="","","Post 3") -> Post 3 | C9: =Post_Positions!A4 -> Unarmed S/O | E9: =IF(Post_Positions!A4="","",Post_Positions!Q4) -> 0 | F9: =IF($B9="","",Post_Positions!$C$12) -> 33.74 | G9: AUTO | I9: =IF(OR(F9="",F9=0),"",((F9*(1+Inputs!$B$45+Inputs!$B$46))/Inputs!$B$43)*(Inputs!$B$44/Inputs!$B$6)) -> 123.94286 | J9: =IF(E9="","",IF(G9="AUTO",I9*Inputs!$B$43,H9)) -> 86.76 | K9: 0 | L9: 0 | M9: 0 | N9: 0 | O9: =IF(OR(E9="",F9=""),"",E9*F9*(1+$U$3*(IF(K9="",0,K9)+IF(L9="",0,L9)))) -> 0 | P9: =IF(OR(E9="",J9=""),"",E9*J9*(1+IF(L9="",0,L9))) -> 0 | Q9: =IF(OR(M9="",N9=""),"",M9*N9) -> 0 | R9: =IF(OR(O9="",P9=""),"",P9-O9-IF(Q9="",0,Q9)) -> 0 | S9: =IF(E9="","",ROUNDUP(E9/28,0)) -> 0 | T9: Weekly Margin | U9: =SUBTOTAL(109,_Calc_Backend!$R$7:$R$21) -> 10431.12 | V9: =IF(Post_Positions!A4="","",Post_Positions!L4) -> 0 | W9: MANUAL
A10: 4 | B10: =IF(Post_Positions!A5="","","Post 4") -> Post 4 | C10: =Post_Positions!A5 -> Unarmed S/O | E10: =IF(Post_Positions!A5="","",Post_Positions!Q5) -> 0 | F10: =IF($B10="","",Post_Positions!$C$12) -> 33.74 | G10: AUTO | I10: =IF(OR(F10="",F10=0),"",((F10*(1+Inputs!$B$45+Inputs!$B$46))/Inputs!$B$43)*(Inputs!$B$44/Inputs!$B$6)) -> 123.94286 | J10: =IF(E10="","",IF(G10="AUTO",I10*Inputs!$B$43,H10)) -> 86.76 | K10: 0 | L10: 0 | M10: 0 | N10: 0 | O10: =IF(OR(E10="",F10=""),"",E10*F10*(1+$U$3*(IF(K10="",0,K10)+IF(L10="",0,L10)))) -> 0 | P10: =IF(OR(E10="",J10=""),"",E10*J10*(1+IF(L10="",0,L10))) -> 0 | Q10: =IF(OR(M10="",N10=""),"",M10*N10) -> 0 | R10: =IF(OR(O10="",P10=""),"",P10-O10-IF(Q10="",0,Q10)) -> 0 | S10: =IF(E10="","",ROUNDUP(E10/28,0)) -> 0 | T10: Headcount | U10: =SUBTOTAL(109,_Calc_Backend!$S$7:$S$21) -> 12 | V10: =IF(Post_Positions!A5="","",Post_Positions!L5) -> 0 | W10: MANUAL
A11: 5 | B11: =IF(Post_Positions!A6="","","Post 5") -> Post 5 | C11: =Post_Positions!A6 -> Rovering Patrol Officer | E11: =IF(Post_Positions!A6="","",Post_Positions!Q6) -> 0 | F11: =IF($B11="","",Post_Positions!$C$12) -> 33.74 | G11: AUTO | I11: =IF(OR(F11="",F11=0),"",((F11*(1+Inputs!$B$45+Inputs!$B$46))/Inputs!$B$43)*(Inputs!$B$44/Inputs!$B$6)) -> 123.94286 | J11: =IF(E11="","",IF(G11="AUTO",I11*Inputs!$B$43,H11)) -> 86.76 | K11: 0 | L11: 0 | M11: 0 | N11: 0 | O11: =IF(OR(E11="",F11=""),"",E11*F11*(1+$U$3*(IF(K11="",0,K11)+IF(L11="",0,L11)))) -> 0 | P11: =IF(OR(E11="",J11=""),"",E11*J11*(1+IF(L11="",0,L11))) -> 0 | Q11: =IF(OR(M11="",N11=""),"",M11*N11) -> 0 | R11: =IF(OR(O11="",P11=""),"",P11-O11-IF(Q11="",0,Q11)) -> 0 | S11: =IF(E11="","",ROUNDUP(E11/28,0)) -> 0 | T11: AUTO rate = ((Pay Wage × (1 + Inputs!B44 locality pay + Inputs!B45 labor market adjustment)) ÷ Inputs!B42 labor share) × (Inputs!B43 workforce hours basis ÷ Inputs!B6 productive coverage hours). Final Bill Rate switches automatically based on Rate Mode. | V11: =IF(Post_Positions!A6="","",Post_Positions!L6) -> 0 | W11: MANUAL
A12: 6 | B12: =IF(Post_Positions!A7="","","Post 6") -> Post 6 | C12: =Post_Positions!A7 -> Unarmed S/O | E12: =IF(Post_Positions!A7="","",Post_Positions!Q7) -> 0 | F12: =IF($B12="","",Post_Positions!$C$12) -> 33.74 | G12: AUTO | I12: =IF(OR(F12="",F12=0),"",((F12*(1+Inputs!$B$45+Inputs!$B$46))/Inputs!$B$43)*(Inputs!$B$44/Inputs!$B$6)) -> 123.94286 | J12: =IF(E12="","",IF(G12="AUTO",I12*Inputs!$B$43,H12)) -> 86.76 | K12: 0 | L12: 0 | M12: 0 | N12: 0 | O12: =IF(OR(E12="",F12=""),"",E12*F12*(1+$U$3*(IF(K12="",0,K12)+IF(L12="",0,L12)))) -> 0 | P12: =IF(OR(E12="",J12=""),"",E12*J12*(1+IF(L12="",0,L12))) -> 0 | Q12: =IF(OR(M12="",N12=""),"",M12*N12) -> 0 | R12: =IF(OR(O12="",P12=""),"",P12-O12-IF(Q12="",0,Q12)) -> 0 | S12: =IF(E12="","",ROUNDUP(E12/28,0)) -> 0 | V12: =IF(Post_Positions!A7="","",Post_Positions!L7) -> 0 | W12: MANUAL
A13: 7 | B13: =IF(Post_Positions!A8="","","Post 7") -> Post 7 | C13: =Post_Positions!A8 -> Unarmed S/O | E13: =IF(Post_Positions!A8="","",Post_Positions!Q8) -> 0 | F13: =IF($B13="","",Post_Positions!$C$12) -> 33.74 | G13: AUTO | I13: =IF(OR(F13="",F13=0),"",((F13*(1+Inputs!$B$45+Inputs!$B$46))/Inputs!$B$43)*(Inputs!$B$44/Inputs!$B$6)) -> 123.94286 | J13: =IF(E13="","",IF(G13="AUTO",I13*Inputs!$B$43,H13)) -> 86.76 | K13: 0 | L13: 0 | M13: 0 | N13: 0 | O13: =IF(OR(E13="",F13=""),"",E13*F13*(1+$U$3*(IF(K13="",0,K13)+IF(L13="",0,L13)))) -> 0 | P13: =IF(OR(E13="",J13=""),"",E13*J13*(1+IF(L13="",0,L13))) -> 0 | Q13: =IF(OR(M13="",N13=""),"",M13*N13) -> 0 | R13: =IF(OR(O13="",P13=""),"",P13-O13-IF(Q13="",0,Q13)) -> 0 | S13: =IF(E13="","",ROUNDUP(E13/28,0)) -> 0 | T13: Annual Hours | U13: =IF(U5="","",U5*52) -> 17472 | V13: =IF(Post_Positions!A8="","",Post_Positions!L8) -> 0 | W13: MANUAL
A14: 8 | B14: =IF(Post_Positions!A9="","","Post 8") -> Post 8 | C14: =Post_Positions!A9 -> Unarmed S/O | E14: =IF(Post_Positions!A9="","",Post_Positions!Q9) -> 0 | F14: =IF($B14="","",Post_Positions!$C$12) -> 33.74 | G14: AUTO | I14: =IF(OR(F14="",F14=0),"",((F14*(1+Inputs!$B$45+Inputs!$B$46))/Inputs!$B$43)*(Inputs!$B$44/Inputs!$B$6)) -> 123.94286 | J14: =IF(E14="","",IF(G14="AUTO",I14*Inputs!$B$43,H14)) -> 86.76 | K14: 0 | L14: 0 | M14: 0 | N14: 0 | O14: =IF(OR(E14="",F14=""),"",E14*F14*(1+$U$3*(IF(K14="",0,K14)+IF(L14="",0,L14)))) -> 0 | P14: =IF(OR(E14="",J14=""),"",E14*J14*(1+IF(L14="",0,L14))) -> 0 | Q14: =IF(OR(M14="",N14=""),"",M14*N14) -> 0 | R14: =IF(OR(O14="",P14=""),"",P14-O14-IF(Q14="",0,Q14)) -> 0 | S14: =IF(E14="","",ROUNDUP(E14/28,0)) -> 0 | T14: Blended Direct Wage | U14: =IFERROR(Post_Positions!$C$12,"") -> 33.74 | V14: =IF(Post_Positions!A9="","",Post_Positions!L9) -> 0 | W14: MANUAL
A15: 9 | B15: =IF(Post_Positions!A10="","","Post 9") -> Post 9 | C15: =Post_Positions!A10 -> Unarmed S/O | E15: =IF(Post_Positions!A10="","",Post_Positions!Q10) -> 0 | F15: =IF($B15="","",Post_Positions!$C$12) -> 33.74 | G15: AUTO | I15: =IF(OR(F15="",F15=0),"",((F15*(1+Inputs!$B$45+Inputs!$B$46))/Inputs!$B$43)*(Inputs!$B$44/Inputs!$B$6)) -> 123.94286 | J15: =IF(E15="","",IF(G15="AUTO",I15*Inputs!$B$43,H15)) -> 86.76 | K15: 0 | L15: 0 | M15: 0 | N15: 0 | O15: =IF(OR(E15="",F15=""),"",E15*F15*(1+$U$3*(IF(K15="",0,K15)+IF(L15="",0,L15)))) -> 0 | P15: =IF(OR(E15="",J15=""),"",E15*J15*(1+IF(L15="",0,L15))) -> 0 | Q15: =IF(OR(M15="",N15=""),"",M15*N15) -> 0 | R15: =IF(OR(O15="",P15=""),"",P15-O15-IF(Q15="",0,Q15)) -> 0 | S15: =IF(E15="","",ROUNDUP(E15/28,0)) -> 0 | T15: Blended Bill Rate | U15: =IFERROR(U7/U5,"") -> 64.785 | V15: =IF(Post_Positions!A10="","",Post_Positions!L10) -> 0 | W15: MANUAL
A16: 10 | B16: =IF(Post_Positions!A11="","","Post 10") -> Post 10 | C16: =Post_Positions!A11 -> Unarmed S/O | E16: =IF(Post_Positions!A11="","",Post_Positions!Q11) -> 0 | F16: =IF($B16="","",Post_Positions!$C$12) -> 33.74 | G16: AUTO | I16: =IF(OR(F16="",F16=0),"",((F16*(1+Inputs!$B$45+Inputs!$B$46))/Inputs!$B$43)*(Inputs!$B$44/Inputs!$B$6)) -> 123.94286 | J16: =IF(E16="","",IF(G16="AUTO",I16*Inputs!$B$43,H16)) -> 86.76 | K16: 0 | L16: 0 | M16: 0 | N16: 0 | O16: =IF(OR(E16="",F16=""),"",E16*F16*(1+$U$3*(IF(K16="",0,K16)+IF(L16="",0,L16)))) -> 0 | P16: =IF(OR(E16="",J16=""),"",E16*J16*(1+IF(L16="",0,L16))) -> 0 | Q16: =IF(OR(M16="",N16=""),"",M16*N16) -> 0 | R16: =IF(OR(O16="",P16=""),"",P16-O16-IF(Q16="",0,Q16)) -> 0 | S16: =IF(E16="","",ROUNDUP(E16/28,0)) -> 0 | T16: Annual Billings | U16: =IF(U7="","",U7*52) -> 1131923.5 | V16: =IF(Post_Positions!A11="","",Post_Positions!L11) -> 0 | W16: MANUAL
A17: 11 | F17: =IF($B17="","",Post_Positions!$C$12) | G17: AUTO | I17: =IF(OR(F17="",F17=0),"",((F17*(1+Inputs!$B$45+Inputs!$B$46))/Inputs!$B$43)*(Inputs!$B$44/Inputs!$B$6)) | J17: =IF(E17="","",IF(G17="AUTO",I17*Inputs!$B$43,H17)) | O17: =IF(OR(E17="",F17=""),"",E17*F17*(1+$U$3*(IF(K17="",0,K17)+IF(L17="",0,L17)))) | P17: =IF(OR(E17="",J17=""),"",E17*J17*(1+IF(L17="",0,L17))) | Q17: =IF(OR(M17="",N17=""),"",M17*N17) | R17: =IF(OR(O17="",P17=""),"",P17-O17-IF(Q17="",0,Q17)) | S17: =IF(E17="","",ROUNDUP(E17/28,0)) | T17: Annual Pay Cost | U17: =IF(U6="","",U6*52) -> 589505.28
A18: 12 | F18: =IF($B18="","",Post_Positions!$C$12) | G18: AUTO | I18: =IF(OR(F18="",F18=0),"",((F18*(1+Inputs!$B$45+Inputs!$B$46))/Inputs!$B$43)*(Inputs!$B$44/Inputs!$B$6)) | J18: =IF(E18="","",IF(G18="AUTO",I18*Inputs!$B$43,H18)) | O18: =IF(OR(E18="",F18=""),"",E18*F18*(1+$U$3*(IF(K18="",0,K18)+IF(L18="",0,L18)))) | P18: =IF(OR(E18="",J18=""),"",E18*J18*(1+IF(L18="",0,L18))) | Q18: =IF(OR(M18="",N18=""),"",M18*N18) | R18: =IF(OR(O18="",P18=""),"",P18-O18-IF(Q18="",0,Q18)) | S18: =IF(E18="","",ROUNDUP(E18/28,0)) | T18: Annual Training Cost | U18: =IF(U8="","",U8*52) -> 0
A19: 13 | F19: =IF($B19="","",Post_Positions!$C$12) | G19: AUTO | I19: =IF(OR(F19="",F19=0),"",((F19*(1+Inputs!$B$45+Inputs!$B$46))/Inputs!$B$43)*(Inputs!$B$44/Inputs!$B$6)) | J19: =IF(E19="","",IF(G19="AUTO",I19*Inputs!$B$43,H19)) | O19: =IF(OR(E19="",F19=""),"",E19*F19*(1+$U$3*(IF(K19="",0,K19)+IF(L19="",0,L19)))) | P19: =IF(OR(E19="",J19=""),"",E19*J19*(1+IF(L19="",0,L19))) | Q19: =IF(OR(M19="",N19=""),"",M19*N19) | R19: =IF(OR(O19="",P19=""),"",P19-O19-IF(Q19="",0,Q19)) | S19: =IF(E19="","",ROUNDUP(E19/28,0)) | T19: Annual Margin | U19: =IF(U9="","",U9*52) -> 542418.24
A20: 14 | F20: =IF($B20="","",Post_Positions!$C$12) | G20: AUTO | I20: =IF(OR(F20="",F20=0),"",((F20*(1+Inputs!$B$45+Inputs!$B$46))/Inputs!$B$43)*(Inputs!$B$44/Inputs!$B$6)) | J20: =IF(E20="","",IF(G20="AUTO",I20*Inputs!$B$43,H20)) | O20: =IF(OR(E20="",F20=""),"",E20*F20*(1+$U$3*(IF(K20="",0,K20)+IF(L20="",0,L20)))) | P20: =IF(OR(E20="",J20=""),"",E20*J20*(1+IF(L20="",0,L20))) | Q20: =IF(OR(M20="",N20=""),"",M20*N20) | R20: =IF(OR(O20="",P20=""),"",P20-O20-IF(Q20="",0,Q20)) | S20: =IF(E20="","",ROUNDUP(E20/28,0)) | T20: Actual vs Target Rate | U20: =IFERROR(U15-Vendor_Pricing!B7,"") -> -12.550952
A21: 15 | F21: =IF($B21="","",Post_Positions!$C$12) | G21: AUTO | I21: =IF(OR(F21="",F21=0),"",((F21*(1+Inputs!$B$45+Inputs!$B$46))/Inputs!$B$43)*(Inputs!$B$44/Inputs!$B$6)) | J21: =IF(E21="","",IF(G21="AUTO",I21*Inputs!$B$43,H21)) | O21: =IF(OR(E21="",F21=""),"",E21*F21*(1+$U$3*(IF(K21="",0,K21)+IF(L21="",0,L21)))) | P21: =IF(OR(E21="",J21=""),"",E21*J21*(1+IF(L21="",0,L21))) | Q21: =IF(OR(M21="",N21=""),"",M21*N21) | R21: =IF(OR(O21="",P21=""),"",P21-O21-IF(Q21="",0,Q21)) | S21: =IF(E21="","",ROUNDUP(E21/28,0)) | T21: Feed Status | U21: =IF(U5>0,"ACTIVE - pricing tabs linked to Post_Positions","INACTIVE - using manual worksheet inputs") -> ACTIVE - pricing tabs linked to Post_Positions
A22: Totals | E22: =SUBTOTAL(109,_Calc_Backend!$E$7:$E$21) -> 336 | O22: =SUBTOTAL(109,_Calc_Backend!$O$7:$O$21) -> 11336.64 | P22: =SUBTOTAL(109,_Calc_Backend!$P$7:$P$21) -> 21767.76 | Q22: =SUBTOTAL(109,_Calc_Backend!$Q$7:$Q$21) -> 0 | R22: =SUBTOTAL(109,_Calc_Backend!$R$7:$R$21) -> 10431.12 | S22: =SUBTOTAL(109,_Calc_Backend!$S$7:$S$21) -> 12 | T22: Annual Coverage Hours | U22: =X33 -> 3865.12
T23: Weekly Labor Hours | U23: =X36 -> 336
T24: Annual Labor Hours | U24: =X37 -> 17472 | W24: GASQ Scope of Work (Integrated with Post / Positions)
T25: FTEs Required | U25: =X38 -> 12 | W25: Edit scope inputs here; staffing metrics update automatically and remain mirrored on the Scope_of_Work tab.
W26: User Inputs
W27: Hours of Coverage per Day | X27: 8.5
W28: Days of Coverage per Week | X28: 7
W29: Weeks of Coverage | X29: 9.28
W30: Staff per 8-Hour Shift | X30: 7
W32: Calculated Staffing Metrics
W33: Annual Coverage Hours | X33: =X27*X28*X29*X30 -> 3865.12
W34: 8-Hour Shifts per Day | X34: =X27/8 -> 1.0625
W35: Daily Labor Hours | X35: =X27*X30 -> 59.5
W36: Weekly Labor Hours | X36: =IF(_Calc_Backend!$U$5>0,_Calc_Backend!$U$5,X27*X28*X30) -> 336
W37: Annual Labor Hours | X37: =IF(_Calc_Backend!$U$5>0,_Calc_Backend!$U$13,X33) -> 17472
W38: FTEs Required @ Paid Hours Basis | X38: =IFERROR(X37/Inputs!$B$5,0) -> 12
W39: Coverage-to-FTE Ratio | X39: =IFERROR(X37/Inputs!$B$6,0) -> 12
W41: Notes
